Workbook

Sheet SPECIAL REQUEST
A1: Timestamp | B1: Branch | C1: Date | D1: To | E1: Purpose | F1: ITEM_ID | G1: Qty | H1: Unit | I1: Description | J1: UPrice | K1: Amount | L1: Total | M1: Requested By | N1: Status | O1: Release Date | P1: Received By | Q1: PDF URL
A2: 45971.055 | B2: WAREHOUSE | C2: 45971 | D2: PURCHASING OFFICE | E2: SPECIAL REQUEST | G2: 1 | H2: PC | I2: White Board | K2: 0 | L2: 0 | M2: Warehouse | N2: Approved | O2: 45971 | Q2: https://drive.google.com/file/d/1n1A1UTzNz-20b75jH0Y5AdjgSiagG7tA/view?usp=drivesdk
A3: 45973.994 | B3: TUBIGON | C3: 45960 | D3: PURCHASING OFFICE | E3: SPECIAL REQUEST | G3: 1 | H3: PC | I3: Chair | K3: 0 | L3: 0 | M3: TUBIGON | N3: Approved | O3: 45960 | Q3: https://drive.google.com/file/d/1hVy_a7MG8tjKZxKT0hb4MrFaxe_EXCMS/view?usp=drivesdk
A4: 45973.995 | B4: CLARIN | C4: 45960 | D4: PURCHASING OFFICE | E4: SPECIAL REQUEST | G4: 1 | H4: PC | I4: Brother Printer | K4: 0 | L4: 0 | M4: CLARIN | N4: Approved | O4: 45960 | Q4: https://drive.google.com/file/d/1UNkQa3s5U0xyq5xQJ8yCGuy1kqd0pxh4/view?usp=drivesdk
A5: 45973.996 | B5: WAREHOUSE | C5: 45932 | D5: PURCHASING OFFICE | E5: SPECIAL REQUEST | G5: 1 | H5: PC | I5: white board | K5: 0 | L5: 0 | M5: warehouse | N5: Approved | O5: 45932 | P5: Glenn | Q5: https://drive.google.com/file/d/1t6hSLMHJHJ3EI9D7qXWaq3WoO8QkeAFN/view?usp=drivesdk
A6: 45973.997 | B6: BULACAO | C6: 45932 | D6: PURCHASING OFFICE | E6: SPECIAL REQUEST | G6: 1 | H6: PC | I6: Bar Chair | K6: 0 | L6: 0 | M6: Bulacao | N6: Approved | O6: 45932 | Q6: https://drive.google.com/file/d/1Zs7O_1RMhToXNZgm5Fkzv0sn2-ZMRiqe/view?usp=drivesdk
A7: 45973.998 | B7: Y3S TALISAY | C7: 45932 | D7: PURCHASING OFFICE | E7: SPECIAL REQUEST | G7: 1 | H7: PC | I7: Bar Chair | K7: 0 | L7: 0 | M7: Y3S TALISAY | N7: Approved | O7: 45932 | P7: Ariel | Q7: https://drive.google.com/file/d/1C6cKHFFpTBofptivHQJo2g_KGtCnLZpm/view?usp=drivesdk
A8: 45973.999 | B8: BOGO | C8: 45929 | D8: PURCHASING OFFICE | E8: SPECIAL REQUEST | G8: 1 | H8: PC | I8: Money Detector | K8: 0 | L8: 0 | M8: BOGO | N8: Approved | O8: 45929 | P8: Kim | Q8: https://drive.google.com/file/d/1OC9cwNA3u5G8sDESN8z-KVBqWeZzLCeS/view?usp=drivesdk
A9: 45979.643 | B9: MINGLANILLA | C9: 45979 | D9: PURCHASING OFFICE | E9: SPECIAL REQUEST | G9: 1 | H9: BTL | I9: MURIATIC ACID | J9: 43.5 | K9: 43.5 | L9: 43.5 | M9: MINGLANILLA | N9: Approved | O9: 45980 | Q9: https://drive.google.com/file/d/1wZAH1FJD3vE4KRJMmSrNbjuWAYsm8BBn/view?usp=drivesdk
A10: 45982.399 | B10: BARILI MB | C10: 45982 | D10: PURCHASING OFFICE | E10: SPECIAL REQUEST | G10: 1 | I10: MOP | J10: 208 | K10: 208 | L10: 208 | M10: DARYL CLYDE DENILA | N10: Approved | O10: 45993 | Q10: https://drive.google.com/file/d/1nbSNHmGkihPWapA0MUiuJpX3KiA-4YCy/view?usp=drivesdk
A11: 45986.424 | B11: YATI LILOAN | C11: 45986 | D11: PURCHASING OFFICE | E11: SPECIAL REQUEST | G11: 1 | H11: PC | I11: Plastic Expandable Envelope w/ divider long | K11: 0 | L11: 0 | M11: YATI LIOAN | N11: Approved | O11: 45987 | Q11: https://drive.google.com/file/d/1vhjqe399oMgU19G7wyqoqeRaxjM3Dk90/view?usp=drivesdk
A12: 45988.398 | B12: YATI LILOAN | C12: 45982 | D12: PURCHASING OFFICE | E12: SPECIAL REQUEST | G12: 1 | H12: PC | I12: Money Bag (pencil pouch) | J12: 59 | K12: 59 | L12: 59 | M12: YATI LIOAN | N12: Approved | O12: 41238 | Q12: https://drive.google.com/file/d/1hR2FUKT3dZGNRViReU7Y_vDjhyDQVh_u/view?usp=drivesdk
A13: 45988.398 | B13: YATI LILOAN | C13: 45982 | D13: PURCHASING OFFICE | E13: SPECIAL REQUEST | G13: 1 | H13: PC | I13: FILE ORAGANIZER (FOR ACCOUNTANT) (Magazine Case) steel /book shelf | J13: 330 | K13: 330 | L13: 330 | M13: YATI LIOAN | N13: Approved | O13: 41238 | Q13: https://drive.google.com/file/d/1hR2FUKT3dZGNRViReU7Y_vDjhyDQVh_u/view?usp=drivesdk
A14: 45988.478 | B14: SIERRA BULLONES | C14: 45960 | D14: PURCHASING OFFICE | E14: SPECIAL REQUEST | G14: 1 | H14: PC | I14: TAPE DISPENSER | K14: 0 | L14: 0 | M14: SIERRA BULLONES | N14: Approved | O14: 45989 | Q14: https://drive.google.com/file/d/1NfsJh15vZlG7cXylBUF7_QQIkWC2VKVR/view?usp=drivesdk
A15: 45988.479 | B15: BACAYAN | C15: 45964 | D15: PURCHASING OFFICE | E15: SPECIAL REQUEST | G15: 4 | H15: PCS | I15: PUDLOCK | K15: 0 | L15: 0 | M15: BACAYAN | N15: Approved | O15: 41238 | Q15: https://drive.google.com/file/d/1WR-TKZI0MRvQgcBp4u2UJVGfFTytW8A7/view?usp=drivesdk
A16: 45988.482 | B16: BACAYAN | C16: 45979 | D16: PURCHASING OFFICE | E16: SPECIAL REQUEST | G16: 2 | H16: PCS | I16: FEATHER DUSTER | J16: 45 | K16: 45 | L16: 90 | M16: BACAYAN | N16: Approved | O16: 45993 | Q16: https://drive.google.com/file/d/1a0m0GQBXvzGjTO9cXZ54nspGK9BJeeHA/view?usp=drivesdk
A17: 45988.484 | B17: Y3S PARDO | C17: 45971 | D17: PURCHASING OFFICE | E17: SPECIAL REQUEST | G17: 1 | H17: PC | I17: FILER (CASHIER) PAHIGDA (Magazine Case) Steel | J17: 352 | K17: 352 | L17: 352 | M17: Y3S PARDO | N17: Approved | O17: 41238 | Q17: https://drive.google.com/file/d/1ixSV3oaVwGkGFgjhyqR3EI9gwu3yGblo/view?usp=drivesdk
A18: 45988.484 | B18: Y3S PARDO | C18: 45971 | D18: PURCHASING OFFICE | E18: SPECIAL REQUEST | G18: 2 | H18: PCS | I18: FILER ( LOANS) PATINDOG (Magazine Case) Steel /book shelf | J18: 330 | K18: 660 | L18: 660 | M18: Y3S PARDO | N18: Approved | O18: 41238 | Q18: https://drive.google.com/file/d/1ixSV3oaVwGkGFgjhyqR3EI9gwu3yGblo/view?usp=drivesdk
A19: 45988.717 | B19: CARMEN | C19: 45966 | D19: PURCHASING OFFICE | E19: SPECIAL REQUEST | G19: 10 | H19: PCS | I19: EXPANDED ENVELOPE | J19: 14 | K19: 140 | L19: 140 | M19: CARMEN | N19: Approved | O19: 45989 | Q19: https://drive.google.com/file/d/15zAF_9NPmyEz0XHjsK3m-9Hh1_8NMQwd/view?usp=drivesdk
A20: 45989.474 | B20: SIERRA BULLONES | C20: 45989 | D20: PURCHASING OFFICE | E20: SPECIAL REQUEST | G20: 1 | H20: PC | I20: Tool Box | J20: 752 | K20: 752 | L20: 794 | M20: SIERRA BULLONES | N20: Approved | O20: 45989 | Q20: https://drive.google.com/file/d/1xLAWybpV80_o0tMQWMA3dwa3b1YgAmgO/view?usp=drivesdk
A21: 45989.474 | B21: SIERRA BULLONES | C21: 45989 | D21: PURCHASING OFFICE | E21: SPECIAL REQUEST | G21: 1 | H21: PC | I21: ScrewDriver | J21: 42 | K21: 42 | L21: 794 | M21: SIERRA BULLONES | N21: Approved | O21: 45989 | Q21: https://drive.google.com/file/d/1xLAWybpV80_o0tMQWMA3dwa3b1YgAmgO/view?usp=drivesdk
A22: 45989.495 | B22: BULACAO | C22: 45989 | D22: PURCHASING OFFICE | E22: SPECIAL REQUEST | G22: 1 | H22: BLT | I22: MURIATIC ACID | J22: 43.5 | K22: 43.5 | L22: 43.5 | M22: Bulacao | N22: Approved | O22: 45989 | Q22: https://drive.google.com/file/d/1G80ZMCQF6ddiM6DjUhkwJOwCB0IqYwVe/view?usp=drivesdk
A23: 45992.471 | B23: BACAYAN | C23: 45989 | D23: PURCHASING OFFICE | E23: SPECIAL REQUEST | G23: 1 | H23: PC | I23: CUTTER | J23: 15 | K23: 15 | L23: 15 | M23: BACAYAN | N23: Approved | O23: 45993 | Q23: https://drive.google.com/file/d/1Dq22D_ecXUxnQi7dZZM2j57VfO7Xhh0b/view?usp=drivesdk
A24: 45992.471 | B24: BACAYAN | C24: 45989 | D24: PURCHASING OFFICE | E24: SPECIAL REQUEST | G24: 5 | H24: PCS | I24: STICK GLUE | J24: 6 | K24: 6 | L24: 30 | M24: BACAYAN | N24: Approved | O24: 45993 | Q24: https://drive.google.com/file/d/1Dq22D_ecXUxnQi7dZZM2j57VfO7Xhh0b/view?usp=drivesdk
A25: 45993.36 | B25: MINGLANILLA | C25: 45993 | D25: PURCHASING OFFICE | E25: SPECIAL REQUEST | G25: 1 | H25: PC | I25: WHITEBOARD ERASER | K25: 0 | L25: 0 | M25: JENIFE OLIVA | N25: Approved | O25: 45993 | Q25: https://drive.google.com/file/d/1EOv7iZoRSC_RdGptl65i3v_NHv-1l7fZ/view?usp=drivesdk
A26: 45993.686 | B26: Y3S BARILI | C26: 45984 | D26: PURCHASING OFFICE | E26: SPECIAL REQUEST | G26: 2 | H26: PCS | I26: MOP | J26: 208 | K26: 416 | L26: 416 | M26: Y3S BARILI | N26: Approved | O26: 45993 | Q26: https://drive.google.com/file/d/16uNShiAtLgdAoZqCCg4PIOf31sCV3SMQ/view?usp=drivesdk
A27: 45994.398 | B27: ADMIN | C27: 45994 | D27: PURCHASING OFFICE | E27: SPECIAL REQUEST | G27: 100 | H27: PCS | I27: Plastic medium (Para sa Sudlan sa Uniform) white | J27: 86.15 | K27: 86.15 | L27: 86.15 | M27: Ma'am Joy HR | N27: Approved | O27: 45995 | Q27: https://drive.google.com/file/d/1AU9A20MU8m_jfanAGO1iHt41W_Ij16OR/view?usp=drivesdk
A28: 45995.395 | B28: V-RAMA | C28: 45995 | D28: PURCHASING OFFICE | E28: SPECIAL REQUEST | G28: 3 | I28: USB (Cashier, Accountant, Loans) 32G | J28: 250 | K28: 750 | L28: 750 | M28: V-RAMA | N28: Approved | O28: 45995 | Q28: https://drive.google.com/file/d/1P773IJ2I_380ZtYCWyqQI7NCobLYatBl/view?usp=drivesdk
A29: 45995.397 | B29: ADMIN | C29: 45995 | D29: PURCHASING OFFICE | E29: SPECIAL REQUEST | G29: 1 | I29: USB 32G | J29: 250 | K29: 250 | L29: 250 | M29: Accounting Dept. | N29: Approved | O29: 45995 | Q29: https://drive.google.com/file/d/15no4SHnYFGy2LYz6Pic5G_7QhFeLaiNI/view?usp=drivesdk
A30: 45995.546 | B30: LAGTANG | C30: 45995 | D30: PURCHASING OFFICE | E30: SPECIAL REQUEST | G30: 3 | H30: PC | I30: YARN para sa yabe | J30: 8 | K30: 24 | L30: 24 | M30: LAGTANG | N30: Approved | O30: 45995 | Q30: https://drive.google.com/file/d/1pp8v9AvTu6gueoFvoHWD7JMV6snoIUf2/view?usp=drivesdk
A31: 45995.546 | B31: LAGTANG | C31: 45995 | D31: PURCHASING OFFICE | E31: SPECIAL REQUEST | G31: 1 | H31: PC | I31: Pen Holder w/ Divider ( Cashier) | J31: 96 | K31: 96 | L31: 96 | M31: LAGTANG | N31: Approved | O31: 45995 | Q31: https://drive.google.com/file/d/1pp8v9AvTu6gueoFvoHWD7JMV6snoIUf2/view?usp=drivesdk
A32: 46000.637 | B32: LILOAN | C32: 46000 | D32: PURCHASING OFFICE | E32: SPECIAL REQUEST | G32: 2 | H32: PCS | I32: File Rack/Vellum Organizer (Magazine Case) Steel / FILE CASE | J32: 360 | K32: 720 | L32: 720 | M32: LILOAN | N32: Approved | O32: 46000 | Q32: https://drive.google.com/file/d/1jQ6ugMZPD2NH47jGd-rn1YVNNAm-IMVl/view?usp=drivesdk
A33: 46000.692 | B33: TAYUD CONSOLACION | C33: 46000 | D33: PURCHASING OFFICE | E33: SPECIAL REQUEST | G33: 2 | H33: PCS | I33: File Rack/Vellum Organizer (Magazine Case) Steel / FILE CASE | J33: 360 | K33: 720 | L33: 720 | M33: Tayud Consolacion | N33: Approved | O33: 46000 | Q33: https://drive.google.com/file/d/1BNSnqcMFzBXSYQV_kzMp2EQces3ZrNFd/view?usp=drivesdk
A34: 46001.361 | B34: ADMIN | C34: 46001 | D34: PURCHASING OFFICE | E34: SPECIAL REQUEST | G34: 1 | H34: PC | I34: File Rack (Magazine Case) color Red Plastic | J34: 360 | K34: 360 | L34: 360 | M34: Ma'am Madi | N34: Approved | O34: 1/20/26 | Q34: https://drive.google.com/file/d/19wrXXlCRUWOU345j087vlu2tvyCQbSQh/view?usp=drivesdk
A35: 46001.658 | B35: ADMIN | C35: 46001 | D35: PURCHASING OFFICE | E35: SPECIAL REQUEST | G35: 5 | H35: PCS | I35: ID MAKER | J35: 30 | K35: 150 | L35: 150 | M35: IT DEPT | N35: Approved | Q35: https://drive.google.com/file/d/1MnFokygosY1ZTiVGl2k2GWNwT-Y52XY0/view?usp=drivesdk
A36: 46002.381 | B36: YATI LILOAN | C36: 46002 | D36: PURCHASING OFFICE | E36: SPECIAL REQUEST | G36: 5 | H36: PCS | I36: PLACTIC ENVELOPE (THICK) LONG BAGA GYUD | K36: 0 | L36: 0 | M36: YATI LIOAN | N36: Approved | O36: 12/30/25 | Q36: https://drive.google.com/file/d/1Ra0vvLkIPyiJHYnNqTKyaHHI6z5d2zfS/view?usp=drivesdk
A37: 46006.481 | B37: CARMEN | C37: 46006 | D37: PURCHASING OFFICE | E37: SPECIAL REQUEST | G37: 1 | H37: PC | I37: UV LIGHT BULB MONEY DETECTOR (CASHIER) | K37: 0 | L37: 0 | M37: CARMEN | N37: Approved | O37: 12/23/25 | Q37: https://drive.google.com/file/d/11ABwdJLv9fCMtGJ86xl75X8FblG3LE_B/view?usp=drivesdk
A38: 46006.481 | B38: CARMEN | C38: 46006 | D38: PURCHASING OFFICE | E38: SPECIAL REQUEST | G38: 1 | H38: PC | I38: CASH BOX (CASHIER) | J38: 600 | K38: 600 | L38: 600 | M38: CARMEN | N38: To Buy | Q38: https://drive.google.com/file/d/11ABwdJLv9fCMtGJ86xl75X8FblG3LE_B/view?usp=drivesdk
A39: 46006.481 | B39: CARMEN | C39: 46006 | D39: PURCHASING OFFICE | E39: SPECIAL REQUEST | G39: 9 | H39: PCS | I39: DOOR MAT | J39: 35 | K39: 300 | L39: 300 | M39: CARMEN | N39: Approved | O39: 46357 | Q39: https://drive.google.com/file/d/11ABwdJLv9fCMtGJ86xl75X8FblG3LE_B/view?usp=drivesdk
A40: 46006.481 | B40: CARMEN | C40: 46006 | D40: PURCHASING OFFICE | E40: SPECIAL REQUEST | G40: 1 | H40: PC | I40: MORNING EVOTIONAL FOR NEXT YEAR (BISAYA) | K40: 0 | L40: 0 | M40: CARMEN | N40: Approved | O40: 12/23/25 | Q40: https://drive.google.com/file/d/11ABwdJLv9fCMtGJ86xl75X8FblG3LE_B/view?usp=drivesdk
A41: 46015.61 | B41: SIERRA BULLONES | C41: 46014 | D41: PURCHASING OFFICE | E41: SPECIAL REQUEST | G41: 100 | H41: PC | I41: Puched Card / DTR CARD | J41: 400 | K41: 400 | L41: 400 | M41: SIERRA BULLONES | N41: Approved | O41: 46357 | Q41: https://drive.google.com/file/d/1LLYIWJU3zQAGSEHVu29spoWOOqnI9gFI/view?usp=drivesdk
A42: 46015.61 | B42: SIERRA BULLONES | C42: 46014 | D42: PURCHASING OFFICE | E42: SPECIAL REQUEST | G42: 1 | H42: PC | I42: Toilet Brush | J42: 300 | K42: 300 | L42: 300 | M42: SIERRA BULLONES | N42: Petty Cash By Branch | Q42: https://drive.google.com/file/d/1LLYIWJU3zQAGSEHVu29spoWOOqnI9gFI/view?usp=drivesdk
A43: 46015.612 | B43: PITOGO | C43: 46014 | D43: PURCHASING OFFICE | E43: SPECIAL REQUEST | G43: 2 | H43: PC | I43: Book Shelves /File Rack | J43: 400 | K43: 800 | L43: 800 | M43: PITOGO | N43: Approved | O43: 1/20/26 | Q43: https://drive.google.com/file/d/1gErGJFhTBLGKcQqGWVvcs7h_5ccXJIqi/view?usp=drivesdk
A44: 46015.612 | B44: PITOGO | C44: 46014 | D44: PURCHASING OFFICE | E44: SPECIAL REQUEST | G44: 1 | H44: PC | I44: Scissor | K44: 0 | L44: 120 | M44: PITOGO | N44: Approved | O44: 46357 | Q44: https://drive.google.com/file/d/1gErGJFhTBLGKcQqGWVvcs7h_5ccXJIqi/view?usp=drivesdk
A45: 46019.36 | B45: LAGTANG | C45: 46017 | D45: PURCHASING OFFICE | E45: SPECIAL REQUEST | G45: 1 | H45: PC | I45: Transparent Plastic cellophane / Zipper bag | J45: 120 | K45: 120 | L45: 0 | M45: LAGTANG | N45: To Buy | Q45: https://drive.google.com/file/d/1GBYpk7c5Xz3KjGNmiuS8N9iMKNkVkvC_/view?usp=drivesdk
A46: 46021.386 | B46: LILOAN | C46: 46021 | D46: PURCHASING OFFICE | E46: SPECIAL REQUEST | G46: 1 | H46: PC | I46: Tape Dispenser | K46: 0 | L46: 0 | M46: LILOAN | N46: Approved | O46: 46357 | Q46: https://drive.google.com/file/d/1TFdyfaSO46J8L_tfe0vDVW7Ebd5FR9_F/view?usp=drivesdk
A47: 46021.386 | B47: LILOAN | C47: 46021 | D47: PURCHASING OFFICE | E47: SPECIAL REQUEST | G47: 2 | H47: PC | I47: Metal organizer for record book (loans) | J47: 360 | K47: 720 | L47: 720 | M47: LILOAN | N47: Approved | O47: 1/20/26 | Q47: https://drive.google.com/file/d/1TFdyfaSO46J8L_tfe0vDVW7Ebd5FR9_F/view?usp=drivesdk
A48: 46021.388 | B48: Y3S PARDO | C48: 46021 | D48: PURCHASING OFFICE | E48: SPECIAL REQUEST | G48: 3 | H48: PCS | I48: Plastic Envelope w/ String long (loans) For Paper's Pending & Approved | J48: 120 | K48: 360 | L48: 360 | M48: Y3S PARDO | N48: Approved | O48: 1/21/26 | Q48: https://drive.google.com/file/d/1T9q1d4yrYqkIkVgZLXe9MJCw_OEt9V_q/view?usp=drivesdk
A49: 46024.443 | B49: PINAMUNGAJAN | C49: 46024 | D49: PURCHASING OFFICE | E49: SPECIAL REQUEST | G49: 1 | I49: BUDGET FOR RENEWAL OF BUSINESS PERMIT | J49: 10000 | K49: 10000 | L49: 10000 | M49: Renalyn Icalina | N49: Accouting Dept | Q49: https://drive.google.com/file/d/1887rqH4UyW6D6zKZU724OtTbOTFa-EM8/view?usp=drivesdk
A50: 46024.496 | B50: TOLEDO | C50: 46024 | D50: PURCHASING OFFICE | E50: SPECIAL REQUEST | G50: 1 | I50: FOR BUSINESS PERMIT RENEWAL | J50: 10000 | K50: 10000 | L50: 10000 | M50: PRECIOUS BACUS | N50: Accouting Dept | Q50: https://drive.google.com/file/d/1PxqmGTvPDjCBfAecPkdUDMC9qXTRBa_p/view?usp=drivesdk
A51: 46024.516 | B51: V-RAMA | C51: 46024 | D51: PURCHASING OFFICE | E51: SPECIAL REQUEST | G51: 3 | I51: Referral fee | J51: 1000 | K51: 3000 | L51: 3000 | M51: Junalie Narvasa | N51: Accouting Dept | Q51: https://drive.google.com/file/d/1ZxVG3ZbhESqGXf6ZTWAAXpkR_bTlBPT9/view?usp=drivesdk
A52: 46024.648 | B52: YATI LILOAN | C52: 45659 | D52: PURCHASING OFFICE | E52: SPECIAL REQUEST | G52: 3 | H52: Persons | I52: X-RAY | J52: 300 | K52: 900 | L52: 990 | M52: EDGARDO JIMENEZ | N52: Accouting Dept | Q52: https://drive.google.com/file/d/1g0L7_UiFY03MIaC42syCFU_rn0_MuchH/view?usp=drivesdk
A53: 46024.648 | B53: YATI LILOAN | C53: 45659 | D53: PURCHASING OFFICE | E53: SPECIAL REQUEST | G53: 3 | H53: Persons | I53: TRAVEL EXPENSES | J53: 30 | K53: 90 | L53: 990 | M53: EDGARDO JIMENEZ | N53: Accouting Dept | Q53: https://drive.google.com/file/d/1g0L7_UiFY03MIaC42syCFU_rn0_MuchH/view?usp=drivesdk
A54: 46026.371 | B54: V-RAMA | C54: 46026 | D54: PURCHASING OFFICE | E54: SPECIAL REQUEST | G54: 1 | I54: BUDGET FOR BUSINESS PERMIT RENEWAL | J54: 50000 | K54: 50000 | L54: 50000 | M54: NEBRIA, SAMUEL | N54: Accouting Dept | Q54: https://drive.google.com/file/d/1amA9wWHm4833h2bYKIPRPC467QbpE3yG/view?usp=drivesdk
A55: 46026.444 | B55: SAN FERNANDO MB | C55: 46026 | D55: PURCHASING OFFICE | E55: SPECIAL REQUEST | G55: 1 | I55: PCF FOR REPLENISHMENT FOR THE ENDING OF THE MONTH OF DECEMBER 2025. | J55: 1945 | K55: 1945 | L55: 1945 | M55: Francis Bagatua | N55: Accouting Dept | Q55: https://drive.google.com/file/d/1G1ADw31iAdZf_bccIh-A6ayWVbfD0ZPf/view?usp=drivesdk
A56: 46026.471 | B56: SAN FERNANDO MB | C56: 46026 | D56: PURCHASING OFFICE | E56: SPECIAL REQUEST | G56: 1 | I56: REQUEST FOR PAYMENT FOR BUSINESS PERMIT RENEWAL AND OTHER EXPENSES FOR RENEWAL. | J56: 10000 | K56: 10000 | L56: 10000 | M56: Francis Bagatua | N56: Accouting Dept | Q56: https://drive.google.com/file/d/1HD8KLZnSYEFG3I5R825l0lB3F0QBwCGk/view?usp=drivesdk
A57: 46026.549 | B57: TAYUD CONSOLACION | C57: 46026 | D57: PURCHASING OFFICE | E57: SPECIAL REQUEST | G57: 1 | H57: BOX EACH | I57: BUDGET FOR BLUE CORE AND GEAR OIL | J57: 10127 | K57: 10127 | L57: 10127 | M57: AMIT, ANYA FE ESMERO | N57: Accouting Dept | Q57: https://drive.google.com/file/d/1nE-geVIfe5CsuqZ_GlX-kkKgTidCUHqS/view?usp=drivesdk
A58: 46026.569 | B58: UBAY | C58: 46026 | D58: PURCHASING OFFICE | E58: SPECIAL REQUEST | G58: 3 | H58: PCS | I58: OFFICE CHAIR (Accountant, Cashier,Loans) kay platic ra ilang Chair | J58: 2500 | K58: 7500 | L58: 7500 | M58: ROCILO FLORES | N58: To Buy | Q58: https://drive.google.com/file/d/1I7lNXY6NUJiC0ypWwb5t6ZmHoJZ6OAAW/view?usp=drivesdk
A59: 46026.623 | B59: SAN FERNANDO MB | C59: 46026 | D59: PURCHASING OFFICE | E59: SPECIAL REQUEST | G59: 1 | I59: REFERRAL FEE (1 MIO GRAVIS BKV3 ASSUMED FINANCING) | J59: 350 | K59: 350 | L59: 350 | M59: Francis Bagatua | N59: Accouting Dept | Q59: https://drive.google.com/file/d/17hSrl9t6gDeCpteYUYsL4jCszeW7f5Te/view?usp=drivesdk
A60: 46027.377 | B60: Y3S BARILI | C60: 46027 | D60: PURCHASING OFFICE | E60: SPECIAL REQUEST | G60: 1 | I60: BUSINESS PERMIT RENEWAL (ESTIMATION) | J60: 26000 | K60: 26000 | L60: 26000 | M60: Lyneth Bianggos | N60: Accouting Dept | Q60: https://drive.google.com/file/d/1YGemKsdtirZ7OLf5sHg7HRp-b7FfuTzx/view?usp=drivesdk
A61: 46027.511 | B61: Y3S CORDOVA | C61: 46027 | D61: PURCHASING OFFICE | E61: SPECIAL REQUEST | G61: 1 | I61: YAMAHA ACTIVITY FOR JANUARY 17-31,2026 | J61: 8500 | K61: 8500 | L61: 8500 | M61: JERSON C.MARAPO | N61: Accouting Dept | Q61: https://drive.google.com/file/d/15r0yGo1Q6Db5kH0aaAa3NlUsLpYgJdZV/view?usp=drivesdk
A62: 46027.543 | B62: UBAY | C62: 46361 | D62: PURCHASING OFFICE | E62: SPECIAL REQUEST | G62: 1 | I62: RENEWAL OF BUSINESS PERMIT | J62: 23000 | K62: 23000 | L62: 23000 | M62: ROCILO FLORES | N62: Accouting Dept | Q62: https://drive.google.com/file/d/12obOOVDuuq_5MUoTmMacPSdrqkKKzLXX/view?usp=drivesdk
A63: 46027.555 | B63: Y3S TALISAY | C63: 46027 | D63: PURCHASING OFFICE | E63: SPECIAL REQUEST | G63: 2 | I63: Referral Fee | J63: 1000 | K63: 2000 | L63: 2000 | M63: FLORENDO, ELLEN G. | N63: Accouting Dept | Q63: https://drive.google.com/file/d/1t7BpztNV6Vgs9BBOoHNpWnvIlA9_9Hx9/view?usp=drivesdk
A64: 46027.579 | B64: TUBIGON | C64: 46027 | D64: PURCHASING OFFICE | E64: SPECIAL REQUEST | G64: 1 | I64: Renewal of business permit | J64: 23000 | K64: 23000 | L64: 23000 | M64: Neil Ray L. Saludes | N64: Accouting Dept | Q64: https://drive.google.com/file/d/1624Xjau33nTf1kbh3grBYjM1GpbxwF9p/view?usp=drivesdk
A65: 46027.582 | B65: Y3S TALISAY | C65: 46027 | D65: PURCHASING OFFICE | E65: SPECIAL REQUEST | G65: 2 | I65: REFERRAL FEE | J65: 1000 | K65: 2000 | L65: 2000 | M65: FLORENDO, ELLEN G. | N65: Accouting Dept | Q65: https://drive.google.com/file/d/1Iozj6Vnu5er2rXvRAnfNXlUoJ-hgs3hM/view?usp=drivesdk
A66: 46027.615 | B66: BOGO | C66: 46027 | D66: PURCHASING OFFICE | E66: SPECIAL REQUEST | G66: 1 | I66: KAWIT SATELLITE RENTAL FOR JANUARY 2026 | J66: 3500 | K66: 3500 | L66: 3500 | M66: EDA TEROL | N66: Accouting Dept | Q66: https://drive.google.com/file/d/1Sxdx4WDDxdtbn67qJlT9HS5Y0VfbxEsg/view?usp=drivesdk
A67: 46027.748 | B67: BALAMBAN | C67: 46027 | D67: PURCHASING OFFICE | E67: SPECIAL REQUEST | G67: 1 | H67: 15000 | I67: BUSINESS PERMIT RENEWAL | J67: 15000 | K67: 15000 | L67: 15000 | M67: JOHN ROGER MONTERO | N67: Accouting Dept | Q67: https://drive.google.com/file/d/1btuT-Tc_KM99AndkViCVCxzZvf4chwsm/view?usp=drivesdk
A68: 46027.756 | B68: BALAMBAN | C68: 46027 | D68: PURCHASING OFFICE | E68: SPECIAL REQUEST | G68: 96 | H68: 4 BOXES | I68: BLUE CORE | J68: 345 | K68: 33120 | L68: 41760 | M68: JOHN ROGER MONTERO | N68: Accouting Dept | Q68: https://drive.google.com/file/d/12eLHreIoXawl3pOrji-zdEMyIKs6v36X/view?usp=drivesdk
A69: 46027.756 | B69: BALAMBAN | C69: 46027 | D69: PURCHASING OFFICE | E69: SPECIAL REQUEST | G69: 144 | H69: 4 BOXES | I69: GEAR OIL | J69: 60 | K69: 8640 | L69: 41760 | M69: JOHN ROGER MONTERO | N69: Accouting Dept | Q69: https://drive.google.com/file/d/12eLHreIoXawl3pOrji-zdEMyIKs6v36X/view?usp=drivesdk
A70: 46028.396 | B70: Y3S PARDO | C70: 46028 | D70: PURCHASING OFFICE | E70: SPECIAL REQUEST | G70: 1 | I70: RENEWAL FOR SERVICE | J70: 500 | K70: 500 | L70: 500 | M70: MERY APLE M. PORMENTO | N70: Petty Cash By Branch | Q70: https://drive.google.com/file/d/1A4q6vgivmIC-0lE9o0U37bLrRsF8QshJ/view?usp=drivesdk
A71: 46028.4 | B71: YATI LILOAN | C71: 46028 | D71: PURCHASING OFFICE | E71: SPECIAL REQUEST | G71: 1 | I71: BPLO - ASSESSMENT | J71: 9595 | K71: 9595 | L71: 11175 | M71: EDGARDO JIMENEZ | N71: Accouting Dept | Q71: https://drive.google.com/file/d/1fqMlnfyIxt0w0fQaBG-F62tJIVgVnswt/view?usp=drivesdk
A72: 46028.4 | B72: YATI LILOAN | C72: 46028 | D72: PURCHASING OFFICE | E72: SPECIAL REQUEST | G72: 1 | I72: MENRO - GREENING | J72: 1250 | K72: 1250 | L72: 11175 | M72: EDGARDO JIMENEZ | N72: Accouting Dept | Q72: https://drive.google.com/file/d/1fqMlnfyIxt0w0fQaBG-F62tJIVgVnswt/view?usp=drivesdk
A73: 46028.4 | B73: YATI LILOAN | C73: 46028 | D73: PURCHASING OFFICE | E73: SPECIAL REQUEST | G73: 1 | I73: BARANGAY BUSINESS CLEARANCE | J73: 330 | K73: 330 | L73: 11175 | M73: EDGARDO JIMENEZ | N73: Accouting Dept | Q73: https://drive.google.com/file/d/1fqMlnfyIxt0w0fQaBG-F62tJIVgVnswt/view?usp=drivesdk
A74: 46028.4 | B74: V-RAMA | C74: 46028 | D74: PURCHASING OFFICE | E74: SPECIAL REQUEST | G74: 1 | I74: REFERRAL FEE | J74: 1000 | K74: 1000 | L74: 1000 | M74: NEBRIA, SAMUEL | N74: Accouting Dept | Q74: https://drive.google.com/file/d/10MxLKcf_L26uQWjenmftQAvwAiU9jmB4/view?usp=drivesdk
A75: 46028.413 | B75: BACAYAN | C75: 46028 | D75: PURCHASING OFFICE | E75: SPECIAL REQUEST | G75: 1 | I75: BARANGAY CLEARANCE | J75: 2030 | K75: 2030 | L75: 26778 | M75: ODTOHAN, RICHARD | N75: Accouting Dept | Q75: https://drive.google.com/file/d/1HRzDvtRVCzoKL_g8lE9z1gSFeBqwDrWy/view?usp=drivesdk
A76: 46028.413 | B76: BACAYAN | C76: 46028 | D76: PURCHASING OFFICE | E76: SPECIAL REQUEST | G76: 1 | I76: FOR RENEWAL | J76: 24748 | K76: 24748 | L76: 26778 | M76: ODTOHAN, RICHARD | N76: Accouting Dept | Q76: https://drive.google.com/file/d/1HRzDvtRVCzoKL_g8lE9z1gSFeBqwDrWy/view?usp=drivesdk
A77: 46028.453 | B77: Y3S SAN FERNANDO | C77: 46028 | D77: PURCHASING OFFICE | E77: SPECIAL REQUEST | G77: 1 | I77: REQUEST BUDGET FOR BUSINESS PERMIT RENEWAL | J77: 35000 | K77: 35000 | L77: 35000 | M77: JAMES GENON | N77: Accouting Dept | Q77: https://drive.google.com/file/d/1C9S5uf0-oJ2ig4KaW8WQpQOY4ID4dsnF/view?usp=drivesdk
A78: 46028.678 | B78: Y3S TALISAY | C78: 46028 | D78: PURCHASING OFFICE | E78: SPECIAL REQUEST | G78: 1 | I78: WHEELS FOR COMPANY SERVICE | J78: 2875 | K78: 2875 | L78: 2875 | M78: LETECIA DALIMET | N78: Accouting Dept | Q78: https://drive.google.com/file/d/1BumVHrd7nT5npbDrEQDYyQcIYD1x2kjY/view?usp=drivesdk
A79: 46028.684 | B79: Y3S BARILI | C79: 46028 | D79: PURCHASING OFFICE | E79: SPECIAL REQUEST | G79: 1 | I79: PAYMENT FOR TAX FOR THE YEAR 2025-2026 | J79: 70805 | K79: 70805 | L79: 70805 | M79: LYNETH M BIANGGOS | N79: Accouting Dept | Q79: https://drive.google.com/file/d/1xg67yXEqbXXsgmzYlTg_Mn4k68qjsSu3/view?usp=drivesdk
A80: 46028.72 | B80: PINAMUNGAJAN | C80: 46028 | D80: PURCHASING OFFICE | E80: SPECIAL REQUEST | G80: 1 | I80: MAINIT, JOHN LEE ( EMARIE, EKS) | J80: 1000 | K80: 1000 | L80: 2000 | M80: CELLON, GLADESE P. | N80: Accouting Dept | Q80: https://drive.google.com/file/d/1pIoyxNdcW4lPF4UUqm_JYQNjRmYww7jh/view?usp=drivesdk
A81: 46028.72 | B81: PINAMUNGAJAN | C81: 46028 | D81: PURCHASING OFFICE | E81: SPECIAL REQUEST | G81: 1 | I81: TEJANA JEPHUNNEH L. (HIJAPON, MARILYN) | J81: 1000 | K81: 1000 | L81: 2000 | M81: CELLON, GLADESE P. | N81: Accouting Dept | Q81: https://drive.google.com/file/d/1pIoyxNdcW4lPF4UUqm_JYQNjRmYww7jh/view?usp=drivesdk
... A83: 46029.36 | B83: BULACAO | C83: 46029 | D83: PURCHASING OFFICE | E83: SPECIAL REQUEST | G83: 1 | I83: MONITOR | J83: 6345 | K83: 6345 | L83: 6345 | M83: IVY L HAMISTOSO | N83: Accouting Dept | Q83: https://drive.google.com/file/d/1ZYe5-6wO7FzaxyEMmgn5vbSKxv4_gPVg/view?usp=drivesdk
A84: 46029.36 | B84: BULACAO | C84: 46029 | D84: PURCHASING OFFICE | E84: SPECIAL REQUEST | G84: 1 | I84: KEYBOARD | K84: 0 | L84: 6345 | M84: IVY L HAMISTOSO | N84: Accouting Dept | Q84: https://drive.google.com/file/d/1ZYe5-6wO7FzaxyEMmgn5vbSKxv4_gPVg/view?usp=drivesdk
A85: 46029.366 | B85: CARMEN | C85: 46029 | D85: PURCHASING OFFICE | E85: SPECIAL REQUEST | G85: 1 | I85: BUSINESS PERMIT BUDGET | J85: 28000 | K85: 28000 | L85: 28000 | M85: JANRIEL ORJALIZA | N85: Accouting Dept | Q85: https://drive.google.com/file/d/123TKmqp2xeZ-WQclIyLPeaAP2z-q4PQq/view?usp=drivesdk
A86: 46029.369 | B86: TALIBON | C86: 46029 | D86: PURCHASING OFFICE | E86: SPECIAL REQUEST | G86: 1 | I86: Budget for business permit renewal | J86: 22000 | K86: 22000 | L86: 22000 | M86: Danilo T. Boligor Jr. | N86: Accouting Dept | Q86: https://drive.google.com/file/d/1uOo6OyThdqMWLlut5ihdsotmRfLvfbEc/view?usp=drivesdk
A87: 46029.382 | B87: TAYUD CONSOLACION | C87: 46029 | D87: PURCHASING OFFICE | E87: SPECIAL REQUEST | G87: 6 | I87: REFERRAL FEE | J87: 1000 | K87: 6000 | L87: 6000 | M87: AMIT, ANYA FE ESMERO | N87: Accouting Dept | Q87: https://drive.google.com/file/d/1Yld_qqQpktlt8uwdO9eTWaX-jChXDCzv/view?usp=drivesdk
A88: 46029.406 | B88: SAN FERNANDO MB | C88: 46029 | D88: PURCHASING OFFICE | E88: SPECIAL REQUEST | G88: 1 | I88: REQUEST FOR PAYMENT FOR BUSINESS PERMIT RENEWAL. | J88: 20000 | K88: 20000 | L88: 20000 | M88: Francis Bagatua | N88: Accouting Dept | Q88: https://drive.google.com/file/d/16iE4rysY5LSL0qz_ke3z9t7QFWE9t4Cr/view?usp=drivesdk
A89: 46029.424 | B89: Y3S TALISAY | C89: 46007 | D89: PURCHASING OFFICE | E89: SPECIAL REQUEST | G89: 1 | H89: PC | I89: Stapler Big for Parts with Staple wire | J89: 500 | K89: 500 | L89: 500 | M89: Y3S Talisay | N89: To Buy | Q89: https://drive.google.com/file/d/1UWjX79xM0MXNd2f86TbSqg525MobFS9d/view?usp=drivesdk
A90: 46029.454 | B90: Y3S CORDOVA | C90: 46029 | D90: PURCHASING OFFICE | E90: SPECIAL REQUEST | G90: 1 | I90: business permit/xray/drugtest/fire | J90: 36437 | K90: 36437 | L90: 36437 | M90: JERSON C.MARAPO | N90: Accouting Dept | Q90: https://drive.google.com/file/d/1h5nz6Zvf-n020t-4gWyWIUkuWudNvqH-/view?usp=drivesdk
A91: 46029.463 | B91: TOLEDO | C91: 46029 | D91: PURCHASING OFFICE | E91: SPECIAL REQUEST | G91: 24 | H91: pcs | I91: SUPREME OIL | J91: 335 | K91: 8040 | L91: 22320 | M91: CHRISTIAN BEJIC | N91: Accouting Dept | Q91: https://drive.google.com/file/d/1Y68g1TIYfWRik7XyPEKsQz1EFu8JSuqu/view?usp=drivesdk
A92: 46029.463 | B92: TOLEDO | C92: 46029 | D92: PURCHASING OFFICE | E92: SPECIAL REQUEST | G92: 24 | H92: pcs | I92: BLUE CORE OIL | J92: 345 | K92: 8280 | L92: 22320 | M92: CHRISTIAN BEJIC | N92: Accouting Dept | Q92: https://drive.google.com/file/d/1Y68g1TIYfWRik7XyPEKsQz1EFu8JSuqu/view?usp=drivesdk
A93: 46029.463 | B93: TOLEDO | C93: 46029 | D93: PURCHASING OFFICE | E93: SPECIAL REQUEST | G93: 24 | H93: pcs | I93: PERFORMANCE OIL | J93: 250 | K93: 6000 | L93: 22320 | M93: CHRISTIAN BEJIC | N93: Accouting Dept | Q93: https://drive.google.com/file/d/1Y68g1TIYfWRik7XyPEKsQz1EFu8JSuqu/view?usp=drivesdk
A94: 46029.544 | B94: CLARIN | C94: 46029 | D94: PURCHASING OFFICE | E94: SPECIAL REQUEST | G94: 1 | I94: MAYORS PERMIT | J94: 37382 | K94: 37382 | L94: 41592 | M94: SHYREL BRUCE D. LAMORIN | N94: Accouting Dept | Q94: https://drive.google.com/file/d/1dD3U7HeIk7Db_3A2q7lxwfYT6Mz1DYXX/view?usp=drivesdk
A95: 46029.544 | B95: CLARIN | C95: 46029 | D95: PURCHASING OFFICE | E95: SPECIAL REQUEST | G95: 1 | I95: BARANGAY CLEARANCE | J95: 1200 | K95: 1200 | L95: 41592 | M95: SHYREL BRUCE D. LAMORIN | N95: Accouting Dept | Q95: https://drive.google.com/file/d/1dD3U7HeIk7Db_3A2q7lxwfYT6Mz1DYXX/view?usp=drivesdk
A96: 46029.544 | B96: CLARIN | C96: 46029 | D96: PURCHASING OFFICE | E96: SPECIAL REQUEST | G96: 1 | I96: XRAY | J96: 1775 | K96: 1775 | L96: 41592 | M96: SHYREL BRUCE D. LAMORIN | N96: Accouting Dept | Q96: https://drive.google.com/file/d/1dD3U7HeIk7Db_3A2q7lxwfYT6Mz1DYXX/view?usp=drivesdk
A97: 46029.544 | B97: CLARIN | C97: 46029 | D97: PURCHASING OFFICE | E97: SPECIAL REQUEST | G97: 1 | I97: FIRE(BFP) | J97: 1235 | K97: 1235 | L97: 41592 | M97: SHYREL BRUCE D. LAMORIN | N97: Accouting Dept | Q97: https://drive.google.com/file/d/1dD3U7HeIk7Db_3A2q7lxwfYT6Mz1DYXX/view?usp=drivesdk
A98: 46029.6 | B98: LILOAN | C98: 46029 | D98: PURCHASING OFFICE | E98: SPECIAL REQUEST | G98: 1 | I98: ESPINOSA, DENNIS | J98: 1000 | K98: 1000 | L98: 6000 | M98: CUESTAS, JERSON T. | N98: Accouting Dept | Q98: https://drive.google.com/file/d/1OefUVUY3BylL1qB3zk63iZR3gYAIgiBf/view?usp=drivesdk
A99: 46029.6 | B99: LILOAN | C99: 46029 | D99: PURCHASING OFFICE | E99: SPECIAL REQUEST | G99: 1 | I99: TECSON, RANDY M. | J99: 1000 | K99: 1000 | L99: 6000 | M99: CUESTAS, JERSON T. | N99: Accouting Dept | Q99: https://drive.google.com/file/d/1OefUVUY3BylL1qB3zk63iZR3gYAIgiBf/view?usp=drivesdk
A100: 46029.6 | B100: LILOAN | C100: 46029 | D100: PURCHASING OFFICE | E100: SPECIAL REQUEST | G100: 1 | I100: DECHOS, CASHELLE ANNE G. | J100: 1000 | K100: 1000 | L100: 6000 | M100: CUESTAS, JERSON T. | N100: Accouting Dept | Q100: https://drive.google.com/file/d/1OefUVUY3BylL1qB3zk63iZR3gYAIgiBf/view?usp=drivesdk
A101: 46029.6 | B101: LILOAN | C101: 46029 | D101: PURCHASING OFFICE | E101: SPECIAL REQUEST | G101: 1 | I101: OLAYBAR, DEITHER | J101: 1000 | K101: 1000 | L101: 6000 | M101: CUESTAS, JERSON T. | N101: Accouting Dept | Q101: https://drive.google.com/file/d/1OefUVUY3BylL1qB3zk63iZR3gYAIgiBf/view?usp=drivesdk
...

Sheet Accouting Dept

Sheet To Buy

Sheet BRANCH LIST
A1: Branch_ID | B1: Branch | C1: Email
A2: AD001 | B2: ADMIN | C2: gmpcpurchasing@gmail.com
A3: WH002 | B3: WAREHOUSE | C3: warehousegiant21@gmail.com
A4: BR001 | B4: LAGTANG | C4: giantmotoprolagtang@gmail.com
A5: BR002 | B5: V-RAMA | C5: gmpcguad_accounting@yahoo.com.ph
A6: BR003 | B6: BULACAO | C6: ivyhamistoso@gmail.com
A7: BR004 | B7: Y3S TALISAY | C7: gmpcyamaha3st@gmail.com
A8: BR005 | B8: MINGLANILLA | C8: giantmotoprolinao@gmail.com
A9: BR006 | B9: Y3S PARDO | C9: gmpcy3spardo@yahoo.com
A10: BR007 | B10: LAPU-LAPU | C10: giantmotoproopon19@gmail.com
A11: BR008 | B11: BACAYAN | C11: gmpcbacayan@gmail.com
A12: BR009 | B12: SAN FERNANDO MB | C12: gmpcsanfernando@gmail.com
... A32: BR029 | B32: YATI LILOAN | C32: gmpcyatililoan@gmail.com
A33: BR030 | B33: CAMOTES

Sheet SUMMARY
A1: Branch | B1: ITEM_ID | C1: Description | D1: Total Qty | E1: Total Amount | F1: Timestamp
A2: =IFERROR(__xludf.DUMMYFUNCTION("ARRAYFORMULA( QUERY( { IFERROR(FILTER(ADMIN!B:B, ADMIN!N:N=""Approved"")), IFERROR(FILTER(ADMIN!F:F, ADMIN!N:N=""Approved"")), IFERROR(FILTER(ADMIN!I:I, ADMIN!N:N=""Approved"")), IFERROR(FILTER(ADMIN!G:G, ADMIN!N:N=""Approved"&""")), IFERROR(FILTER(ADMIN!K:K, ADMIN!N:N=""Approved"")); IFERROR(FILTER(WAREHOUSE!B:B, WAREHOUSE!N:N=""Approved"")), IFERROR(FILTER(WAREHOUSE!F:F, WAREHOUSE!N:N=""Approved"")), IFERROR(FILTER(WAREHOUSE!I:I, WAREHOUSE!N:N="""&"Approved"")), IFERROR(FILTER(WAREHOUSE!G:G, WAREHOUSE!N:N=""Approved"")), IFERROR(FILTER(WAREHOUSE!K:K, WAREHOUSE!N:N=""Approved"")); IFERROR(FILTER(LAGTANG!B:B, LAGTANG!N:N=""Approved"")), IFERROR(FILTER(LAGTANG!F:F, LAGTAN"&"G!N:N=""Approved"")), IFERROR(FILTER(LAGTANG!I:I, LAGTANG!N:N=""Approved"")), IFERROR(FILTER(LAGTANG!G:G, LAGTANG!N:N=""Approved"")), IFERROR(FILTER(LAGTANG!K:K, LAGTANG!N:N=""Approved"")); IFERROR(FILTER('V-RAMA'!B:B, 'V-RA"&"MA'!N:N=""Approved"")), IFERROR(FILTER('V-RAMA'!F:F, 'V-RAMA'!N:N=""Approved"")), IFERROR(FILTER('V-RAMA'!I:I, 'V-RAMA'!N:N=""Approved"")), IFERROR(FILTER('V-RAMA'!G:G, 'V-RAMA'!N:N=""Approved"")), IFERROR(FILTER('V-RAMA'!K:K, 'V-R"&"AMA'!N:N=""Approved"")); IFERROR(FILTER(BULACAO!B:B, BULACAO!N:N=""Approved"")), IFERROR(FILTER(BULACAO!F:F, BULACAO!N:N=""Approved"")), IFERROR(FILTER(BULACAO!I:I, BULACAO!N:N=""Approved"")), IFERROR(FILTER(BULACAO!G:G, BUL"&"ACAO!N:N=""Approved"")), IFERROR(FILTER(BULACAO!K:K, BULACAO!N:N=""Approved"")); IFERROR(FILTER('Y3S TALISAY'!B:B, 'Y3S TALISAY'!N:N=""Approved"")), IFERROR(FILTER('Y3S TALISAY'!F:F, 'Y3S TALISAY'!N:N=""Approved"")), IFERROR"&"(FILTER('Y3S TALISAY'!I:I, 'Y3S TALISAY'!N:N=""Approved"")), IFERROR(FILTER('Y3S TALISAY'!G:G, 'Y3S TALISAY'!N:N=""Approved"")), IFERROR(FILTER('Y3S TALISAY'!K:K, 'Y3S TALISAY'!N:N=""Approved"")); IFERROR(FILTER(MINGLANILLA!B:B, M"&"INGLANILLA!N:N=""Approved"")), IFERROR(FILTER(MINGLANILLA!F:F, MINGLANILLA!N:N=""Approved"")), IFERROR(FILTER(MINGLANILLA!I:I, MINGLANILLA!N:N=""Approved"")), IFERROR(FILTER(MINGLANILLA!G:G, MINGLANILLA!N:N=""Approved"")), IFERROR("&"FILTER(MINGLANILLA!K:K, MINGLANILLA!N:N=""Approved"")); IFERROR(FILTER('Y3S PARDO'!B:B, 'Y3S PARDO'!N:N=""Approved"")), IFERROR(FILTER('Y3S PARDO'!F:F, 'Y3S PARDO'!N:N=""Approved"")), IFERROR(FILTER('Y3S PARDO'!I:I, 'Y3S PARDO'!N:"&"N=""Approved"")), IFERROR(FILTER('Y3S PARDO'!G:G, 'Y3S PARDO'!N:N=""Approved"")), IFERROR(FILTER('Y3S PARDO'!K:K, 'Y3S PARDO'!N:N=""Approved"")); IFERROR(FILTER('LAPU-LAPU'!B:B, 'LAPU-LAPU'!N:N=""Approved"")), IFERROR(FILTER"&"('LAPU-LAPU'!F:F, 'LAPU-LAPU'!N:N=""Approved"")), IFERROR(FILTER('LAPU-LAPU'!I:I, 'LAPU-LAPU'!N:N=""Approved"")), IFERROR(FILTER('LAPU-LAPU'!G:G, 'LAPU-LAPU'!N:N=""Approved"")), IFERROR(FILTER('LAPU-LAPU'!K:K, 'LAPU-LAPU'!N:N=""Approved"&""")); IFERROR(FILTER(BACAYAN!B:B, BACAYAN!N:N=""Approved"")), IFERROR(FILTER(BACAYAN!F:F, BACAYAN!N:N=""Approved"")), IFERROR(FILTER(BACAYAN!I:I, BACAYAN!N:N=""Approved"")), IFERROR(FILTER(BACAYAN!G:G, BACAYAN!N:N=""Approved"&""")), IFERROR(FILTER(BACAYAN!K:K, BACAYAN!N:N=""Approved"")); IFERROR(FILTER('SAN FERNANDO MB'!B:B, 'SAN FERNANDO MB'!N:N=""Approved"")), IFERROR(FILTER('SAN FERNANDO MB'!F:F, 'SAN FERNANDO MB'!N:N=""Approved"")), IFERROR(FI"&"LTER('SAN FERNANDO MB'!I:I, 'SAN FERNANDO MB'!N:N=""Approved"")), IFERROR(FILTER('SAN FERNANDO MB'!G:G, 'SAN FERNANDO MB'!N:N=""Approved"")), IFERROR(FILTER('SAN FERNANDO MB'!K:K, 'SAN FERNANDO MB'!N:N=""Approved"")); IFERROR(FILT"&"ER('Y3S SAN FERNANDO'!B:B, 'Y3S SAN FERNANDO'!N:N=""Approved"")), IFERROR(FILTER('Y3S SAN FERNANDO'!F:F, 'Y3S SAN FERNANDO'!N:N=""Approved"")), IFERROR(FILTER('Y3S SAN FERNANDO'!I:I, 'Y3S SAN FERNANDO'!N:N=""Approved"")), IFERROR(FILTER("&"'Y3S SAN FERNANDO'!G:G, 'Y3S SAN FERNANDO'!N:N=""Approved"")), IFERROR(FILTER('Y3S SAN FERNANDO'!K:K, 'Y3S SAN FERNANDO'!N:N=""Approved"")); IFERROR(FILTER(LILOAN!B:B, LILOAN!N:N=""Approved"")), IFERROR(FILTER(LILOAN!F:F, LILOAN!N"&":N=""Approved"")), IFERROR(FILTER(LILOAN!I:I, LILOAN!N:N=""Approved"")), IFERROR(FILTER(LILOAN!G:G, LILOAN!N:N=""Approved"")), IFERROR(FILTER(LILOAN!K:K, LILOAN!N:N=""Approved"")); IFERROR(FILTER('CORDOVA MB'!B:B, 'CORDOVA M"&"B'!N:N=""Approved"")), IFERROR(FILTER('CORDOVA MB'!F:F, 'CORDOVA MB'!N:N=""Approved"")), IFERROR(FILTER('CORDOVA MB'!I:I, 'CORDOVA MB'!N:N=""Approved"")), IFERROR(FILTER('CORDOVA MB'!G:G, 'CORDOVA MB'!N:N=""Approved"")), IFERROR(FI"&"LTER('CORDOVA MB'!K:K, 'CORDOVA MB'!N:N=""Approved"")); IFERROR(FILTER('Y3S CORDOVA'!B:B, 'Y3S CORDOVA'!N:N=""Approved"")), IFERROR(FILTER('Y3S CORDOVA'!F:F, 'Y3S CORDOVA'!N:N=""Approved"")), IFERROR(FILTER('Y3S CORDOVA'!I:I, 'Y3S"&" CORDOVA'!N:N=""Approved"")), IFERROR(FILTER('Y3S CORDOVA'!G:G, 'Y3S CORDOVA'!N:N=""Approved"")), IFERROR(FILTER('Y3S CORDOVA'!K:K, 'Y3S CORDOVA'!N:N=""Approved"")); IFERROR(FILTER(CLARIN!B:B, CLARIN!N:N=""Approved"")), IFER"&"ROR(FILTER(CLARIN!F:F, CLARIN!N:N=""Approved"")), IFERROR(FILTER(CLARIN!I:I, CLARIN!N:N=""Approved"")), IFERROR(FILTER(CLARIN!G:G, CLARIN!N:N=""Approved"")), IFERROR(FILTER(CLARIN!K:K, CLARIN!N:N=""Approved"")); IFERROR(FILT"&"ER(TOLEDO!B:B, TOLEDO!N:N=""Approved"")), IFERROR(FILTER(TOLEDO!F:F, TOLEDO!N:N=""Approved"")), IFERROR(FILTER(TOLEDO!I:I, TOLEDO!N:N=""Approved"")), IFERROR(FILTER(TOLEDO!G:G, TOLEDO!N:N=""Approved"")), IFERROR(FILTER(TOLEDO!K:K, "&"TOLEDO!N:N=""Approved"")); IFERROR(FILTER(UBAY!B:B, UBAY!N:N=""Approved"")), IFERROR(FILTER(UBAY!F:F, UBAY!N:N=""Approved"")), IFERROR(FILTER(UBAY!I:I, UBAY!N:N=""Approved"")), IFERROR(FILTER(UBAY!G:G, UBAY!N:N=""Approved"")"&"), IFERROR(FILTER(UBAY!K:K, UBAY!N:N=""Approved"")); IFERROR(FILTER(CARMEN!B:B, CARMEN!N:N=""Approved"")), IFERROR(FILTER(CARMEN!F:F, CARMEN!N:N=""Approved"")), IFERROR(FILTER(CARMEN!I:I, CARMEN!N:N=""Approved"")), IFE"&"RROR(FILTER(CARMEN!G:G, CARMEN!N:N=""Approved"")), IFERROR(FILTER(CARMEN!K:K, CARMEN!N:N=""Approved"")); IFERROR(FILTER(TUBIGON!B:B, TUBIGON!N:N=""Approved"")), IFERROR(FILTER(TUBIGON!F:F, TUBIGON!N:N=""Approved"")), IFERROR"&"(FILTER(TUBIGON!I:I, TUBIGON!N:N=""Approved"")), IFERROR(FILTER(TUBIGON!G:G, TUBIGON!N:N=""Approved"")), IFERROR(FILTER(TUBIGON!K:K, TUBIGON!N:N=""Approved"")); IFERROR(FILTER(TALIBON!B:B, TALIBON!N:N=""Approved"")), IFERROR"&"(FILTER(TALIBON!F:F, TALIBON!N:N=""Approved"")), IFERROR(FILTER(TALIBON!I:I, TALIBON!N:N=""Approved"")), IFERROR(FILTER(TALIBON!G:G, TALIBON!N:N=""Approved"")), IFERROR(FILTER(TALIBON!K:K, TALIBON!N:N=""Approved"")); IFERROR"&"(FILTER(BOGO!B:B, BOGO!N:N=""Approved"")), IFERROR(FILTER(BOGO!F:F, BOGO!N:N=""Approved"")), IFERROR(FILTER(BOGO!I:I, BOGO!N:N=""Approved"")), IFERROR(FILTER(BOGO!G:G, BOGO!N:N=""Approved"")), IFERROR(FILTER(BOGO!K:K, BOGO!N:N=""Ap"&"proved"")); IFERROR(FILTER(BALAMBAN!B:B, BALAMBAN!N:N=""Approved"")), IFERROR(FILTER(BALAMBAN!F:F, BALAMBAN!N:N=""Approved"")), IFERROR(FILTER(BALAMBAN!I:I, BALAMBAN!N:N=""Approved"")), IFERROR(FILTER(BALAMBAN!G:G, BALAMBAN!"&"N:N=""Approved"")), IFERROR(FILTER(BALAMBAN!K:K, BALAMBAN!N:N=""Approved"")); IFERROR(FILTER('Y3S BARILI'!B:B, 'Y3S BARILI'!N:N=""Approved"")), IFERROR(FILTER('Y3S BARILI'!F:F, 'Y3S BARILI'!N:N=""Approved"")), IFERROR(FILTER"&"('Y3S BARILI'!I:I, 'Y3S BARILI'!N:N=""Approved"")), IFERROR(FILTER('Y3S BARILI'!G:G, 'Y3S BARILI'!N:N=""Approved"")), IFERROR(FILTER('Y3S BARILI'!K:K, 'Y3S BARILI'!N:N=""Approved"")); IFERROR(FILTER('BARILI MB'!B:B, 'BARILI MB'!N:"&"N=""Approved"")), IFERROR(FILTER('BARILI MB'!F:F, 'BARILI MB'!N:N=""Approved"")), IFERROR(FILTER('BARILI MB'!I:I, 'BARILI MB'!N:N=""Approved"")), IFERROR(FILTER('BARILI MB'!G:G, 'BARILI MB'!N:N=""Approved"")), IFERROR(FILTER('BARIL"&"I MB'!K:K, 'BARILI MB'!N:N=""Approved"")); IFERROR(FILTER('SIERRA BULLONES'!B:B, 'SIERRA BULLONES'!N:N=""Approved"")), IFERROR(FILTER('SIERRA BULLONES'!F:F, 'SIERRA BULLONES'!N:N=""Approved"")), IFERROR(FILTER('SIERRA BULLONES'!I:"&"I, 'SIERRA BULLONES'!N:N=""Approved"")), IFERROR(FILTER('SIERRA BULLONES'!G:G, 'SIERRA BULLONES'!N:N=""Approved"")), IFERROR(FILTER('SIERRA BULLONES'!K:K, 'SIERRA BULLONES'!N:N=""Approved"")); IFERROR(FILTER(PITOGO!B:B, PITOGO!N:N"&"=""Approved"")), IFERROR(FILTER(PITOGO!F:F, PITOGO!N:N=""Approved"")), IFERROR(FILTER(PITOGO!I:I, PITOGO!N:N=""Approved"")), IFERROR(FILTER(PITOGO!G:G, PITOGO!N:N=""Approved"")), IFERROR(FILTER(PITOGO!K:K, PITOGO!N:N=""Approved""))"&"; IFERROR(FILTER('TAYUD CONSOLACION'!B:B, 'TAYUD CONSOLACION'!N:N=""Approved"")), IFERROR(FILTER('TAYUD CONSOLACION'!F:F, 'TAYUD CONSOLACION'!N:N=""Approved"")), IFERROR(FILTER('TAYUD CONSOLACION'!I:I, 'TAYUD CONSOLACION'!N:N=""Ap"&"proved"")), IFERROR(FILTER('TAYUD CONSOLACION'!G:G, 'TAYUD CONSOLACION'!N:N=""Approved"")), IFERROR(FILTER('TAYUD CONSOLACION'!K:K, 'TAYUD CONSOLACION'!N:N=""Approved"")); IFERROR(FILTER(PINAMUNGAJAN!B:B, PINAMUNGAJAN!N:N=""Approv"&"ed"")), IFERROR(FILTER(PINAMUNGAJAN!F:F, PINAMUNGAJAN!N:N=""Approved"")), IFERROR(FILTER(PINAMUNGAJAN!I:I, PINAMUNGAJAN!N:N=""Approved"")), IFERROR(FILTER(PINAMUNGAJAN!G:G, PINAMUNGAJAN!N:N=""Approved"")), IFERROR(FILTER(PINAMUNGAJ"&"AN!K:K, PINAMUNGAJAN!N:N=""Approved"")); IFERROR(FILTER(CANDIJAY!B:B, CANDIJAY!N:N=""Approved"")), IFERROR(FILTER(CANDIJAY!F:F, CANDIJAY!N:N=""Approved"")), IFERROR(FILTER(CANDIJAY!I:I, CANDIJAY!N:N=""Approved"")), IFERROR(F"&"ILTER(CANDIJAY!G:G, CANDIJAY!N:N=""Approved"")), IFERROR(FILTER(CANDIJAY!K:K, CANDIJAY!N:N=""Approved"")); IFERROR(FILTER('YATI LILOAN'!B:B, 'YATI LILOAN'!N:N=""Approved"")), IFERROR(FILTER('YATI LILOAN'!F:F, 'YATI LILOAN'!N:N=""A"&"pproved"")), IFERROR(FILTER('YATI LILOAN'!I:I, 'YATI LILOAN'!N:N=""Approved"")), IFERROR(FILTER('YATI LILOAN'!G:G, 'YATI LILOAN'!N:N=""Approved"")), IFERROR(FILTER('YATI LILOAN'!K:K, 'YATI LILOAN'!N:N=""Approved"")); IFERROR("&"FILTER(CAMOTES!B:B, CAMOTES!N:N=""Approved"")), IFERROR(FILTER(CAMOTES!F:F, CAMOTES!N:N=""Approved"")), IFERROR(FILTER(CAMOTES!I:I, CAMOTES!N:N=""Approved"")), IFERROR(FILTER(CAMOTES!G:G, CAMOTES!N:N=""Approved"")), IFERROR(FILTER("&"CAMOTES!K:K, CAMOTES!N:N=""Approved"")) }, ""select * where Col1 is not null"" ) )"),"ADMIN") -> ADMIN | B2: =IFERROR(__xludf.DUMMYFUNCTION("""COMPUTED_VALUE"""),"ITM007") -> ITM007 | C2: =IFERROR(__xludf.DUMMYFUNCTION("""COMPUTED_VALUE"""),"LOGBOOK VALIANT RECORD (150 & 300P PAGES)") -> LOGBOOK VALIANT RECORD (150 & 300P PAGES) | D2: =IFERROR(__xludf.DUMMYFUNCTION("""COMPUTED_VALUE"""),1.0) -> 1 | E2: =IFERROR(__xludf.DUMMYFUNCTION("""COMPUTED_VALUE"""),0.0) -> 0
A3: =IFERROR(__xludf.DUMMYFUNCTION("""COMPUTED_VALUE"""),"ADMIN") -> ADMIN | B3: =IFERROR(__xludf.DUMMYFUNCTION("""COMPUTED_VALUE"""),"ITM003") -> ITM003 | C3: =IFERROR(__xludf.DUMMYFUNCTION("""COMPUTED_VALUE"""),"BOND PAPER A4") -> BOND PAPER A4 | D3: =IFERROR(__xludf.DUMMYFUNCTION("""COMPUTED_VALUE"""),1.0) -> 1 | E3: =IFERROR(__xludf.DUMMYFUNCTION("""COMPUTED_VALUE"""),0.0) -> 0
A4: =IFERROR(__xludf.DUMMYFUNCTION("""COMPUTED_VALUE"""),"ADMIN") -> ADMIN | B4: =IFERROR(__xludf.DUMMYFUNCTION("""COMPUTED_VALUE"""),"ITM001") -> ITM001 | C4: =IFERROR(__xludf.DUMMYFUNCTION("""COMPUTED_VALUE"""),"BOND PAPER (LONG)") -> BOND PAPER (LONG) | D4: =IFERROR(__xludf.DUMMYFUNCTION("""COMPUTED_VALUE"""),1.0) -> 1 | E4: =IFERROR(__xludf.DUMMYFUNCTION("""COMPUTED_VALUE"""),0.0) -> 0
A5: =IFERROR(__xludf.DUMMYFUNCTION("""COMPUTED_VALUE"""),"ADMIN") -> ADMIN | B5: =IFERROR(__xludf.DUMMYFUNCTION("""COMPUTED_VALUE"""),"ITM023") -> ITM023 | C5: =IFERROR(__xludf.DUMMYFUNCTION("""COMPUTED_VALUE"""),"HIGHLIGHTER") -> HIGHLIGHTER | D5: =IFERROR(__xludf.DUMMYFUNCTION("""COMPUTED_VALUE"""),1.0) -> 1 | E5: =IFERROR(__xludf.DUMMYFUNCTION("""COMPUTED_VALUE"""),0.0) -> 0
A6: =IFERROR(__xludf.DUMMYFUNCTION("""COMPUTED_VALUE"""),"ADMIN") -> ADMIN | B6: =IFERROR(__xludf.DUMMYFUNCTION("""COMPUTED_VALUE"""),"ITM002") -> ITM002 | C6: =IFERROR(__xludf.DUMMYFUNCTION("""COMPUTED_VALUE"""),"BOND PAPER (SHORT)") -> BOND PAPER (SHORT) | D6: =IFERROR(__xludf.DUMMYFUNCTION("""COMPUTED_VALUE"""),1.0) -> 1 | E6: =IFERROR(__xludf.DUMMYFUNCTION("""COMPUTED_VALUE"""),0.0) -> 0
A7: =IFERROR(__xludf.DUMMYFUNCTION("""COMPUTED_VALUE"""),"ADMIN") -> ADMIN | B7: =IFERROR(__xludf.DUMMYFUNCTION("""COMPUTED_VALUE"""),"ITM031") -> ITM031 | C7: =IFERROR(__xludf.DUMMYFUNCTION("""COMPUTED_VALUE"""),"SCISSORS") -> SCISSORS | D7: =IFERROR(__xludf.DUMMYFUNCTION("""COMPUTED_VALUE"""),1.0) -> 1 | E7: =IFERROR(__xludf.DUMMYFUNCTION("""COMPUTED_VALUE"""),0.0) -> 0
A8: =IFERROR(__xludf.DUMMYFUNCTION("""COMPUTED_VALUE"""),"ADMIN") -> ADMIN | B8: =IFERROR(__xludf.DUMMYFUNCTION("""COMPUTED_VALUE"""),"ITM027") -> ITM027 | C8: =IFERROR(__xludf.DUMMYFUNCTION("""COMPUTED_VALUE"""),"CORRECTION TAPE") -> CORRECTION TAPE | D8: =IFERROR(__xludf.DUMMYFUNCTION("""COMPUTED_VALUE"""),1.0) -> 1 | E8: =IFERROR(__xludf.DUMMYFUNCTION("""COMPUTED_VALUE"""),0.0) -> 0
A9: =IFERROR(__xludf.DUMMYFUNCTION("""COMPUTED_VALUE"""),"ADMIN") -> ADMIN | B9: =IFERROR(__xludf.DUMMYFUNCTION("""COMPUTED_VALUE"""),"ITM019") -> ITM019 | C9: =IFERROR(__xludf.DUMMYFUNCTION("""COMPUTED_VALUE"""),"FLEXSTICK BLACK BALLPEN (0.5)") -> FLEXSTICK BLACK BALLPEN (0.5) | D9: =IFERROR(__xludf.DUMMYFUNCTION("""COMPUTED_VALUE"""),1.0) -> 1 | E9: =IFERROR(__xludf.DUMMYFUNCTION("""COMPUTED_VALUE"""),0.0) -> 0
A10: =IFERROR(__xludf.DUMMYFUNCTION("""COMPUTED_VALUE"""),"ADMIN") -> ADMIN | B10: =IFERROR(__xludf.DUMMYFUNCTION("""COMPUTED_VALUE"""),"ITM020") -> ITM020 | C10: =IFERROR(__xludf.DUMMYFUNCTION("""COMPUTED_VALUE"""),"FLEXSTICK RED BALLPEN (0.5)") -> FLEXSTICK RED BALLPEN (0.5) | D10: =IFERROR(__xludf.DUMMYFUNCTION("""COMPUTED_VALUE"""),1.0) -> 1 | E10: =IFERROR(__xludf.DUMMYFUNCTION("""COMPUTED_VALUE"""),0.0) -> 0
A11: =IFERROR(__xludf.DUMMYFUNCTION("""COMPUTED_VALUE"""),"ADMIN") -> ADMIN | B11: =IFERROR(__xludf.DUMMYFUNCTION("""COMPUTED_VALUE"""),"ITM031") -> ITM031 | C11: =IFERROR(__xludf.DUMMYFUNCTION("""COMPUTED_VALUE"""),"SCISSORS") -> SCISSORS | D11: =IFERROR(__xludf.DUMMYFUNCTION("""COMPUTED_VALUE"""),1.0) -> 1 | E11: =IFERROR(__xludf.DUMMYFUNCTION("""COMPUTED_VALUE"""),0.0) -> 0
A12: =IFERROR(__xludf.DUMMYFUNCTION("""COMPUTED_VALUE"""),"ADMIN") -> ADMIN | B12: =IFERROR(__xludf.DUMMYFUNCTION("""COMPUTED_VALUE"""),"ITM034") -> ITM034 | C12: =IFERROR(__xludf.DUMMYFUNCTION("""COMPUTED_VALUE"""),"CALCULATOR MX-12B") -> CALCULATOR MX-12B | D12: =IFERROR(__xludf.DUMMYFUNCTION("""COMPUTED_VALUE"""),1.0) -> 1 | E12: =IFERROR(__xludf.DUMMYFUNCTION("""COMPUTED_VALUE"""),0.0) -> 0
A13: =IFERROR(__xludf.DUMMYFUNCTION("""COMPUTED_VALUE"""),"ADMIN") -> ADMIN | B13: =IFERROR(__xludf.DUMMYFUNCTION("""COMPUTED_VALUE"""),"ITM074") -> ITM074 | C13: =IFERROR(__xludf.DUMMYFUNCTION("""COMPUTED_VALUE"""),"STAPLE WIRE #35") -> STAPLE WIRE #35 | D13: =IFERROR(__xludf.DUMMYFUNCTION("""COMPUTED_VALUE"""),1.0) -> 1 | E13: =IFERROR(__xludf.DUMMYFUNCTION("""COMPUTED_VALUE"""),0.0) -> 0
A14: =IFERROR(__xludf.DUMMYFUNCTION("""COMPUTED_VALUE"""),"ADMIN") -> ADMIN | B14: =IFERROR(__xludf.DUMMYFUNCTION("""COMPUTED_VALUE"""),"ITM030") -> ITM030 | C14: =IFERROR(__xludf.DUMMYFUNCTION("""COMPUTED_VALUE"""),"STAPLER") -> STAPLER | D14: =IFERROR(__xludf.DUMMYFUNCTION("""COMPUTED_VALUE"""),1.0) -> 1 | E14: =IFERROR(__xludf.DUMMYFUNCTION("""COMPUTED_VALUE"""),0.0) -> 0
A15: =IFERROR(__xludf.DUMMYFUNCTION("""COMPUTED_VALUE"""),"ADMIN") -> ADMIN | B15: =IFERROR(__xludf.DUMMYFUNCTION("""COMPUTED_VALUE"""),"ITM002") -> ITM002 | C15: =IFERROR(__xludf.DUMMYFUNCTION("""COMPUTED_VALUE"""),"BOND PAPER (SHORT)") -> BOND PAPER (SHORT) | D15: =IFERROR(__xludf.DUMMYFUNCTION("""COMPUTED_VALUE"""),1.0) -> 1 | E15: =IFERROR(__xludf.DUMMYFUNCTION("""COMPUTED_VALUE"""),0.0) -> 0
A16: =IFERROR(__xludf.DUMMYFUNCTION("""COMPUTED_VALUE"""),"ADMIN") -> ADMIN | B16: =IFERROR(__xludf.DUMMYFUNCTION("""COMPUTED_VALUE"""),"ITM004") -> ITM004 | C16: =IFERROR(__xludf.DUMMYFUNCTION("""COMPUTED_VALUE"""),"BOND PAPER NEWSPRINT (SHORT)") -> BOND PAPER NEWSPRINT (SHORT) | D16: =IFERROR(__xludf.DUMMYFUNCTION("""COMPUTED_VALUE"""),1.0) -> 1 | E16: =IFERROR(__xludf.DUMMYFUNCTION("""COMPUTED_VALUE"""),0.0) -> 0
A17: =IFERROR(__xludf.DUMMYFUNCTION("""COMPUTED_VALUE"""),"ADMIN") -> ADMIN | B17: =IFERROR(__xludf.DUMMYFUNCTION("""COMPUTED_VALUE"""),"ITM093") -> ITM093 | C17: =IFERROR(__xludf.DUMMYFUNCTION("""COMPUTED_VALUE"""),"TRASH BAG (XXL)") -> TRASH BAG (XXL) | D17: =IFERROR(__xludf.DUMMYFUNCTION("""COMPUTED_VALUE"""),1.0) -> 1 | E17: =IFERROR(__xludf.DUMMYFUNCTION("""COMPUTED_VALUE"""),0.0) -> 0
A18: =IFERROR(__xludf.DUMMYFUNCTION("""COMPUTED_VALUE"""),"ADMIN") -> ADMIN | B18: =IFERROR(__xludf.DUMMYFUNCTION("""COMPUTED_VALUE"""),"ITM095") -> ITM095 | C18: =IFERROR(__xludf.DUMMYFUNCTION("""COMPUTED_VALUE"""),"TRASH BAG (LARGE)") -> TRASH BAG (LARGE) | D18: =IFERROR(__xludf.DUMMYFUNCTION("""COMPUTED_VALUE"""),1.0) -> 1 | E18: =IFERROR(__xludf.DUMMYFUNCTION("""COMPUTED_VALUE"""),0.0) -> 0
A19: =IFERROR(__xludf.DUMMYFUNCTION("""COMPUTED_VALUE"""),"WAREHOUSE") -> WAREHOUSE | B19: =IFERROR(__xludf.DUMMYFUNCTION("""COMPUTED_VALUE"""),"ITM038") -> ITM038 | C19: =IFERROR(__xludf.DUMMYFUNCTION("""COMPUTED_VALUE"""),"MASKING TAPE") -> MASKING TAPE | D19: =IFERROR(__xludf.DUMMYFUNCTION("""COMPUTED_VALUE"""),3.0) -> 3 | E19: =IFERROR(__xludf.DUMMYFUNCTION("""COMPUTED_VALUE"""),0.0) -> 0
A20: =IFERROR(__xludf.DUMMYFUNCTION("""COMPUTED_VALUE"""),"WAREHOUSE") -> WAREHOUSE | B20: =IFERROR(__xludf.DUMMYFUNCTION("""COMPUTED_VALUE"""),"ITM056") -> ITM056 | C20: =IFERROR(__xludf.DUMMYFUNCTION("""COMPUTED_VALUE"""),"PRIDE SOAP POWDER") -> PRIDE SOAP POWDER | D20: =IFERROR(__xludf.DUMMYFUNCTION("""COMPUTED_VALUE"""),10.0) -> 10 | E20: =IFERROR(__xludf.DUMMYFUNCTION("""COMPUTED_VALUE"""),0.0) -> 0
A21: =IFERROR(__xludf.DUMMYFUNCTION("""COMPUTED_VALUE"""),"WAREHOUSE") -> WAREHOUSE | B21: =IFERROR(__xludf.DUMMYFUNCTION("""COMPUTED_VALUE"""),"ITM061") -> ITM061 | C21: =IFERROR(__xludf.DUMMYFUNCTION("""COMPUTED_VALUE"""),"JOY") -> JOY | D21: =IFERROR(__xludf.DUMMYFUNCTION("""COMPUTED_VALUE"""),3.0) -> 3 | E21: =IFERROR(__xludf.DUMMYFUNCTION("""COMPUTED_VALUE"""),0.0) -> 0
A22: =IFERROR(__xludf.DUMMYFUNCTION("""COMPUTED_VALUE"""),"WAREHOUSE") -> WAREHOUSE | B22: =IFERROR(__xludf.DUMMYFUNCTION("""COMPUTED_VALUE"""),"ITM002") -> ITM002 | C22: =IFERROR(__xludf.DUMMYFUNCTION("""COMPUTED_VALUE"""),"BOND PAPER (SHORT)") -> BOND PAPER (SHORT) | D22: =IFERROR(__xludf.DUMMYFUNCTION("""COMPUTED_VALUE"""),1.0) -> 1 | E22: =IFERROR(__xludf.DUMMYFUNCTION("""COMPUTED_VALUE"""),0.0) -> 0
A23: =IFERROR(__xludf.DUMMYFUNCTION("""COMPUTED_VALUE"""),"WAREHOUSE") -> WAREHOUSE | B23: =IFERROR(__xludf.DUMMYFUNCTION("""COMPUTED_VALUE"""),"ITM092") -> ITM092 | C23: =IFERROR(__xludf.DUMMYFUNCTION("""COMPUTED_VALUE"""),"RAGS") -> RAGS | D23: =IFERROR(__xludf.DUMMYFUNCTION("""COMPUTED_VALUE"""),1.0) -> 1 | E23: =IFERROR(__xludf.DUMMYFUNCTION("""COMPUTED_VALUE"""),0.0) -> 0
A24: =IFERROR(__xludf.DUMMYFUNCTION("""COMPUTED_VALUE"""),"WAREHOUSE") -> WAREHOUSE | B24: =IFERROR(__xludf.DUMMYFUNCTION("""COMPUTED_VALUE"""),"ITM079") -> ITM079 | C24: =IFERROR(__xludf.DUMMYFUNCTION("""COMPUTED_VALUE"""),"DRINKING CUPS") -> DRINKING CUPS | D24: =IFERROR(__xludf.DUMMYFUNCTION("""COMPUTED_VALUE"""),1.0) -> 1 | E24: =IFERROR(__xludf.DUMMYFUNCTION("""COMPUTED_VALUE"""),0.0) -> 0
A25: =IFERROR(__xludf.DUMMYFUNCTION("""COMPUTED_VALUE"""),"LAGTANG") -> LAGTANG | B25: =IFERROR(__xludf.DUMMYFUNCTION("""COMPUTED_VALUE"""),"ITM002") -> ITM002 | C25: =IFERROR(__xludf.DUMMYFUNCTION("""COMPUTED_VALUE"""),"BOND PAPER (SHORT)") -> BOND PAPER (SHORT) | D25: =IFERROR(__xludf.DUMMYFUNCTION("""COMPUTED_VALUE"""),1.0) -> 1 | E25: =IFERROR(__xludf.DUMMYFUNCTION("""COMPUTED_VALUE"""),0.0) -> 0
A26: =IFERROR(__xludf.DUMMYFUNCTION("""COMPUTED_VALUE"""),"LAGTANG") -> LAGTANG | B26: =IFERROR(__xludf.DUMMYFUNCTION("""COMPUTED_VALUE"""),"ITM012") -> ITM012 | C26: =IFERROR(__xludf.DUMMYFUNCTION("""COMPUTED_VALUE"""),"BROWN FOLDER (LONG)") -> BROWN FOLDER (LONG) | D26: =IFERROR(__xludf.DUMMYFUNCTION("""COMPUTED_VALUE"""),20.0) -> 20 | E26: =IFERROR(__xludf.DUMMYFUNCTION("""COMPUTED_VALUE"""),0.0) -> 0
A27: =IFERROR(__xludf.DUMMYFUNCTION("""COMPUTED_VALUE"""),"LAGTANG") -> LAGTANG | B27: =IFERROR(__xludf.DUMMYFUNCTION("""COMPUTED_VALUE"""),"ITM027") -> ITM027 | C27: =IFERROR(__xludf.DUMMYFUNCTION("""COMPUTED_VALUE"""),"CORRECTION TAPE") -> CORRECTION TAPE | D27: =IFERROR(__xludf.DUMMYFUNCTION("""COMPUTED_VALUE"""),2.0) -> 2 | E27: =IFERROR(__xludf.DUMMYFUNCTION("""COMPUTED_VALUE"""),0.0) -> 0
A28: =IFERROR(__xludf.DUMMYFUNCTION("""COMPUTED_VALUE"""),"LAGTANG") -> LAGTANG | B28: =IFERROR(__xludf.DUMMYFUNCTION("""COMPUTED_VALUE"""),"ITM062") -> ITM062 | C28: =IFERROR(__xludf.DUMMYFUNCTION("""COMPUTED_VALUE"""),"DOWNY") -> DOWNY | D28: =IFERROR(__xludf.DUMMYFUNCTION("""COMPUTED_VALUE"""),3.0) -> 3 | E28: =IFERROR(__xludf.DUMMYFUNCTION("""COMPUTED_VALUE"""),0.0) -> 0
A29: =IFERROR(__xludf.DUMMYFUNCTION("""COMPUTED_VALUE"""),"LAGTANG") -> LAGTANG | B29: =IFERROR(__xludf.DUMMYFUNCTION("""COMPUTED_VALUE"""),"ITM020") -> ITM020 | C29: =IFERROR(__xludf.DUMMYFUNCTION("""COMPUTED_VALUE"""),"FLEXSTICK RED BALLPEN (0.5)") -> FLEXSTICK RED BALLPEN (0.5) | D29: =IFERROR(__xludf.DUMMYFUNCTION("""COMPUTED_VALUE"""),5.0) -> 5 | E29: =IFERROR(__xludf.DUMMYFUNCTION("""COMPUTED_VALUE"""),0.0) -> 0
A30: =IFERROR(__xludf.DUMMYFUNCTION("""COMPUTED_VALUE"""),"LAGTANG") -> LAGTANG | B30: =IFERROR(__xludf.DUMMYFUNCTION("""COMPUTED_VALUE"""),"ITM023") -> ITM023 | C30: =IFERROR(__xludf.DUMMYFUNCTION("""COMPUTED_VALUE"""),"HIGHLIGHTER") -> HIGHLIGHTER | D30: =IFERROR(__xludf.DUMMYFUNCTION("""COMPUTED_VALUE"""),1.0) -> 1 | E30: =IFERROR(__xludf.DUMMYFUNCTION("""COMPUTED_VALUE"""),0.0) -> 0
A31: =IFERROR(__xludf.DUMMYFUNCTION("""COMPUTED_VALUE"""),"LAGTANG") -> LAGTANG | B31: =IFERROR(__xludf.DUMMYFUNCTION("""COMPUTED_VALUE"""),"ITM061") -> ITM061 | C31: =IFERROR(__xludf.DUMMYFUNCTION("""COMPUTED_VALUE"""),"JOY") -> JOY | D31: =IFERROR(__xludf.DUMMYFUNCTION("""COMPUTED_VALUE"""),3.0) -> 3 | E31: =IFERROR(__xludf.DUMMYFUNCTION("""COMPUTED_VALUE"""),0.0) -> 0
A32: =IFERROR(__xludf.DUMMYFUNCTION("""COMPUTED_VALUE"""),"LAGTANG") -> LAGTANG | B32: =IFERROR(__xludf.DUMMYFUNCTION("""COMPUTED_VALUE"""),"ITM038") -> ITM038 | C32: =IFERROR(__xludf.DUMMYFUNCTION("""COMPUTED_VALUE"""),"MASKING TAPE") -> MASKING TAPE | D32: =IFERROR(__xludf.DUMMYFUNCTION("""COMPUTED_VALUE"""),1.0) -> 1 | E32: =IFERROR(__xludf.DUMMYFUNCTION("""COMPUTED_VALUE"""),0.0) -> 0
A33: =IFERROR(__xludf.DUMMYFUNCTION("""COMPUTED_VALUE"""),"LAGTANG") -> LAGTANG | B33: =IFERROR(__xludf.DUMMYFUNCTION("""COMPUTED_VALUE"""),"ITM056") -> ITM056 | C33: =IFERROR(__xludf.DUMMYFUNCTION("""COMPUTED_VALUE"""),"PRIDE SOAP POWDER") -> PRIDE SOAP POWDER | D33: =IFERROR(__xludf.DUMMYFUNCTION("""COMPUTED_VALUE"""),6.0) -> 6 | E33: =IFERROR(__xludf.DUMMYFUNCTION("""COMPUTED_VALUE"""),0.0) -> 0
A34: =IFERROR(__xludf.DUMMYFUNCTION("""COMPUTED_VALUE"""),"LAGTANG") -> LAGTANG | B34: =IFERROR(__xludf.DUMMYFUNCTION("""COMPUTED_VALUE"""),"ITM063") -> ITM063 | C34: =IFERROR(__xludf.DUMMYFUNCTION("""COMPUTED_VALUE"""),"SAFEGUARD SOAP") -> SAFEGUARD SOAP | D34: =IFERROR(__xludf.DUMMYFUNCTION("""COMPUTED_VALUE"""),1.0) -> 1 | E34: =IFERROR(__xludf.DUMMYFUNCTION("""COMPUTED_VALUE"""),0.0) -> 0
A35: =IFERROR(__xludf.DUMMYFUNCTION("""COMPUTED_VALUE"""),"LAGTANG") -> LAGTANG | B35: =IFERROR(__xludf.DUMMYFUNCTION("""COMPUTED_VALUE"""),"ITM064") -> ITM064 | C35: =IFERROR(__xludf.DUMMYFUNCTION("""COMPUTED_VALUE"""),"STICKY NOTES 2X2 A02") -> STICKY NOTES 2X2 A02 | D35: =IFERROR(__xludf.DUMMYFUNCTION("""COMPUTED_VALUE"""),1.0) -> 1 | E35: =IFERROR(__xludf.DUMMYFUNCTION("""COMPUTED_VALUE"""),0.0) -> 0
A36: =IFERROR(__xludf.DUMMYFUNCTION("""COMPUTED_VALUE"""),"LAGTANG") -> LAGTANG | B36: =IFERROR(__xludf.DUMMYFUNCTION("""COMPUTED_VALUE"""),"ITM096") -> ITM096 | C36: =IFERROR(__xludf.DUMMYFUNCTION("""COMPUTED_VALUE"""),"TRASH BAG (MEDIUM)") -> TRASH BAG (MEDIUM) | D36: =IFERROR(__xludf.DUMMYFUNCTION("""COMPUTED_VALUE"""),1.0) -> 1 | E36: =IFERROR(__xludf.DUMMYFUNCTION("""COMPUTED_VALUE"""),0.0) -> 0
A37: =IFERROR(__xludf.DUMMYFUNCTION("""COMPUTED_VALUE"""),"LAGTANG") -> LAGTANG | B37: =IFERROR(__xludf.DUMMYFUNCTION("""COMPUTED_VALUE"""),"ITM006") -> ITM006 | C37: =IFERROR(__xludf.DUMMYFUNCTION("""COMPUTED_VALUE"""),"VELLUM PAPER") -> VELLUM PAPER | D37: =IFERROR(__xludf.DUMMYFUNCTION("""COMPUTED_VALUE"""),20.0) -> 20 | E37: =IFERROR(__xludf.DUMMYFUNCTION("""COMPUTED_VALUE"""),0.0) -> 0
A38: =IFERROR(__xludf.DUMMYFUNCTION("""COMPUTED_VALUE"""),"LAGTANG") -> LAGTANG | B38: =IFERROR(__xludf.DUMMYFUNCTION("""COMPUTED_VALUE"""),"ITM089") -> ITM089 | C38: =IFERROR(__xludf.DUMMYFUNCTION("""COMPUTED_VALUE"""),"ZONROX (COLORSAFE)") -> ZONROX (COLORSAFE) | D38: =IFERROR(__xludf.DUMMYFUNCTION("""COMPUTED_VALUE"""),1.0) -> 1 | E38: =IFERROR(__xludf.DUMMYFUNCTION("""COMPUTED_VALUE"""),0.0) -> 0
A39: =IFERROR(__xludf.DUMMYFUNCTION("""COMPUTED_VALUE"""),"LAGTANG") -> LAGTANG | B39: =IFERROR(__xludf.DUMMYFUNCTION("""COMPUTED_VALUE"""),"ITM003") -> ITM003 | C39: =IFERROR(__xludf.DUMMYFUNCTION("""COMPUTED_VALUE"""),"BOND PAPER A4") -> BOND PAPER A4 | D39: =IFERROR(__xludf.DUMMYFUNCTION("""COMPUTED_VALUE"""),1.0) -> 1 | E39: =IFERROR(__xludf.DUMMYFUNCTION("""COMPUTED_VALUE"""),0.0) -> 0
A40: =IFERROR(__xludf.DUMMYFUNCTION("""COMPUTED_VALUE"""),"LAGTANG") -> LAGTANG | B40: =IFERROR(__xludf.DUMMYFUNCTION("""COMPUTED_VALUE"""),"ITM010") -> ITM010 | C40: =IFERROR(__xludf.DUMMYFUNCTION("""COMPUTED_VALUE"""),"BROWN ENVELOPE (LONG)") -> BROWN ENVELOPE (LONG) | D40: =IFERROR(__xludf.DUMMYFUNCTION("""COMPUTED_VALUE"""),5.0) -> 5 | E40: =IFERROR(__xludf.DUMMYFUNCTION("""COMPUTED_VALUE"""),0.0) -> 0
A41: =IFERROR(__xludf.DUMMYFUNCTION("""COMPUTED_VALUE"""),"LAGTANG") -> LAGTANG | B41: =IFERROR(__xludf.DUMMYFUNCTION("""COMPUTED_VALUE"""),"ITM011") -> ITM011 | C41: =IFERROR(__xludf.DUMMYFUNCTION("""COMPUTED_VALUE"""),"BROWN ENVELOPE (SHORT)") -> BROWN ENVELOPE (SHORT) | D41: =IFERROR(__xludf.DUMMYFUNCTION("""COMPUTED_VALUE"""),5.0) -> 5 | E41: =IFERROR(__xludf.DUMMYFUNCTION("""COMPUTED_VALUE"""),0.0) -> 0
A42: =IFERROR(__xludf.DUMMYFUNCTION("""COMPUTED_VALUE"""),"LAGTANG") -> LAGTANG | B42: =IFERROR(__xludf.DUMMYFUNCTION("""COMPUTED_VALUE"""),"ITM019") -> ITM019 | C42: =IFERROR(__xludf.DUMMYFUNCTION("""COMPUTED_VALUE"""),"FLEXSTICK BLACK BALLPEN (0.5)") -> FLEXSTICK BLACK BALLPEN (0.5) | D42: =IFERROR(__xludf.DUMMYFUNCTION("""COMPUTED_VALUE"""),6.0) -> 6 | E42: =IFERROR(__xludf.DUMMYFUNCTION("""COMPUTED_VALUE"""),0.0) -> 0
A43: =IFERROR(__xludf.DUMMYFUNCTION("""COMPUTED_VALUE"""),"LAGTANG") -> LAGTANG | B43: =IFERROR(__xludf.DUMMYFUNCTION("""COMPUTED_VALUE"""),"ITM006") -> ITM006 | C43: =IFERROR(__xludf.DUMMYFUNCTION("""COMPUTED_VALUE"""),"VELLUM PAPER") -> VELLUM PAPER | D43: =IFERROR(__xludf.DUMMYFUNCTION("""COMPUTED_VALUE"""),25.0) -> 25 | E43: =IFERROR(__xludf.DUMMYFUNCTION("""COMPUTED_VALUE"""),0.0) -> 0
A44: =IFERROR(__xludf.DUMMYFUNCTION("""COMPUTED_VALUE"""),"LAGTANG") -> LAGTANG | B44: =IFERROR(__xludf.DUMMYFUNCTION("""COMPUTED_VALUE"""),"ITM015") -> ITM015 | C44: =IFERROR(__xludf.DUMMYFUNCTION("""COMPUTED_VALUE"""),"WHITE FOLDER (SHORT)") -> WHITE FOLDER (SHORT) | D44: =IFERROR(__xludf.DUMMYFUNCTION("""COMPUTED_VALUE"""),5.0) -> 5 | E44: =IFERROR(__xludf.DUMMYFUNCTION("""COMPUTED_VALUE"""),0.0) -> 0
A45: =IFERROR(__xludf.DUMMYFUNCTION("""COMPUTED_VALUE"""),"V-RAMA") -> V-RAMA | B45: =IFERROR(__xludf.DUMMYFUNCTION("""COMPUTED_VALUE"""),"ITM072") -> ITM072 | C45: =IFERROR(__xludf.DUMMYFUNCTION("""COMPUTED_VALUE"""),"BINDER CLIPS 1 1/4 32MM") -> BINDER CLIPS 1 1/4 32MM | D45: =IFERROR(__xludf.DUMMYFUNCTION("""COMPUTED_VALUE"""),1.0) -> 1 | E45: =IFERROR(__xludf.DUMMYFUNCTION("""COMPUTED_VALUE"""),0.0) -> 0
A46: =IFERROR(__xludf.DUMMYFUNCTION("""COMPUTED_VALUE"""),"V-RAMA") -> V-RAMA | B46: =IFERROR(__xludf.DUMMYFUNCTION("""COMPUTED_VALUE"""),"ITM001") -> ITM001 | C46: =IFERROR(__xludf.DUMMYFUNCTION("""COMPUTED_VALUE"""),"BOND PAPER (LONG)") -> BOND PAPER (LONG) | D46: =IFERROR(__xludf.DUMMYFUNCTION("""COMPUTED_VALUE"""),1.0) -> 1 | E46: =IFERROR(__xludf.DUMMYFUNCTION("""COMPUTED_VALUE"""),0.0) -> 0
A47: =IFERROR(__xludf.DUMMYFUNCTION("""COMPUTED_VALUE"""),"V-RAMA") -> V-RAMA | B47: =IFERROR(__xludf.DUMMYFUNCTION("""COMPUTED_VALUE"""),"ITM003") -> ITM003 | C47: =IFERROR(__xludf.DUMMYFUNCTION("""COMPUTED_VALUE"""),"BOND PAPER A4") -> BOND PAPER A4 | D47: =IFERROR(__xludf.DUMMYFUNCTION("""COMPUTED_VALUE"""),1.0) -> 1 | E47: =IFERROR(__xludf.DUMMYFUNCTION("""COMPUTED_VALUE"""),0.0) -> 0
A48: =IFERROR(__xludf.DUMMYFUNCTION("""COMPUTED_VALUE"""),"V-RAMA") -> V-RAMA | B48: =IFERROR(__xludf.DUMMYFUNCTION("""COMPUTED_VALUE"""),"ITM012") -> ITM012 | C48: =IFERROR(__xludf.DUMMYFUNCTION("""COMPUTED_VALUE"""),"BROWN FOLDER (LONG)") -> BROWN FOLDER (LONG) | D48: =IFERROR(__xludf.DUMMYFUNCTION("""COMPUTED_VALUE"""),20.0) -> 20 | E48: =IFERROR(__xludf.DUMMYFUNCTION("""COMPUTED_VALUE"""),0.0) -> 0
A49: =IFERROR(__xludf.DUMMYFUNCTION("""COMPUTED_VALUE"""),"V-RAMA") -> V-RAMA | B49: =IFERROR(__xludf.DUMMYFUNCTION("""COMPUTED_VALUE"""),"ITM009") -> ITM009 | C49: =IFERROR(__xludf.DUMMYFUNCTION("""COMPUTED_VALUE"""),"CARBON PAPER (LONG BLUE)") -> CARBON PAPER (LONG BLUE) | D49: =IFERROR(__xludf.DUMMYFUNCTION("""COMPUTED_VALUE"""),11.0) -> 11 | E49: =IFERROR(__xludf.DUMMYFUNCTION("""COMPUTED_VALUE"""),0.0) -> 0
A50: =IFERROR(__xludf.DUMMYFUNCTION("""COMPUTED_VALUE"""),"V-RAMA") -> V-RAMA | B50: =IFERROR(__xludf.DUMMYFUNCTION("""COMPUTED_VALUE"""),"ITM106") -> ITM106 | C50: =IFERROR(__xludf.DUMMYFUNCTION("""COMPUTED_VALUE"""),"DOOR MAT") -> DOOR MAT | D50: =IFERROR(__xludf.DUMMYFUNCTION("""COMPUTED_VALUE"""),1.0) -> 1 | E50: =IFERROR(__xludf.DUMMYFUNCTION("""COMPUTED_VALUE"""),0.0) -> 0
A51: =IFERROR(__xludf.DUMMYFUNCTION("""COMPUTED_VALUE"""),"V-RAMA") -> V-RAMA | B51: =IFERROR(__xludf.DUMMYFUNCTION("""COMPUTED_VALUE"""),"ITM040") -> ITM040 | C51: =IFERROR(__xludf.DUMMYFUNCTION("""COMPUTED_VALUE"""),"DOUBLE-SIDED TAPE (1 INCH)") -> DOUBLE-SIDED TAPE (1 INCH) | D51: =IFERROR(__xludf.DUMMYFUNCTION("""COMPUTED_VALUE"""),2.0) -> 2 | E51: =IFERROR(__xludf.DUMMYFUNCTION("""COMPUTED_VALUE"""),0.0) -> 0
A52: =IFERROR(__xludf.DUMMYFUNCTION("""COMPUTED_VALUE"""),"V-RAMA") -> V-RAMA | B52: =IFERROR(__xludf.DUMMYFUNCTION("""COMPUTED_VALUE"""),"ITM062") -> ITM062 | C52: =IFERROR(__xludf.DUMMYFUNCTION("""COMPUTED_VALUE"""),"DOWNY") -> DOWNY | D52: =IFERROR(__xludf.DUMMYFUNCTION("""COMPUTED_VALUE"""),3.0) -> 3 | E52: =IFERROR(__xludf.DUMMYFUNCTION("""COMPUTED_VALUE"""),0.0) -> 0
A53: =IFERROR(__xludf.DUMMYFUNCTION("""COMPUTED_VALUE"""),"V-RAMA") -> V-RAMA | B53: =IFERROR(__xludf.DUMMYFUNCTION("""COMPUTED_VALUE"""),"ITM067") -> ITM067 | C53: =IFERROR(__xludf.DUMMYFUNCTION("""COMPUTED_VALUE"""),"FASTENER") -> FASTENER | D53: =IFERROR(__xludf.DUMMYFUNCTION("""COMPUTED_VALUE"""),1.0) -> 1 | E53: =IFERROR(__xludf.DUMMYFUNCTION("""COMPUTED_VALUE"""),0.0) -> 0
A54: =IFERROR(__xludf.DUMMYFUNCTION("""COMPUTED_VALUE"""),"V-RAMA") -> V-RAMA | B54: =IFERROR(__xludf.DUMMYFUNCTION("""COMPUTED_VALUE"""),"ITM019") -> ITM019 | C54: =IFERROR(__xludf.DUMMYFUNCTION("""COMPUTED_VALUE"""),"FLEXSTICK BLACK BALLPEN (0.5)") -> FLEXSTICK BLACK BALLPEN (0.5) | D54: =IFERROR(__xludf.DUMMYFUNCTION("""COMPUTED_VALUE"""),6.0) -> 6 | E54: =IFERROR(__xludf.DUMMYFUNCTION("""COMPUTED_VALUE"""),0.0) -> 0
A55: =IFERROR(__xludf.DUMMYFUNCTION("""COMPUTED_VALUE"""),"V-RAMA") -> V-RAMA | B55: =IFERROR(__xludf.DUMMYFUNCTION("""COMPUTED_VALUE"""),"ITM023") -> ITM023 | C55: =IFERROR(__xludf.DUMMYFUNCTION("""COMPUTED_VALUE"""),"HIGHLIGHTER") -> HIGHLIGHTER | D55: =IFERROR(__xludf.DUMMYFUNCTION("""COMPUTED_VALUE"""),2.0) -> 2 | E55: =IFERROR(__xludf.DUMMYFUNCTION("""COMPUTED_VALUE"""),0.0) -> 0
A56: =IFERROR(__xludf.DUMMYFUNCTION("""COMPUTED_VALUE"""),"V-RAMA") -> V-RAMA | B56: =IFERROR(__xludf.DUMMYFUNCTION("""COMPUTED_VALUE"""),"ITM100") -> ITM100 | C56: =IFERROR(__xludf.DUMMYFUNCTION("""COMPUTED_VALUE"""),"INK BROTHER SET") -> INK BROTHER SET | D56: =IFERROR(__xludf.DUMMYFUNCTION("""COMPUTED_VALUE"""),1.0) -> 1 | E56: =IFERROR(__xludf.DUMMYFUNCTION("""COMPUTED_VALUE"""),0.0) -> 0
A57: =IFERROR(__xludf.DUMMYFUNCTION("""COMPUTED_VALUE"""),"V-RAMA") -> V-RAMA | B57: =IFERROR(__xludf.DUMMYFUNCTION("""COMPUTED_VALUE"""),"ITM038") -> ITM038 | C57: =IFERROR(__xludf.DUMMYFUNCTION("""COMPUTED_VALUE"""),"MASKING TAPE") -> MASKING TAPE | D57: =IFERROR(__xludf.DUMMYFUNCTION("""COMPUTED_VALUE"""),2.0) -> 2 | E57: =IFERROR(__xludf.DUMMYFUNCTION("""COMPUTED_VALUE"""),0.0) -> 0
A58: =IFERROR(__xludf.DUMMYFUNCTION("""COMPUTED_VALUE"""),"V-RAMA") -> V-RAMA | B58: =IFERROR(__xludf.DUMMYFUNCTION("""COMPUTED_VALUE"""),"ITM039") -> ITM039 | C58: =IFERROR(__xludf.DUMMYFUNCTION("""COMPUTED_VALUE"""),"PACKAGING TAPE BROWN") -> PACKAGING TAPE BROWN | D58: =IFERROR(__xludf.DUMMYFUNCTION("""COMPUTED_VALUE"""),1.0) -> 1 | E58: =IFERROR(__xludf.DUMMYFUNCTION("""COMPUTED_VALUE"""),0.0) -> 0
A59: =IFERROR(__xludf.DUMMYFUNCTION("""COMPUTED_VALUE"""),"V-RAMA") -> V-RAMA | B59: =IFERROR(__xludf.DUMMYFUNCTION("""COMPUTED_VALUE"""),"ITM068") -> ITM068 | C59: =IFERROR(__xludf.DUMMYFUNCTION("""COMPUTED_VALUE"""),"PAPER CLIPS 50MM") -> PAPER CLIPS 50MM | D59: =IFERROR(__xludf.DUMMYFUNCTION("""COMPUTED_VALUE"""),1.0) -> 1 | E59: =IFERROR(__xludf.DUMMYFUNCTION("""COMPUTED_VALUE"""),0.0) -> 0
A60: =IFERROR(__xludf.DUMMYFUNCTION("""COMPUTED_VALUE"""),"V-RAMA") -> V-RAMA | B60: =IFERROR(__xludf.DUMMYFUNCTION("""COMPUTED_VALUE"""),"ITM056") -> ITM056 | C60: =IFERROR(__xludf.DUMMYFUNCTION("""COMPUTED_VALUE"""),"PRIDE SOAP POWDER") -> PRIDE SOAP POWDER | D60: =IFERROR(__xludf.DUMMYFUNCTION("""COMPUTED_VALUE"""),6.0) -> 6 | E60: =IFERROR(__xludf.DUMMYFUNCTION("""COMPUTED_VALUE"""),0.0) -> 0
A61: =IFERROR(__xludf.DUMMYFUNCTION("""COMPUTED_VALUE"""),"V-RAMA") -> V-RAMA | B61: =IFERROR(__xludf.DUMMYFUNCTION("""COMPUTED_VALUE"""),"ITM092") -> ITM092 | C61: =IFERROR(__xludf.DUMMYFUNCTION("""COMPUTED_VALUE"""),"RAGS") -> RAGS | D61: =IFERROR(__xludf.DUMMYFUNCTION("""COMPUTED_VALUE"""),1.0) -> 1 | E61: =IFERROR(__xludf.DUMMYFUNCTION("""COMPUTED_VALUE"""),0.0) -> 0
A62: =IFERROR(__xludf.DUMMYFUNCTION("""COMPUTED_VALUE"""),"V-RAMA") -> V-RAMA | B62: =IFERROR(__xludf.DUMMYFUNCTION("""COMPUTED_VALUE"""),"ITM074") -> ITM074 | C62: =IFERROR(__xludf.DUMMYFUNCTION("""COMPUTED_VALUE"""),"STAPLE WIRE #35") -> STAPLE WIRE #35 | D62: =IFERROR(__xludf.DUMMYFUNCTION("""COMPUTED_VALUE"""),1.0) -> 1 | E62: =IFERROR(__xludf.DUMMYFUNCTION("""COMPUTED_VALUE"""),0.0) -> 0
A63: =IFERROR(__xludf.DUMMYFUNCTION("""COMPUTED_VALUE"""),"V-RAMA") -> V-RAMA | B63: =IFERROR(__xludf.DUMMYFUNCTION("""COMPUTED_VALUE"""),"ITM064") -> ITM064 | C63: =IFERROR(__xludf.DUMMYFUNCTION("""COMPUTED_VALUE"""),"STICKY NOTES 2X2 A02") -> STICKY NOTES 2X2 A02 | D63: =IFERROR(__xludf.DUMMYFUNCTION("""COMPUTED_VALUE"""),3.0) -> 3 | E63: =IFERROR(__xludf.DUMMYFUNCTION("""COMPUTED_VALUE"""),0.0) -> 0
A64: =IFERROR(__xludf.DUMMYFUNCTION("""COMPUTED_VALUE"""),"V-RAMA") -> V-RAMA | B64: =IFERROR(__xludf.DUMMYFUNCTION("""COMPUTED_VALUE"""),"ITM006") -> ITM006 | C64: =IFERROR(__xludf.DUMMYFUNCTION("""COMPUTED_VALUE"""),"VELLUM PAPER") -> VELLUM PAPER | D64: =IFERROR(__xludf.DUMMYFUNCTION("""COMPUTED_VALUE"""),20.0) -> 20 | E64: =IFERROR(__xludf.DUMMYFUNCTION("""COMPUTED_VALUE"""),0.0) -> 0
A65: =IFERROR(__xludf.DUMMYFUNCTION("""COMPUTED_VALUE"""),"V-RAMA") -> V-RAMA | B65: =IFERROR(__xludf.DUMMYFUNCTION("""COMPUTED_VALUE"""),"ITM021") -> ITM021 | C65: =IFERROR(__xludf.DUMMYFUNCTION("""COMPUTED_VALUE"""),"WYTEBORD MARKER PILOT (BLACK)") -> WYTEBORD MARKER PILOT (BLACK) | D65: =IFERROR(__xludf.DUMMYFUNCTION("""COMPUTED_VALUE"""),1.0) -> 1 | E65: =IFERROR(__xludf.DUMMYFUNCTION("""COMPUTED_VALUE"""),0.0) -> 0
A66: =IFERROR(__xludf.DUMMYFUNCTION("""COMPUTED_VALUE"""),"BULACAO") -> BULACAO | B66: =IFERROR(__xludf.DUMMYFUNCTION("""COMPUTED_VALUE"""),"ITM087") -> ITM087 | C66: =IFERROR(__xludf.DUMMYFUNCTION("""COMPUTED_VALUE"""),"ALBATROSS") -> ALBATROSS | D66: =IFERROR(__xludf.DUMMYFUNCTION("""COMPUTED_VALUE"""),1.0) -> 1 | E66: =IFERROR(__xludf.DUMMYFUNCTION("""COMPUTED_VALUE"""),0.0) -> 0
A67: =IFERROR(__xludf.DUMMYFUNCTION("""COMPUTED_VALUE"""),"BULACAO") -> BULACAO | B67: =IFERROR(__xludf.DUMMYFUNCTION("""COMPUTED_VALUE"""),"ITM056") -> ITM056 | C67: =IFERROR(__xludf.DUMMYFUNCTION("""COMPUTED_VALUE"""),"PRIDE SOAP POWDER") -> PRIDE SOAP POWDER | D67: =IFERROR(__xludf.DUMMYFUNCTION("""COMPUTED_VALUE"""),6.0) -> 6 | E67: =IFERROR(__xludf.DUMMYFUNCTION("""COMPUTED_VALUE"""),0.0) -> 0
A68: =IFERROR(__xludf.DUMMYFUNCTION("""COMPUTED_VALUE"""),"BULACAO") -> BULACAO | B68: =IFERROR(__xludf.DUMMYFUNCTION("""COMPUTED_VALUE"""),"ITM063") -> ITM063 | C68: =IFERROR(__xludf.DUMMYFUNCTION("""COMPUTED_VALUE"""),"SAFEGUARD SOAP") -> SAFEGUARD SOAP | D68: =IFERROR(__xludf.DUMMYFUNCTION("""COMPUTED_VALUE"""),1.0) -> 1 | E68: =IFERROR(__xludf.DUMMYFUNCTION("""COMPUTED_VALUE"""),0.0) -> 0
A69: =IFERROR(__xludf.DUMMYFUNCTION("""COMPUTED_VALUE"""),"BULACAO") -> BULACAO | B69: =IFERROR(__xludf.DUMMYFUNCTION("""COMPUTED_VALUE"""),"ITM089") -> ITM089 | C69: =IFERROR(__xludf.DUMMYFUNCTION("""COMPUTED_VALUE"""),"ZONROX (COLORSAFE)") -> ZONROX (COLORSAFE) | D69: =IFERROR(__xludf.DUMMYFUNCTION("""COMPUTED_VALUE"""),1.0) -> 1 | E69: =IFERROR(__xludf.DUMMYFUNCTION("""COMPUTED_VALUE"""),0.0) -> 0
A70: =IFERROR(__xludf.DUMMYFUNCTION("""COMPUTED_VALUE"""),"BULACAO") -> BULACAO | B70: =IFERROR(__xludf.DUMMYFUNCTION("""COMPUTED_VALUE"""),"ITM088") -> ITM088 | C70: =IFERROR(__xludf.DUMMYFUNCTION("""COMPUTED_VALUE"""),"ZONROX (ORIGINAL)") -> ZONROX (ORIGINAL) | D70: =IFERROR(__xludf.DUMMYFUNCTION("""COMPUTED_VALUE"""),1.0) -> 1 | E70: =IFERROR(__xludf.DUMMYFUNCTION("""COMPUTED_VALUE"""),0.0) -> 0
A71: =IFERROR(__xludf.DUMMYFUNCTION("""COMPUTED_VALUE"""),"BULACAO") -> BULACAO | B71: =IFERROR(__xludf.DUMMYFUNCTION("""COMPUTED_VALUE"""),"ITM094") -> ITM094 | C71: =IFERROR(__xludf.DUMMYFUNCTION("""COMPUTED_VALUE"""),"TRASH BAG (XL)") -> TRASH BAG (XL) | D71: =IFERROR(__xludf.DUMMYFUNCTION("""COMPUTED_VALUE"""),1.0) -> 1 | E71: =IFERROR(__xludf.DUMMYFUNCTION("""COMPUTED_VALUE"""),0.0) -> 0
A72: =IFERROR(__xludf.DUMMYFUNCTION("""COMPUTED_VALUE"""),"BULACAO") -> BULACAO | B72: =IFERROR(__xludf.DUMMYFUNCTION("""COMPUTED_VALUE"""),"ITM012") -> ITM012 | C72: =IFERROR(__xludf.DUMMYFUNCTION("""COMPUTED_VALUE"""),"BROWN FOLDER (LONG)") -> BROWN FOLDER (LONG) | D72: =IFERROR(__xludf.DUMMYFUNCTION("""COMPUTED_VALUE"""),30.0) -> 30 | E72: =IFERROR(__xludf.DUMMYFUNCTION("""COMPUTED_VALUE"""),0.0) -> 0
A73: =IFERROR(__xludf.DUMMYFUNCTION("""COMPUTED_VALUE"""),"BULACAO") -> BULACAO | B73: =IFERROR(__xludf.DUMMYFUNCTION("""COMPUTED_VALUE"""),"ITM027") -> ITM027 | C73: =IFERROR(__xludf.DUMMYFUNCTION("""COMPUTED_VALUE"""),"CORRECTION TAPE") -> CORRECTION TAPE | D73: =IFERROR(__xludf.DUMMYFUNCTION("""COMPUTED_VALUE"""),1.0) -> 1 | E73: =IFERROR(__xludf.DUMMYFUNCTION("""COMPUTED_VALUE"""),0.0) -> 0
A74: =IFERROR(__xludf.DUMMYFUNCTION("""COMPUTED_VALUE"""),"BULACAO") -> BULACAO | B74: =IFERROR(__xludf.DUMMYFUNCTION("""COMPUTED_VALUE"""),"ITM067") -> ITM067 | C74: =IFERROR(__xludf.DUMMYFUNCTION("""COMPUTED_VALUE"""),"FASTENER") -> FASTENER | D74: =IFERROR(__xludf.DUMMYFUNCTION("""COMPUTED_VALUE"""),1.0) -> 1 | E74: =IFERROR(__xludf.DUMMYFUNCTION("""COMPUTED_VALUE"""),0.0) -> 0
A75: =IFERROR(__xludf.DUMMYFUNCTION("""COMPUTED_VALUE"""),"BULACAO") -> BULACAO | B75: =IFERROR(__xludf.DUMMYFUNCTION("""COMPUTED_VALUE"""),"ITM019") -> ITM019 | C75: =IFERROR(__xludf.DUMMYFUNCTION("""COMPUTED_VALUE"""),"FLEXSTICK BLACK BALLPEN (0.5)") -> FLEXSTICK BLACK BALLPEN (0.5) | D75: =IFERROR(__xludf.DUMMYFUNCTION("""COMPUTED_VALUE"""),5.0) -> 5 | E75: =IFERROR(__xludf.DUMMYFUNCTION("""COMPUTED_VALUE"""),0.0) -> 0
A76: =IFERROR(__xludf.DUMMYFUNCTION("""COMPUTED_VALUE"""),"BULACAO") -> BULACAO | B76: =IFERROR(__xludf.DUMMYFUNCTION("""COMPUTED_VALUE"""),"ITM056") -> ITM056 | C76: =IFERROR(__xludf.DUMMYFUNCTION("""COMPUTED_VALUE"""),"PRIDE SOAP POWDER") -> PRIDE SOAP POWDER | D76: =IFERROR(__xludf.DUMMYFUNCTION("""COMPUTED_VALUE"""),6.0) -> 6 | E76: =IFERROR(__xludf.DUMMYFUNCTION("""COMPUTED_VALUE"""),0.0) -> 0
A77: =IFERROR(__xludf.DUMMYFUNCTION("""COMPUTED_VALUE"""),"Y3S TALISAY") -> Y3S TALISAY | B77: =IFERROR(__xludf.DUMMYFUNCTION("""COMPUTED_VALUE"""),"ITM004") -> ITM004 | C77: =IFERROR(__xludf.DUMMYFUNCTION("""COMPUTED_VALUE"""),"BOND PAPER NEWSPRINT (SHORT)") -> BOND PAPER NEWSPRINT (SHORT) | D77: =IFERROR(__xludf.DUMMYFUNCTION("""COMPUTED_VALUE"""),1.0) -> 1 | E77: =IFERROR(__xludf.DUMMYFUNCTION("""COMPUTED_VALUE"""),0.0) -> 0
A78: =IFERROR(__xludf.DUMMYFUNCTION("""COMPUTED_VALUE"""),"Y3S TALISAY") -> Y3S TALISAY | B78: =IFERROR(__xludf.DUMMYFUNCTION("""COMPUTED_VALUE"""),"ITM012") -> ITM012 | C78: =IFERROR(__xludf.DUMMYFUNCTION("""COMPUTED_VALUE"""),"BROWN FOLDER (LONG)") -> BROWN FOLDER (LONG) | D78: =IFERROR(__xludf.DUMMYFUNCTION("""COMPUTED_VALUE"""),20.0) -> 20 | E78: =IFERROR(__xludf.DUMMYFUNCTION("""COMPUTED_VALUE"""),0.0) -> 0
A79: =IFERROR(__xludf.DUMMYFUNCTION("""COMPUTED_VALUE"""),"Y3S TALISAY") -> Y3S TALISAY | B79: =IFERROR(__xludf.DUMMYFUNCTION("""COMPUTED_VALUE"""),"ITM027") -> ITM027 | C79: =IFERROR(__xludf.DUMMYFUNCTION("""COMPUTED_VALUE"""),"CORRECTION TAPE") -> CORRECTION TAPE | D79: =IFERROR(__xludf.DUMMYFUNCTION("""COMPUTED_VALUE"""),1.0) -> 1 | E79: =IFERROR(__xludf.DUMMYFUNCTION("""COMPUTED_VALUE"""),0.0) -> 0
A80: =IFERROR(__xludf.DUMMYFUNCTION("""COMPUTED_VALUE"""),"Y3S TALISAY") -> Y3S TALISAY | B80: =IFERROR(__xludf.DUMMYFUNCTION("""COMPUTED_VALUE"""),"ITM020") -> ITM020 | C80: =IFERROR(__xludf.DUMMYFUNCTION("""COMPUTED_VALUE"""),"FLEXSTICK RED BALLPEN (0.5)") -> FLEXSTICK RED BALLPEN (0.5) | D80: =IFERROR(__xludf.DUMMYFUNCTION("""COMPUTED_VALUE"""),2.0) -> 2 | E80: =IFERROR(__xludf.DUMMYFUNCTION("""COMPUTED_VALUE"""),0.0) -> 0
A81: =IFERROR(__xludf.DUMMYFUNCTION("""COMPUTED_VALUE"""),"Y3S TALISAY") -> Y3S TALISAY | B81: =IFERROR(__xludf.DUMMYFUNCTION("""COMPUTED_VALUE"""),"ITM056") -> ITM056 | C81: =IFERROR(__xludf.DUMMYFUNCTION("""COMPUTED_VALUE"""),"PRIDE SOAP POWDER") -> PRIDE SOAP POWDER | D81: =IFERROR(__xludf.DUMMYFUNCTION("""COMPUTED_VALUE"""),6.0) -> 6 | E81: =IFERROR(__xludf.DUMMYFUNCTION("""COMPUTED_VALUE"""),0.0) -> 0
A82: =IFERROR(__xludf.DUMMYFUNCTION("""COMPUTED_VALUE"""),"Y3S TALISAY") -> Y3S TALISAY | B82: =IFERROR(__xludf.DUMMYFUNCTION("""COMPUTED_VALUE"""),"ITM092") -> ITM092 | C82: =IFERROR(__xludf.DUMMYFUNCTION("""COMPUTED_VALUE"""),"RAGS") -> RAGS | D82: =IFERROR(__xludf.DUMMYFUNCTION("""COMPUTED_VALUE"""),1.0) -> 1 | E82: =IFERROR(__xludf.DUMMYFUNCTION("""COMPUTED_VALUE"""),0.0) -> 0
A83: =IFERROR(__xludf.DUMMYFUNCTION("""COMPUTED_VALUE"""),"Y3S TALISAY") -> Y3S TALISAY | B83: =IFERROR(__xludf.DUMMYFUNCTION("""COMPUTED_VALUE"""),"ITM098") -> ITM098 | C83: =IFERROR(__xludf.DUMMYFUNCTION("""COMPUTED_VALUE"""),"TISSUE PAPER") -> TISSUE PAPER | D83: =IFERROR(__xludf.DUMMYFUNCTION("""COMPUTED_VALUE"""),3.0) -> 3 | E83: =IFERROR(__xludf.DUMMYFUNCTION("""COMPUTED_VALUE"""),0.0) -> 0
A84: =IFERROR(__xludf.DUMMYFUNCTION("""COMPUTED_VALUE"""),"Y3S TALISAY") -> Y3S TALISAY | B84: =IFERROR(__xludf.DUMMYFUNCTION("""COMPUTED_VALUE"""),"ITM100") -> ITM100 | C84: =IFERROR(__xludf.DUMMYFUNCTION("""COMPUTED_VALUE"""),"INK BROTHER SET") -> INK BROTHER SET | D84: =IFERROR(__xludf.DUMMYFUNCTION("""COMPUTED_VALUE"""),1.0) -> 1 | E84: =IFERROR(__xludf.DUMMYFUNCTION("""COMPUTED_VALUE"""),0.0) -> 0
A85: =IFERROR(__xludf.DUMMYFUNCTION("""COMPUTED_VALUE"""),"Y3S TALISAY") -> Y3S TALISAY | B85: =IFERROR(__xludf.DUMMYFUNCTION("""COMPUTED_VALUE"""),"ITM002") -> ITM002 | C85: =IFERROR(__xludf.DUMMYFUNCTION("""COMPUTED_VALUE"""),"BOND PAPER (SHORT)") -> BOND PAPER (SHORT) | D85: =IFERROR(__xludf.DUMMYFUNCTION("""COMPUTED_VALUE"""),1.0) -> 1 | E85: =IFERROR(__xludf.DUMMYFUNCTION("""COMPUTED_VALUE"""),0.0) -> 0
A86: =IFERROR(__xludf.DUMMYFUNCTION("""COMPUTED_VALUE"""),"Y3S TALISAY") -> Y3S TALISAY | B86: =IFERROR(__xludf.DUMMYFUNCTION("""COMPUTED_VALUE"""),"ITM027") -> ITM027 | C86: =IFERROR(__xludf.DUMMYFUNCTION("""COMPUTED_VALUE"""),"CORRECTION TAPE") -> CORRECTION TAPE | D86: =IFERROR(__xludf.DUMMYFUNCTION("""COMPUTED_VALUE"""),4.0) -> 4 | E86: =IFERROR(__xludf.DUMMYFUNCTION("""COMPUTED_VALUE"""),0.0) -> 0
A87: =IFERROR(__xludf.DUMMYFUNCTION("""COMPUTED_VALUE"""),"Y3S TALISAY") -> Y3S TALISAY | B87: =IFERROR(__xludf.DUMMYFUNCTION("""COMPUTED_VALUE"""),"ITM090") -> ITM090 | C87: =IFERROR(__xludf.DUMMYFUNCTION("""COMPUTED_VALUE"""),"GLASS CLEANER") -> GLASS CLEANER | D87: =IFERROR(__xludf.DUMMYFUNCTION("""COMPUTED_VALUE"""),1.0) -> 1 | E87: =IFERROR(__xludf.DUMMYFUNCTION("""COMPUTED_VALUE"""),0.0) -> 0
A88: =IFERROR(__xludf.DUMMYFUNCTION("""COMPUTED_VALUE"""),"Y3S TALISAY") -> Y3S TALISAY | B88: =IFERROR(__xludf.DUMMYFUNCTION("""COMPUTED_VALUE"""),"ITM002") -> ITM002 | C88: =IFERROR(__xludf.DUMMYFUNCTION("""COMPUTED_VALUE"""),"BOND PAPER (SHORT)") -> BOND PAPER (SHORT) | D88: =IFERROR(__xludf.DUMMYFUNCTION("""COMPUTED_VALUE"""),1.0) -> 1 | E88: =IFERROR(__xludf.DUMMYFUNCTION("""COMPUTED_VALUE"""),0.0) -> 0
A89: =IFERROR(__xludf.DUMMYFUNCTION("""COMPUTED_VALUE"""),"Y3S TALISAY") -> Y3S TALISAY | B89: =IFERROR(__xludf.DUMMYFUNCTION("""COMPUTED_VALUE"""),"ITM003") -> ITM003 | C89: =IFERROR(__xludf.DUMMYFUNCTION("""COMPUTED_VALUE"""),"BOND PAPER A4") -> BOND PAPER A4 | D89: =IFERROR(__xludf.DUMMYFUNCTION("""COMPUTED_VALUE"""),1.0) -> 1 | E89: =IFERROR(__xludf.DUMMYFUNCTION("""COMPUTED_VALUE"""),0.0) -> 0
A90: =IFERROR(__xludf.DUMMYFUNCTION("""COMPUTED_VALUE"""),"Y3S TALISAY") -> Y3S TALISAY | B90: =IFERROR(__xludf.DUMMYFUNCTION("""COMPUTED_VALUE"""),"ITM010") -> ITM010 | C90: =IFERROR(__xludf.DUMMYFUNCTION("""COMPUTED_VALUE"""),"BROWN ENVELOPE (LONG)") -> BROWN ENVELOPE (LONG) | D90: =IFERROR(__xludf.DUMMYFUNCTION("""COMPUTED_VALUE"""),15.0) -> 15 | E90: =IFERROR(__xludf.DUMMYFUNCTION("""COMPUTED_VALUE"""),0.0) -> 0
A91: =IFERROR(__xludf.DUMMYFUNCTION("""COMPUTED_VALUE"""),"Y3S TALISAY") -> Y3S TALISAY | B91: =IFERROR(__xludf.DUMMYFUNCTION("""COMPUTED_VALUE"""),"ITM011") -> ITM011 | C91: =IFERROR(__xludf.DUMMYFUNCTION("""COMPUTED_VALUE"""),"BROWN ENVELOPE (SHORT)") -> BROWN ENVELOPE (SHORT) | D91: =IFERROR(__xludf.DUMMYFUNCTION("""COMPUTED_VALUE"""),20.0) -> 20 | E91: =IFERROR(__xludf.DUMMYFUNCTION("""COMPUTED_VALUE"""),0.0) -> 0
A92: =IFERROR(__xludf.DUMMYFUNCTION("""COMPUTED_VALUE"""),"Y3S TALISAY") -> Y3S TALISAY | B92: =IFERROR(__xludf.DUMMYFUNCTION("""COMPUTED_VALUE"""),"ITM012") -> ITM012 | C92: =IFERROR(__xludf.DUMMYFUNCTION("""COMPUTED_VALUE"""),"BROWN FOLDER (LONG)") -> BROWN FOLDER (LONG) | D92: =IFERROR(__xludf.DUMMYFUNCTION("""COMPUTED_VALUE"""),20.0) -> 20 | E92: =IFERROR(__xludf.DUMMYFUNCTION("""COMPUTED_VALUE"""),0.0) -> 0
A93: =IFERROR(__xludf.DUMMYFUNCTION("""COMPUTED_VALUE"""),"Y3S TALISAY") -> Y3S TALISAY | B93: =IFERROR(__xludf.DUMMYFUNCTION("""COMPUTED_VALUE"""),"ITM056") -> ITM056 | C93: =IFERROR(__xludf.DUMMYFUNCTION("""COMPUTED_VALUE"""),"PRIDE SOAP POWDER") -> PRIDE SOAP POWDER | D93: =IFERROR(__xludf.DUMMYFUNCTION("""COMPUTED_VALUE"""),5.0) -> 5 | E93: =IFERROR(__xludf.DUMMYFUNCTION("""COMPUTED_VALUE"""),0.0) -> 0
A94: =IFERROR(__xludf.DUMMYFUNCTION("""COMPUTED_VALUE"""),"Y3S TALISAY") -> Y3S TALISAY | B94: =IFERROR(__xludf.DUMMYFUNCTION("""COMPUTED_VALUE"""),"ITM092") -> ITM092 | C94: =IFERROR(__xludf.DUMMYFUNCTION("""COMPUTED_VALUE"""),"RAGS") -> RAGS | D94: =IFERROR(__xludf.DUMMYFUNCTION("""COMPUTED_VALUE"""),1.0) -> 1 | E94: =IFERROR(__xludf.DUMMYFUNCTION("""COMPUTED_VALUE"""),0.0) -> 0
A95: =IFERROR(__xludf.DUMMYFUNCTION("""COMPUTED_VALUE"""),"Y3S TALISAY") -> Y3S TALISAY | B95: =IFERROR(__xludf.DUMMYFUNCTION("""COMPUTED_VALUE"""),"ITM093") -> ITM093 | C95: =IFERROR(__xludf.DUMMYFUNCTION("""COMPUTED_VALUE"""),"TRASH BAG (XXL)") -> TRASH BAG (XXL) | D95: =IFERROR(__xludf.DUMMYFUNCTION("""COMPUTED_VALUE"""),1.0) -> 1 | E95: =IFERROR(__xludf.DUMMYFUNCTION("""COMPUTED_VALUE"""),0.0) -> 0
A96: =IFERROR(__xludf.DUMMYFUNCTION("""COMPUTED_VALUE"""),"Y3S TALISAY") -> Y3S TALISAY | B96: =IFERROR(__xludf.DUMMYFUNCTION("""COMPUTED_VALUE"""),"ITM015") -> ITM015 | C96: =IFERROR(__xludf.DUMMYFUNCTION("""COMPUTED_VALUE"""),"WHITE FOLDER (SHORT)") -> WHITE FOLDER (SHORT) | D96: =IFERROR(__xludf.DUMMYFUNCTION("""COMPUTED_VALUE"""),5.0) -> 5 | E96: =IFERROR(__xludf.DUMMYFUNCTION("""COMPUTED_VALUE"""),0.0) -> 0
A97: =IFERROR(__xludf.DUMMYFUNCTION("""COMPUTED_VALUE"""),"Y3S TALISAY") -> Y3S TALISAY | B97: =IFERROR(__xludf.DUMMYFUNCTION("""COMPUTED_VALUE"""),"ITM009") -> ITM009 | C97: =IFERROR(__xludf.DUMMYFUNCTION("""COMPUTED_VALUE"""),"CARBON PAPER (LONG BLUE)") -> CARBON PAPER (LONG BLUE) | D97: =IFERROR(__xludf.DUMMYFUNCTION("""COMPUTED_VALUE"""),5.0) -> 5 | E97: =IFERROR(__xludf.DUMMYFUNCTION("""COMPUTED_VALUE"""),0.0) -> 0
A98: =IFERROR(__xludf.DUMMYFUNCTION("""COMPUTED_VALUE"""),"Y3S TALISAY") -> Y3S TALISAY | B98: =IFERROR(__xludf.DUMMYFUNCTION("""COMPUTED_VALUE"""),"ITM078") -> ITM078 | C98: =IFERROR(__xludf.DUMMYFUNCTION("""COMPUTED_VALUE"""),"COFFEE CUPS") -> COFFEE CUPS | D98: =IFERROR(__xludf.DUMMYFUNCTION("""COMPUTED_VALUE"""),1.0) -> 1 | E98: =IFERROR(__xludf.DUMMYFUNCTION("""COMPUTED_VALUE"""),0.0) -> 0
A99: =IFERROR(__xludf.DUMMYFUNCTION("""COMPUTED_VALUE"""),"Y3S TALISAY") -> Y3S TALISAY | B99: =IFERROR(__xludf.DUMMYFUNCTION("""COMPUTED_VALUE"""),"ITM080") -> ITM080 | C99: =IFERROR(__xludf.DUMMYFUNCTION("""COMPUTED_VALUE"""),"COFFEE STICK") -> COFFEE STICK | D99: =IFERROR(__xludf.DUMMYFUNCTION("""COMPUTED_VALUE"""),1.0) -> 1 | E99: =IFERROR(__xludf.DUMMYFUNCTION("""COMPUTED_VALUE"""),0.0) -> 0
A100: =IFERROR(__xludf.DUMMYFUNCTION("""COMPUTED_VALUE"""),"Y3S TALISAY") -> Y3S TALISAY | B100: =IFERROR(__xludf.DUMMYFUNCTION("""COMPUTED_VALUE"""),"ITM079") -> ITM079 | C100: =IFERROR(__xludf.DUMMYFUNCTION("""COMPUTED_VALUE"""),"DRINKING CUPS") -> DRINKING CUPS | D100: =IFERROR(__xludf.DUMMYFUNCTION("""COMPUTED_VALUE"""),1.0) -> 1 | E100: =IFERROR(__xludf.DUMMYFUNCTION("""COMPUTED_VALUE"""),0.0) -> 0
...

Sheet ALL BRANCH APPROVED
A1: Timestamp | B1: Branch | C1: Date | D1: To | E1: Purpose | F1: ITEM_ID | G1: Qty | H1: Unit | I1: Description | J1: UPrice | K1: Amount | L1: Total | M1: Requested By | N1: Status | O1: Release Date | P1: Received By | Q1: PDF URL

Sheet RUNNING STOCKS
A1: Item_ID | B1: Description | C1: Unit | D1: ADMIN | E1: WAREHOUSE | F1: LAGTANG | G1: V-RAMA | H1: BULACAO | I1: Y3S TALISAY | J1: MINGLANILLA | K1: Y3S PARDO | L1: LAPU-LAPU | M1: BACAYAN | N1: SAN FERNANDO MB | O1: Y3S SAN FERNANDO | P1: LILOAN | Q1: CORDOVA MB | R1: Y3S CORDOVA | S1: CLARIN | T1: TOLEDO | U1: UBAY | V1: CARMEN | W1: TUBIGON | X1: TALIBON | Y1: BOGO | Z1: BALAMBAN | AA1: Y3S BARILI | AB1: BARILI MB | AC1: SIERRA BULLONES | AD1: PITOGO | AE1: TAYUD CONSOLACION | AF1: PINAMUNGAJAN | AG1: CANDIJAY | AH1: YATI LILOAN | AI1: CAMOTES | AJ1: Total Outgoing Stocks
A2: ITM001 | B2: BOND PAPER (LONG) | C2: REAM | D2: =IFERROR(SUMIFS(SUMMARY!D:D, SUMMARY!B:B, A2, SUMMARY!A:A, "ADMIN"), 0) -> 1 | E2: 0 | F2: =IFERROR(SUMIFS(SUMMARY!D:D, SUMMARY!B:B, A2, SUMMARY!A:A, "LAGTANG"), 0) -> 0 | G2: =IFERROR(SUMIFS(SUMMARY!D:D, SUMMARY!B:B, A2, SUMMARY!A:A, "V-RAMA"), 0) -> 1 | H2: =IFERROR(SUMIFS(SUMMARY!D:D, SUMMARY!B:B, A2, SUMMARY!A:A, "BULACAO"), 0) -> 0 | I2: =IFERROR(SUMIFS(SUMMARY!D:D, SUMMARY!B:B, A2, SUMMARY!A:A, "Y3S TALISAY"), 0) -> 0 | J2: =IFERROR(SUMIFS(SUMMARY!D:D, SUMMARY!B:B, A2, SUMMARY!A:A, "MINGLANILLA"), 0) -> 0 | K2: =IFERROR(SUMIFS(SUMMARY!D:D, SUMMARY!B:B, A2, SUMMARY!A:A, "Y3S PARDO"), 0) -> 0 | L2: =IFERROR(SUMIFS(SUMMARY!D:D, SUMMARY!B:B, A2, SUMMARY!A:A, "LAPU-LAPU"), 0) -> 0 | M2: =IFERROR(SUMIFS(SUMMARY!D:D, SUMMARY!B:B, A2, SUMMARY!A:A, "BACAYAN"), 0) -> 1 | N2: =IFERROR(SUMIFS(SUMMARY!D:D, SUMMARY!B:B, A2, SUMMARY!A:A, "SAN FERNANDO MB"), 0) -> 1 | O2: =IFERROR(SUMIFS(SUMMARY!D:D, SUMMARY!B:B, A2, SUMMARY!A:A, "Y3S SAN FERNANDO"), 0) -> 1 | P2: =IFERROR(SUMIFS(SUMMARY!D:D, SUMMARY!B:B, A2, SUMMARY!A:A, "LILOAN"), 0) -> 1 | Q2: =IFERROR(SUMIFS(SUMMARY!D:D, SUMMARY!B:B, A2, SUMMARY!A:A, "CORDOVA MB"), 0) -> 0 | R2: =IFERROR(SUMIFS(SUMMARY!D:D, SUMMARY!B:B, A2, SUMMARY!A:A, "Y3S CORDOVA"), 0) -> 1 | S2: =IFERROR(SUMIFS(SUMMARY!D:D, SUMMARY!B:B, A2, SUMMARY!A:A, "CLARIN"), 0) -> 0 | T2: =IFERROR(SUMIFS(SUMMARY!D:D, SUMMARY!B:B, A2, SUMMARY!A:A, "TOLEDO"), 0) -> 0 | U2: =IFERROR(SUMIFS(SUMMARY!D:D, SUMMARY!B:B, A2, SUMMARY!A:A, "UBAY"), 0) -> 0 | V2: =IFERROR(SUMIFS(SUMMARY!D:D, SUMMARY!B:B, A2, SUMMARY!A:A, "CARMEN"), 0) -> 1 | W2: =IFERROR(SUMIFS(SUMMARY!D:D, SUMMARY!B:B, A2, SUMMARY!A:A, "TUBIGON"), 0) -> 0 | X2: =IFERROR(SUMIFS(SUMMARY!D:D, SUMMARY!B:B, A2, SUMMARY!A:A, "TALIBON"), 0) -> 0 | Y2: =IFERROR(SUMIFS(SUMMARY!D:D, SUMMARY!B:B, A2, SUMMARY!A:A, "BOGO"), 0) -> 1 | Z2: =IFERROR(SUMIFS(SUMMARY!D:D, SUMMARY!B:B, A2, SUMMARY!A:A, "BALAMBAN"), 0) -> 0 | AA2: =IFERROR(SUMIFS(SUMMARY!D:D, SUMMARY!B:B, A2, SUMMARY!A:A, "Y3S BARILI"), 0) -> 1 | AB2: =IFERROR(SUMIFS(SUMMARY!D:D, SUMMARY!B:B, A2, SUMMARY!A:A, "BARILI MB"), 0) -> 1 | AC2: =IFERROR(SUMIFS(SUMMARY!D:D, SUMMARY!B:B, A2, SUMMARY!A:A, "SIERRA BULLONES"), 0) -> 1 | AD2: =IFERROR(SUMIFS(SUMMARY!D:D, SUMMARY!B:B, A2, SUMMARY!A:A, "PITOGO"), 0) -> 0 | AE2: =IFERROR(SUMIFS(SUMMARY!D:D, SUMMARY!B:B, A2, SUMMARY!A:A, "TAYUD CONSOLACION"), 0) -> 0 | AF2: =IFERROR(SUMIFS(SUMMARY!D:D, SUMMARY!B:B, A2, SUMMARY!A:A, "PINAMUNGAJAN"), 0) -> 0 | AG2: =IFERROR(SUMIFS(SUMMARY!D:D, SUMMARY!B:B, A2, SUMMARY!A:A, "CANDIJAY"), 0) -> 1 | AH2: =IFERROR(SUMIFS(SUMMARY!D:D, SUMMARY!B:B, A2, SUMMARY!A:A, "YATI LILOAN"), 0) -> 1 | AI2: =IFERROR(SUMIFS(SUMMARY!D:D, SUMMARY!B:B, A2, SUMMARY!A:A, "CAMOTES"), 0) -> 0 | AJ2: =SUM(D2:AH2) -> 14
A3: ITM002 | B3: BOND PAPER (SHORT) | C3: REAM | D3: =IFERROR(SUMIFS(SUMMARY!D:D, SUMMARY!B:B, A3, SUMMARY!A:A, "ADMIN"), 0) -> 2 | E3: =IFERROR(SUMIFS(SUMMARY!D:D, SUMMARY!B:B, A3, SUMMARY!A:A, "WAREHOUSE"), 0) -> 1 | F3: =IFERROR(SUMIFS(SUMMARY!D:D, SUMMARY!B:B, A3, SUMMARY!A:A, "LAGTANG"), 0) -> 1 | G3: =IFERROR(SUMIFS(SUMMARY!D:D, SUMMARY!B:B, A3, SUMMARY!A:A, "V-RAMA"), 0) -> 0 | H3: =IFERROR(SUMIFS(SUMMARY!D:D, SUMMARY!B:B, A3, SUMMARY!A:A, "BULACAO"), 0) -> 0 | I3: =IFERROR(SUMIFS(SUMMARY!D:D, SUMMARY!B:B, A3, SUMMARY!A:A, "Y3S TALISAY"), 0) -> 2 | J3: =IFERROR(SUMIFS(SUMMARY!D:D, SUMMARY!B:B, A3, SUMMARY!A:A, "MINGLANILLA"), 0) -> 1 | K3: =IFERROR(SUMIFS(SUMMARY!D:D, SUMMARY!B:B, A3, SUMMARY!A:A, "Y3S PARDO"), 0) -> 0 | L3: =IFERROR(SUMIFS(SUMMARY!D:D, SUMMARY!B:B, A3, SUMMARY!A:A, "LAPU-LAPU"), 0) -> 0 | M3: =IFERROR(SUMIFS(SUMMARY!D:D, SUMMARY!B:B, A3, SUMMARY!A:A, "BACAYAN"), 0) -> 0 | N3: =IFERROR(SUMIFS(SUMMARY!D:D, SUMMARY!B:B, A3, SUMMARY!A:A, "SAN FERNANDO MB"), 0) -> 1 | O3: =IFERROR(SUMIFS(SUMMARY!D:D, SUMMARY!B:B, A3, SUMMARY!A:A, "Y3S SAN FERNANDO"), 0) -> 1 | P3: =IFERROR(SUMIFS(SUMMARY!D:D, SUMMARY!B:B, A3, SUMMARY!A:A, "LILOAN"), 0) -> 1 | Q3: =IFERROR(SUMIFS(SUMMARY!D:D, SUMMARY!B:B, A3, SUMMARY!A:A, "CORDOVA MB"), 0) -> 0 | R3: =IFERROR(SUMIFS(SUMMARY!D:D, SUMMARY!B:B, A3, SUMMARY!A:A, "Y3S CORDOVA"), 0) -> 3 | S3: =IFERROR(SUMIFS(SUMMARY!D:D, SUMMARY!B:B, A3, SUMMARY!A:A, "CLARIN"), 0) -> 0 | T3: =IFERROR(SUMIFS(SUMMARY!D:D, SUMMARY!B:B, A3, SUMMARY!A:A, "TOLEDO"), 0) -> 0 | U3: =IFERROR(SUMIFS(SUMMARY!D:D, SUMMARY!B:B, A3, SUMMARY!A:A, "UBAY"), 0) -> 1 | V3: =IFERROR(SUMIFS(SUMMARY!D:D, SUMMARY!B:B, A3, SUMMARY!A:A, "CARMEN"), 0) -> 1 | W3: =IFERROR(SUMIFS(SUMMARY!D:D, SUMMARY!B:B, A3, SUMMARY!A:A, "TUBIGON"), 0) -> 1 | X3: =IFERROR(SUMIFS(SUMMARY!D:D, SUMMARY!B:B, A3, SUMMARY!A:A, "TALIBON"), 0) -> 1 | Y3: =IFERROR(SUMIFS(SUMMARY!D:D, SUMMARY!B:B, A3, SUMMARY!A:A, "BOGO"), 0) -> 0 | Z3: =IFERROR(SUMIFS(SUMMARY!D:D, SUMMARY!B:B, A3, SUMMARY!A:A, "BALAMBAN"), 0) -> 0 | AA3: =IFERROR(SUMIFS(SUMMARY!D:D, SUMMARY!B:B, A3, SUMMARY!A:A, "Y3S BARILI"), 0) -> 1 | AB3: =IFERROR(SUMIFS(SUMMARY!D:D, SUMMARY!B:B, A3, SUMMARY!A:A, "BARILI MB"), 0) -> 1 | AC3: =IFERROR(SUMIFS(SUMMARY!D:D, SUMMARY!B:B, A3, SUMMARY!A:A, "SIERRA BULLONES"), 0) -> 1 | AD3: =IFERROR(SUMIFS(SUMMARY!D:D, SUMMARY!B:B, A3, SUMMARY!A:A, "PITOGO"), 0) -> 1 | AE3: =IFERROR(SUMIFS(SUMMARY!D:D, SUMMARY!B:B, A3, SUMMARY!A:A, "TAYUD CONSOLACION"), 0) -> 0 | AF3: =IFERROR(SUMIFS(SUMMARY!D:D, SUMMARY!B:B, A3, SUMMARY!A:A, "PINAMUNGAJAN"), 0) -> 1 | AG3: =IFERROR(SUMIFS(SUMMARY!D:D, SUMMARY!B:B, A3, SUMMARY!A:A, "CANDIJAY"), 0) -> 1 | AH3: =IFERROR(SUMIFS(SUMMARY!D:D, SUMMARY!B:B, A3, SUMMARY!A:A, "YATI LILOAN"), 0) -> 1 | AI3: =IFERROR(SUMIFS(SUMMARY!D:D, SUMMARY!B:B, A3, SUMMARY!A:A, "CAMOTES"), 0) -> 0 | AJ3: =SUM(D3:AH3) -> 24
A4: ITM003 | B4: BOND PAPER A4 | C4: REAM | D4: =IFERROR(SUMIFS(SUMMARY!D:D, SUMMARY!B:B, A4, SUMMARY!A:A, "ADMIN"), 0) -> 1 | E4: =IFERROR(SUMIFS(SUMMARY!D:D, SUMMARY!B:B, A4, SUMMARY!A:A, "WAREHOUSE"), 0) -> 0 | F4: =IFERROR(SUMIFS(SUMMARY!D:D, SUMMARY!B:B, A4, SUMMARY!A:A, "LAGTANG"), 0) -> 1 | G4: =IFERROR(SUMIFS(SUMMARY!D:D, SUMMARY!B:B, A4, SUMMARY!A:A, "V-RAMA"), 0) -> 1 | H4: =IFERROR(SUMIFS(SUMMARY!D:D, SUMMARY!B:B, A4, SUMMARY!A:A, "BULACAO"), 0) -> 0 | I4: =IFERROR(SUMIFS(SUMMARY!D:D, SUMMARY!B:B, A4, SUMMARY!A:A, "Y3S TALISAY"), 0) -> 1 | J4: =IFERROR(SUMIFS(SUMMARY!D:D, SUMMARY!B:B, A4, SUMMARY!A:A, "MINGLANILLA"), 0) -> 0 | K4: =IFERROR(SUMIFS(SUMMARY!D:D, SUMMARY!B:B, A4, SUMMARY!A:A, "Y3S PARDO"), 0) -> 1 | L4: =IFERROR(SUMIFS(SUMMARY!D:D, SUMMARY!B:B, A4, SUMMARY!A:A, "LAPU-LAPU"), 0) -> 0 | M4: =IFERROR(SUMIFS(SUMMARY!D:D, SUMMARY!B:B, A4, SUMMARY!A:A, "BACAYAN"), 0) -> 0 | N4: =IFERROR(SUMIFS(SUMMARY!D:D, SUMMARY!B:B, A4, SUMMARY!A:A, "SAN FERNANDO MB"), 0) -> 0 | O4: =IFERROR(SUMIFS(SUMMARY!D:D, SUMMARY!B:B, A4, SUMMARY!A:A, "Y3S SAN FERNANDO"), 0) -> 0 | P4: =IFERROR(SUMIFS(SUMMARY!D:D, SUMMARY!B:B, A4, SUMMARY!A:A, "LILOAN"), 0) -> 0 | Q4: =IFERROR(SUMIFS(SUMMARY!D:D, SUMMARY!B:B, A4, SUMMARY!A:A, "CORDOVA MB"), 0) -> 0 | R4: =IFERROR(SUMIFS(SUMMARY!D:D, SUMMARY!B:B, A4, SUMMARY!A:A, "Y3S CORDOVA"), 0) -> 1 | S4: =IFERROR(SUMIFS(SUMMARY!D:D, SUMMARY!B:B, A4, SUMMARY!A:A, "CLARIN"), 0) -> 1 | T4: =IFERROR(SUMIFS(SUMMARY!D:D, SUMMARY!B:B, A4, SUMMARY!A:A, "TOLEDO"), 0) -> 0 | U4: =IFERROR(SUMIFS(SUMMARY!D:D, SUMMARY!B:B, A4, SUMMARY!A:A, "UBAY"), 0) -> 0 | V4: =IFERROR(SUMIFS(SUMMARY!D:D, SUMMARY!B:B, A4, SUMMARY!A:A, "CARMEN"), 0) -> 0 | W4: =IFERROR(SUMIFS(SUMMARY!D:D, SUMMARY!B:B, A4, SUMMARY!A:A, "TUBIGON"), 0) -> 0 | X4: =IFERROR(SUMIFS(SUMMARY!D:D, SUMMARY!B:B, A4, SUMMARY!A:A, "TALIBON"), 0) -> 0 | Y4: =IFERROR(SUMIFS(SUMMARY!D:D, SUMMARY!B:B, A4, SUMMARY!A:A, "BOGO"), 0) -> 1 | Z4: =IFERROR(SUMIFS(SUMMARY!D:D, SUMMARY!B:B, A4, SUMMARY!A:A, "BALAMBAN"), 0) -> 1 | AA4: =IFERROR(SUMIFS(SUMMARY!D:D, SUMMARY!B:B, A4, SUMMARY!A:A, "Y3S BARILI"), 0) -> 0 | AB4: =IFERROR(SUMIFS(SUMMARY!D:D, SUMMARY!B:B, A4, SUMMARY!A:A, "BARILI MB"), 0) -> 0 | AC4: =IFERROR(SUMIFS(SUMMARY!D:D, SUMMARY!B:B, A4, SUMMARY!A:A, "SIERRA BULLONES"), 0) -> 0 | AD4: =IFERROR(SUMIFS(SUMMARY!D:D, SUMMARY!B:B, A4, SUMMARY!A:A, "PITOGO"), 0) -> 0 | AE4: =IFERROR(SUMIFS(SUMMARY!D:D, SUMMARY!B:B, A4, SUMMARY!A:A, "TAYUD CONSOLACION"), 0) -> 0 | AF4: =IFERROR(SUMIFS(SUMMARY!D:D, SUMMARY!B:B, A4, SUMMARY!A:A, "PINAMUNGAJAN"), 0) -> 1 | AG4: =IFERROR(SUMIFS(SUMMARY!D:D, SUMMARY!B:B, A4, SUMMARY!A:A, "CANDIJAY"), 0) -> 0 | AH4: =IFERROR(SUMIFS(SUMMARY!D:D, SUMMARY!B:B, A4, SUMMARY!A:A, "YATI LILOAN"), 0) -> 0 | AI4: =IFERROR(SUMIFS(SUMMARY!D:D, SUMMARY!B:B, A4, SUMMARY!A:A, "CAMOTES"), 0) -> 0 | AJ4: =SUM(D4:AH4) -> 10
A5: ITM004 | B5: BOND PAPER NEWSPRINT (SHORT) | C5: REAM | D5: 0 | E5: =IFERROR(SUMIFS(SUMMARY!D:D, SUMMARY!B:B, A5, SUMMARY!A:A, "WAREHOUSE"), 0) -> 0 | F5: =IFERROR(SUMIFS(SUMMARY!D:D, SUMMARY!B:B, A5, SUMMARY!A:A, "LAGTANG"), 0) -> 0 | G5: =IFERROR(SUMIFS(SUMMARY!D:D, SUMMARY!B:B, A5, SUMMARY!A:A, "V-RAMA"), 0) -> 0 | H5: =IFERROR(SUMIFS(SUMMARY!D:D, SUMMARY!B:B, A5, SUMMARY!A:A, "BULACAO"), 0) -> 0 | I5: =IFERROR(SUMIFS(SUMMARY!D:D, SUMMARY!B:B, A5, SUMMARY!A:A, "Y3S TALISAY"), 0) -> 1 | J5: =IFERROR(SUMIFS(SUMMARY!D:D, SUMMARY!B:B, A5, SUMMARY!A:A, "MINGLANILLA"), 0) -> 0 | K5: =IFERROR(SUMIFS(SUMMARY!D:D, SUMMARY!B:B, A5, SUMMARY!A:A, "Y3S PARDO"), 0) -> 2 | L5: =IFERROR(SUMIFS(SUMMARY!D:D, SUMMARY!B:B, A5, SUMMARY!A:A, "LAPU-LAPU"), 0) -> 0 | M5: =IFERROR(SUMIFS(SUMMARY!D:D, SUMMARY!B:B, A5, SUMMARY!A:A, "BACAYAN"), 0) -> 1 | N5: =IFERROR(SUMIFS(SUMMARY!D:D, SUMMARY!B:B, A5, SUMMARY!A:A, "SAN FERNANDO MB"), 0) -> 0 | O5: =IFERROR(SUMIFS(SUMMARY!D:D, SUMMARY!B:B, A5, SUMMARY!A:A, "Y3S SAN FERNANDO"), 0) -> 0 | P5: =IFERROR(SUMIFS(SUMMARY!D:D, SUMMARY!B:B, A5, SUMMARY!A:A, "LILOAN"), 0) -> 1 | Q5: =IFERROR(SUMIFS(SUMMARY!D:D, SUMMARY!B:B, A5, SUMMARY!A:A, "CORDOVA MB"), 0) -> 0 | R5: =IFERROR(SUMIFS(SUMMARY!D:D, SUMMARY!B:B, A5, SUMMARY!A:A, "Y3S CORDOVA"), 0) -> 0 | S5: =IFERROR(SUMIFS(SUMMARY!D:D, SUMMARY!B:B, A5, SUMMARY!A:A, "CLARIN"), 0) -> 1 | T5: =IFERROR(SUMIFS(SUMMARY!D:D, SUMMARY!B:B, A5, SUMMARY!A:A, "TOLEDO"), 0) -> 0 | U5: =IFERROR(SUMIFS(SUMMARY!D:D, SUMMARY!B:B, A5, SUMMARY!A:A, "UBAY"), 0) -> 0 | V5: =IFERROR(SUMIFS(SUMMARY!D:D, SUMMARY!B:B, A5, SUMMARY!A:A, "CARMEN"), 0) -> 0 | W5: =IFERROR(SUMIFS(SUMMARY!D:D, SUMMARY!B:B, A5, SUMMARY!A:A, "TUBIGON"), 0) -> 0 | X5: =IFERROR(SUMIFS(SUMMARY!D:D, SUMMARY!B:B, A5, SUMMARY!A:A, "TALIBON"), 0) -> 0 | Y5: =IFERROR(SUMIFS(SUMMARY!D:D, SUMMARY!B:B, A5, SUMMARY!A:A, "BOGO"), 0) -> 0 | Z5: =IFERROR(SUMIFS(SUMMARY!D:D, SUMMARY!B:B, A5, SUMMARY!A:A, "BALAMBAN"), 0) -> 0 | AA5: =IFERROR(SUMIFS(SUMMARY!D:D, SUMMARY!B:B, A5, SUMMARY!A:A, "Y3S BARILI"), 0) -> 0 | AB5: =IFERROR(SUMIFS(SUMMARY!D:D, SUMMARY!B:B, A5, SUMMARY!A:A, "BARILI MB"), 0) -> 0 | AC5: =IFERROR(SUMIFS(SUMMARY!D:D, SUMMARY!B:B, A5, SUMMARY!A:A, "SIERRA BULLONES"), 0) -> 0 | AD5: =IFERROR(SUMIFS(SUMMARY!D:D, SUMMARY!B:B, A5, SUMMARY!A:A, "PITOGO"), 0) -> 0 | AE5: =IFERROR(SUMIFS(SUMMARY!D:D, SUMMARY!B:B, A5, SUMMARY!A:A, "TAYUD CONSOLACION"), 0) -> 1 | AF5: =IFERROR(SUMIFS(SUMMARY!D:D, SUMMARY!B:B, A5, SUMMARY!A:A, "PINAMUNGAJAN"), 0) -> 0 | AG5: =IFERROR(SUMIFS(SUMMARY!D:D, SUMMARY!B:B, A5, SUMMARY!A:A, "CANDIJAY"), 0) -> 0 | AH5: 0 | AI5: =IFERROR(SUMIFS(SUMMARY!D:D, SUMMARY!B:B, A5, SUMMARY!A:A, "CAMOTES"), 0) -> 0 | AJ5: =SUM(D5:AH5) -> 7
A6: ITM005 | B6: BOND PAPER NEWSPRINT (LONG) | C6: REAM | D6: =IFERROR(SUMIFS(SUMMARY!D:D, SUMMARY!B:B, A6, SUMMARY!A:A, "ADMIN"), 0) -> 0 | E6: =IFERROR(SUMIFS(SUMMARY!D:D, SUMMARY!B:B, A6, SUMMARY!A:A, "WAREHOUSE"), 0) -> 0 | F6: =IFERROR(SUMIFS(SUMMARY!D:D, SUMMARY!B:B, A6, SUMMARY!A:A, "LAGTANG"), 0) -> 0 | G6: =IFERROR(SUMIFS(SUMMARY!D:D, SUMMARY!B:B, A6, SUMMARY!A:A, "V-RAMA"), 0) -> 0 | H6: =IFERROR(SUMIFS(SUMMARY!D:D, SUMMARY!B:B, A6, SUMMARY!A:A, "BULACAO"), 0) -> 0 | I6: =IFERROR(SUMIFS(SUMMARY!D:D, SUMMARY!B:B, A6, SUMMARY!A:A, "Y3S TALISAY"), 0) -> 0 | J6: =IFERROR(SUMIFS(SUMMARY!D:D, SUMMARY!B:B, A6, SUMMARY!A:A, "MINGLANILLA"), 0) -> 0 | K6: =IFERROR(SUMIFS(SUMMARY!D:D, SUMMARY!B:B, A6, SUMMARY!A:A, "Y3S PARDO"), 0) -> 2 | L6: =IFERROR(SUMIFS(SUMMARY!D:D, SUMMARY!B:B, A6, SUMMARY!A:A, "LAPU-LAPU"), 0) -> 0 | M6: =IFERROR(SUMIFS(SUMMARY!D:D, SUMMARY!B:B, A6, SUMMARY!A:A, "BACAYAN"), 0) -> 0 | N6: =IFERROR(SUMIFS(SUMMARY!D:D, SUMMARY!B:B, A6, SUMMARY!A:A, "SAN FERNANDO MB"), 0) -> 0 | O6: =IFERROR(SUMIFS(SUMMARY!D:D, SUMMARY!B:B, A6, SUMMARY!A:A, "Y3S SAN FERNANDO"), 0) -> 0 | P6: =IFERROR(SUMIFS(SUMMARY!D:D, SUMMARY!B:B, A6, SUMMARY!A:A, "LILOAN"), 0) -> 0 | Q6: =IFERROR(SUMIFS(SUMMARY!D:D, SUMMARY!B:B, A6, SUMMARY!A:A, "CORDOVA MB"), 0) -> 0 | R6: =IFERROR(SUMIFS(SUMMARY!D:D, SUMMARY!B:B, A6, SUMMARY!A:A, "Y3S CORDOVA"), 0) -> 0 | S6: =IFERROR(SUMIFS(SUMMARY!D:D, SUMMARY!B:B, A6, SUMMARY!A:A, "CLARIN"), 0) -> 1 | T6: =IFERROR(SUMIFS(SUMMARY!D:D, SUMMARY!B:B, A6, SUMMARY!A:A, "TOLEDO"), 0) -> 0 | U6: =IFERROR(SUMIFS(SUMMARY!D:D, SUMMARY!B:B, A6, SUMMARY!A:A, "UBAY"), 0) -> 0 | V6: =IFERROR(SUMIFS(SUMMARY!D:D, SUMMARY!B:B, A6, SUMMARY!A:A, "CARMEN"), 0) -> 0 | W6: =IFERROR(SUMIFS(SUMMARY!D:D, SUMMARY!B:B, A6, SUMMARY!A:A, "TUBIGON"), 0) -> 0 | X6: =IFERROR(SUMIFS(SUMMARY!D:D, SUMMARY!B:B, A6, SUMMARY!A:A, "TALIBON"), 0) -> 0 | Y6: =IFERROR(SUMIFS(SUMMARY!D:D, SUMMARY!B:B, A6, SUMMARY!A:A, "BOGO"), 0) -> 0 | Z6: =IFERROR(SUMIFS(SUMMARY!D:D, SUMMARY!B:B, A6, SUMMARY!A:A, "BALAMBAN"), 0) -> 1 | AA6: =IFERROR(SUMIFS(SUMMARY!D:D, SUMMARY!B:B, A6, SUMMARY!A:A, "Y3S BARILI"), 0) -> 0 | AB6: =IFERROR(SUMIFS(SUMMARY!D:D, SUMMARY!B:B, A6, SUMMARY!A:A, "BARILI MB"), 0) -> 0 | AC6: =IFERROR(SUMIFS(SUMMARY!D:D, SUMMARY!B:B, A6, SUMMARY!A:A, "SIERRA BULLONES"), 0) -> 0 | AD6: =IFERROR(SUMIFS(SUMMARY!D:D, SUMMARY!B:B, A6, SUMMARY!A:A, "PITOGO"), 0) -> 0 | AE6: =IFERROR(SUMIFS(SUMMARY!D:D, SUMMARY!B:B, A6, SUMMARY!A:A, "TAYUD CONSOLACION"), 0) -> 0 | AF6: =IFERROR(SUMIFS(SUMMARY!D:D, SUMMARY!B:B, A6, SUMMARY!A:A, "PINAMUNGAJAN"), 0) -> 0 | AG6: =IFERROR(SUMIFS(SUMMARY!D:D, SUMMARY!B:B, A6, SUMMARY!A:A, "CANDIJAY"), 0) -> 0 | AH6: =IFERROR(SUMIFS(SUMMARY!D:D, SUMMARY!B:B, A6, SUMMARY!A:A, "YATI LILOAN"), 0) -> 0 | AI6: =IFERROR(SUMIFS(SUMMARY!D:D, SUMMARY!B:B, A6, SUMMARY!A:A, "CAMOTES"), 0) -> 0 | AJ6: =SUM(D6:AH6) -> 4
A7: ITM006 | B7: VELLUM PAPER | C7: PC | D7: =IFERROR(SUMIFS(SUMMARY!D:D, SUMMARY!B:B, A7, SUMMARY!A:A, "ADMIN"), 0) -> 0 | E7: =IFERROR(SUMIFS(SUMMARY!D:D, SUMMARY!B:B, A7, SUMMARY!A:A, "WAREHOUSE"), 0) -> 0 | F7: =IFERROR(SUMIFS(SUMMARY!D:D, SUMMARY!B:B, A7, SUMMARY!A:A, "LAGTANG"), 0) -> 45 | G7: =IFERROR(SUMIFS(SUMMARY!D:D, SUMMARY!B:B, A7, SUMMARY!A:A, "V-RAMA"), 0) -> 20 | H7: =IFERROR(SUMIFS(SUMMARY!D:D, SUMMARY!B:B, A7, SUMMARY!A:A, "BULACAO"), 0) -> 0 | I7: =IFERROR(SUMIFS(SUMMARY!D:D, SUMMARY!B:B, A7, SUMMARY!A:A, "Y3S TALISAY"), 0) -> 0 | J7: =IFERROR(SUMIFS(SUMMARY!D:D, SUMMARY!B:B, A7, SUMMARY!A:A, "MINGLANILLA"), 0) -> 30 | K7: =IFERROR(SUMIFS(SUMMARY!D:D, SUMMARY!B:B, A7, SUMMARY!A:A, "Y3S PARDO"), 0) -> 30 | L7: =IFERROR(SUMIFS(SUMMARY!D:D, SUMMARY!B:B, A7, SUMMARY!A:A, "LAPU-LAPU"), 0) -> 0 | M7: =IFERROR(SUMIFS(SUMMARY!D:D, SUMMARY!B:B, A7, SUMMARY!A:A, "BACAYAN"), 0) -> 20 | N7: =IFERROR(SUMIFS(SUMMARY!D:D, SUMMARY!B:B, A7, SUMMARY!A:A, "SAN FERNANDO MB"), 0) -> 0 | O7: =IFERROR(SUMIFS(SUMMARY!D:D, SUMMARY!B:B, A7, SUMMARY!A:A, "Y3S SAN FERNANDO"), 0) -> 0 | P7: =IFERROR(SUMIFS(SUMMARY!D:D, SUMMARY!B:B, A7, SUMMARY!A:A, "LILOAN"), 0) -> 30 | Q7: =IFERROR(SUMIFS(SUMMARY!D:D, SUMMARY!B:B, A7, SUMMARY!A:A, "CORDOVA MB"), 0) -> 10 | R7: =IFERROR(SUMIFS(SUMMARY!D:D, SUMMARY!B:B, A7, SUMMARY!A:A, "Y3S CORDOVA"), 0) -> 70 | S7: =IFERROR(SUMIFS(SUMMARY!D:D, SUMMARY!B:B, A7, SUMMARY!A:A, "CLARIN"), 0) -> 40 | T7: =IFERROR(SUMIFS(SUMMARY!D:D, SUMMARY!B:B, A7, SUMMARY!A:A, "TOLEDO"), 0) -> 30 | U7: =IFERROR(SUMIFS(SUMMARY!D:D, SUMMARY!B:B, A7, SUMMARY!A:A, "UBAY"), 0) -> 20 | V7: =IFERROR(SUMIFS(SUMMARY!D:D, SUMMARY!B:B, A7, SUMMARY!A:A, "CARMEN"), 0) -> 30 | W7: =IFERROR(SUMIFS(SUMMARY!D:D, SUMMARY!B:B, A7, SUMMARY!A:A, "TUBIGON"), 0) -> 30 | X7: =IFERROR(SUMIFS(SUMMARY!D:D, SUMMARY!B:B, A7, SUMMARY!A:A, "TALIBON"), 0) -> 30 | Y7: =IFERROR(SUMIFS(SUMMARY!D:D, SUMMARY!B:B, A7, SUMMARY!A:A, "BOGO"), 0) -> 30 | Z7: =IFERROR(SUMIFS(SUMMARY!D:D, SUMMARY!B:B, A7, SUMMARY!A:A, "BALAMBAN"), 0) -> 15 | AA7: =IFERROR(SUMIFS(SUMMARY!D:D, SUMMARY!B:B, A7, SUMMARY!A:A, "Y3S BARILI"), 0) -> 0 | AB7: =IFERROR(SUMIFS(SUMMARY!D:D, SUMMARY!B:B, A7, SUMMARY!A:A, "BARILI MB"), 0) -> 20 | AC7: =IFERROR(SUMIFS(SUMMARY!D:D, SUMMARY!B:B, A7, SUMMARY!A:A, "SIERRA BULLONES"), 0) -> 0 | AD7: =IFERROR(SUMIFS(SUMMARY!D:D, SUMMARY!B:B, A7, SUMMARY!A:A, "PITOGO"), 0) -> 0 | AE7: =IFERROR(SUMIFS(SUMMARY!D:D, SUMMARY!B:B, A7, SUMMARY!A:A, "TAYUD CONSOLACION"), 0) -> 0 | AF7: =IFERROR(SUMIFS(SUMMARY!D:D, SUMMARY!B:B, A7, SUMMARY!A:A, "PINAMUNGAJAN"), 0) -> 20 | AG7: =IFERROR(SUMIFS(SUMMARY!D:D, SUMMARY!B:B, A7, SUMMARY!A:A, "CANDIJAY"), 0) -> 20 | AH7: =IFERROR(SUMIFS(SUMMARY!D:D, SUMMARY!B:B, A7, SUMMARY!A:A, "YATI LILOAN"), 0) -> 0 | AI7: =IFERROR(SUMIFS(SUMMARY!D:D, SUMMARY!B:B, A7, SUMMARY!A:A, "CAMOTES"), 0) -> 0 | AJ7: =SUM(D7:AH7) -> 540
A8: ITM007 | B8: LOGBOOK VALIANT RECORD (150 & 300P PAGES) | C8: PC | D8: =IFERROR(SUMIFS(SUMMARY!D:D, SUMMARY!B:B, A8, SUMMARY!A:A, "ADMIN"), 0) -> 1 | E8: =IFERROR(SUMIFS(SUMMARY!D:D, SUMMARY!B:B, A8, SUMMARY!A:A, "WAREHOUSE"), 0) -> 0 | F8: =IFERROR(SUMIFS(SUMMARY!D:D, SUMMARY!B:B, A8, SUMMARY!A:A, "LAGTANG"), 0) -> 0 | G8: =IFERROR(SUMIFS(SUMMARY!D:D, SUMMARY!B:B, A8, SUMMARY!A:A, "V-RAMA"), 0) -> 0 | H8: =IFERROR(SUMIFS(SUMMARY!D:D, SUMMARY!B:B, A8, SUMMARY!A:A, "BULACAO"), 0) -> 0 | I8: =IFERROR(SUMIFS(SUMMARY!D:D, SUMMARY!B:B, A8, SUMMARY!A:A, "Y3S TALISAY"), 0) -> 0 | J8: =IFERROR(SUMIFS(SUMMARY!D:D, SUMMARY!B:B, A8, SUMMARY!A:A, "MINGLANILLA"), 0) -> 0 | K8: =IFERROR(SUMIFS(SUMMARY!D:D, SUMMARY!B:B, A8, SUMMARY!A:A, "Y3S PARDO"), 0) -> 0 | L8: =IFERROR(SUMIFS(SUMMARY!D:D, SUMMARY!B:B, A8, SUMMARY!A:A, "LAPU-LAPU"), 0) -> 0 | M8: =IFERROR(SUMIFS(SUMMARY!D:D, SUMMARY!B:B, A8, SUMMARY!A:A, "BACAYAN"), 0) -> 0 | N8: =IFERROR(SUMIFS(SUMMARY!D:D, SUMMARY!B:B, A8, SUMMARY!A:A, "SAN FERNANDO MB"), 0) -> 0 | O8: =IFERROR(SUMIFS(SUMMARY!D:D, SUMMARY!B:B, A8, SUMMARY!A:A, "Y3S SAN FERNANDO"), 0) -> 0 | P8: =IFERROR(SUMIFS(SUMMARY!D:D, SUMMARY!B:B, A8, SUMMARY!A:A, "LILOAN"), 0) -> 1 | Q8: =IFERROR(SUMIFS(SUMMARY!D:D, SUMMARY!B:B, A8, SUMMARY!A:A, "CORDOVA MB"), 0) -> 0 | R8: =IFERROR(SUMIFS(SUMMARY!D:D, SUMMARY!B:B, A8, SUMMARY!A:A, "Y3S CORDOVA"), 0) -> 0 | S8: =IFERROR(SUMIFS(SUMMARY!D:D, SUMMARY!B:B, A8, SUMMARY!A:A, "CLARIN"), 0) -> 0 | T8: =IFERROR(SUMIFS(SUMMARY!D:D, SUMMARY!B:B, A8, SUMMARY!A:A, "TOLEDO"), 0) -> 0 | U8: =IFERROR(SUMIFS(SUMMARY!D:D, SUMMARY!B:B, A8, SUMMARY!A:A, "UBAY"), 0) -> 0 | V8: =IFERROR(SUMIFS(SUMMARY!D:D, SUMMARY!B:B, A8, SUMMARY!A:A, "CARMEN"), 0) -> 0 | W8: =IFERROR(SUMIFS(SUMMARY!D:D, SUMMARY!B:B, A8, SUMMARY!A:A, "TUBIGON"), 0) -> 0 | X8: =IFERROR(SUMIFS(SUMMARY!D:D, SUMMARY!B:B, A8, SUMMARY!A:A, "TALIBON"), 0) -> 0 | Y8: =IFERROR(SUMIFS(SUMMARY!D:D, SUMMARY!B:B, A8, SUMMARY!A:A, "BOGO"), 0) -> 0 | Z8: =IFERROR(SUMIFS(SUMMARY!D:D, SUMMARY!B:B, A8, SUMMARY!A:A, "BALAMBAN"), 0) -> 0 | AA8: =IFERROR(SUMIFS(SUMMARY!D:D, SUMMARY!B:B, A8, SUMMARY!A:A, "Y3S BARILI"), 0) -> 1 | AB8: =IFERROR(SUMIFS(SUMMARY!D:D, SUMMARY!B:B, A8, SUMMARY!A:A, "BARILI MB"), 0) -> 0 | AC8: =IFERROR(SUMIFS(SUMMARY!D:D, SUMMARY!B:B, A8, SUMMARY!A:A, "SIERRA BULLONES"), 0) -> 0 | AD8: =IFERROR(SUMIFS(SUMMARY!D:D, SUMMARY!B:B, A8, SUMMARY!A:A, "PITOGO"), 0) -> 0 | AE8: =IFERROR(SUMIFS(SUMMARY!D:D, SUMMARY!B:B, A8, SUMMARY!A:A, "TAYUD CONSOLACION"), 0) -> 0 | AF8: =IFERROR(SUMIFS(SUMMARY!D:D, SUMMARY!B:B, A8, SUMMARY!A:A, "PINAMUNGAJAN"), 0) -> 0 | AG8: =IFERROR(SUMIFS(SUMMARY!D:D, SUMMARY!B:B, A8, SUMMARY!A:A, "CANDIJAY"), 0) -> 0 | AH8: =IFERROR(SUMIFS(SUMMARY!D:D, SUMMARY!B:B, A8, SUMMARY!A:A, "YATI LILOAN"), 0) -> 0 | AI8: =IFERROR(SUMIFS(SUMMARY!D:D, SUMMARY!B:B, A8, SUMMARY!A:A, "CAMOTES"), 0) -> 0 | AJ8: =SUM(D8:AH8) -> 3
A9: ITM008 | B9: NOTEBOOK | C9: PC | D9: =IFERROR(SUMIFS(SUMMARY!D:D, SUMMARY!B:B, A9, SUMMARY!A:A, "ADMIN"), 0) -> 0 | E9: =IFERROR(SUMIFS(SUMMARY!D:D, SUMMARY!B:B, A9, SUMMARY!A:A, "WAREHOUSE"), 0) -> 0 | F9: =IFERROR(SUMIFS(SUMMARY!D:D, SUMMARY!B:B, A9, SUMMARY!A:A, "LAGTANG"), 0) -> 0 | G9: =IFERROR(SUMIFS(SUMMARY!D:D, SUMMARY!B:B, A9, SUMMARY!A:A, "V-RAMA"), 0) -> 0 | H9: =IFERROR(SUMIFS(SUMMARY!D:D, SUMMARY!B:B, A9, SUMMARY!A:A, "BULACAO"), 0) -> 0 | I9: =IFERROR(SUMIFS(SUMMARY!D:D, SUMMARY!B:B, A9, SUMMARY!A:A, "Y3S TALISAY"), 0) -> 0 | J9: =IFERROR(SUMIFS(SUMMARY!D:D, SUMMARY!B:B, A9, SUMMARY!A:A, "MINGLANILLA"), 0) -> 0 | K9: =IFERROR(SUMIFS(SUMMARY!D:D, SUMMARY!B:B, A9, SUMMARY!A:A, "Y3S PARDO"), 0) -> 0 | L9: =IFERROR(SUMIFS(SUMMARY!D:D, SUMMARY!B:B, A9, SUMMARY!A:A, "LAPU-LAPU"), 0) -> 0 | M9: =IFERROR(SUMIFS(SUMMARY!D:D, SUMMARY!B:B, A9, SUMMARY!A:A, "BACAYAN"), 0) -> 0 | N9: =IFERROR(SUMIFS(SUMMARY!D:D, SUMMARY!B:B, A9, SUMMARY!A:A, "SAN FERNANDO MB"), 0) -> 0 | O9: =IFERROR(SUMIFS(SUMMARY!D:D, SUMMARY!B:B, A9, SUMMARY!A:A, "Y3S SAN FERNANDO"), 0) -> 0 | P9: =IFERROR(SUMIFS(SUMMARY!D:D, SUMMARY!B:B, A9, SUMMARY!A:A, "LILOAN"), 0) -> 0 | Q9: =IFERROR(SUMIFS(SUMMARY!D:D, SUMMARY!B:B, A9, SUMMARY!A:A, "CORDOVA MB"), 0) -> 0 | R9: =IFERROR(SUMIFS(SUMMARY!D:D, SUMMARY!B:B, A9, SUMMARY!A:A, "Y3S CORDOVA"), 0) -> 0 | S9: =IFERROR(SUMIFS(SUMMARY!D:D, SUMMARY!B:B, A9, SUMMARY!A:A, "CLARIN"), 0) -> 0 | T9: =IFERROR(SUMIFS(SUMMARY!D:D, SUMMARY!B:B, A9, SUMMARY!A:A, "TOLEDO"), 0) -> 1 | U9: =IFERROR(SUMIFS(SUMMARY!D:D, SUMMARY!B:B, A9, SUMMARY!A:A, "UBAY"), 0) -> 0 | V9: =IFERROR(SUMIFS(SUMMARY!D:D, SUMMARY!B:B, A9, SUMMARY!A:A, "CARMEN"), 0) -> 0 | W9: =IFERROR(SUMIFS(SUMMARY!D:D, SUMMARY!B:B, A9, SUMMARY!A:A, "TUBIGON"), 0) -> 1 | X9: =IFERROR(SUMIFS(SUMMARY!D:D, SUMMARY!B:B, A9, SUMMARY!A:A, "TALIBON"), 0) -> 0 | Y9: =IFERROR(SUMIFS(SUMMARY!D:D, SUMMARY!B:B, A9, SUMMARY!A:A, "BOGO"), 0) -> 0 | Z9: =IFERROR(SUMIFS(SUMMARY!D:D, SUMMARY!B:B, A9, SUMMARY!A:A, "BALAMBAN"), 0) -> 0 | AA9: =IFERROR(SUMIFS(SUMMARY!D:D, SUMMARY!B:B, A9, SUMMARY!A:A, "Y3S BARILI"), 0) -> 0 | AB9: =IFERROR(SUMIFS(SUMMARY!D:D, SUMMARY!B:B, A9, SUMMARY!A:A, "BARILI MB"), 0) -> 0 | AC9: =IFERROR(SUMIFS(SUMMARY!D:D, SUMMARY!B:B, A9, SUMMARY!A:A, "SIERRA BULLONES"), 0) -> 0 | AD9: =IFERROR(SUMIFS(SUMMARY!D:D, SUMMARY!B:B, A9, SUMMARY!A:A, "PITOGO"), 0) -> 0 | AE9: =IFERROR(SUMIFS(SUMMARY!D:D, SUMMARY!B:B, A9, SUMMARY!A:A, "TAYUD CONSOLACION"), 0) -> 0 | AF9: =IFERROR(SUMIFS(SUMMARY!D:D, SUMMARY!B:B, A9, SUMMARY!A:A, "PINAMUNGAJAN"), 0) -> 0 | AG9: =IFERROR(SUMIFS(SUMMARY!D:D, SUMMARY!B:B, A9, SUMMARY!A:A, "CANDIJAY"), 0) -> 0 | AH9: =IFERROR(SUMIFS(SUMMARY!D:D, SUMMARY!B:B, A9, SUMMARY!A:A, "YATI LILOAN"), 0) -> 0 | AI9: =IFERROR(SUMIFS(SUMMARY!D:D, SUMMARY!B:B, A9, SUMMARY!A:A, "CAMOTES"), 0) -> 0 | AJ9: =SUM(D9:AH9) -> 2
A10: ITM009 | B10: CARBON PAPER (LONG BLUE) | C10: PC | D10: =IFERROR(SUMIFS(SUMMARY!D:D, SUMMARY!B:B, A10, SUMMARY!A:A, "ADMIN"), 0) -> 0 | E10: =IFERROR(SUMIFS(SUMMARY!D:D, SUMMARY!B:B, A10, SUMMARY!A:A, "WAREHOUSE"), 0) -> 0 | F10: =IFERROR(SUMIFS(SUMMARY!D:D, SUMMARY!B:B, A10, SUMMARY!A:A, "LAGTANG"), 0) -> 0 | G10: =IFERROR(SUMIFS(SUMMARY!D:D, SUMMARY!B:B, A10, SUMMARY!A:A, "V-RAMA"), 0) -> 11 | H10: =IFERROR(SUMIFS(SUMMARY!D:D, SUMMARY!B:B, A10, SUMMARY!A:A, "BULACAO"), 0) -> 0 | I10: =IFERROR(SUMIFS(SUMMARY!D:D, SUMMARY!B:B, A10, SUMMARY!A:A, "Y3S TALISAY"), 0) -> 10 | J10: =IFERROR(SUMIFS(SUMMARY!D:D, SUMMARY!B:B, A10, SUMMARY!A:A, "MINGLANILLA"), 0) -> 10 | K10: =IFERROR(SUMIFS(SUMMARY!D:D, SUMMARY!B:B, A10, SUMMARY!A:A, "Y3S PARDO"), 0) -> 0 | L10: =IFERROR(SUMIFS(SUMMARY!D:D, SUMMARY!B:B, A10, SUMMARY!A:A, "LAPU-LAPU"), 0) -> 0 | M10: =IFERROR(SUMIFS(SUMMARY!D:D, SUMMARY!B:B, A10, SUMMARY!A:A, "BACAYAN"), 0) -> 0 | N10: =IFERROR(SUMIFS(SUMMARY!D:D, SUMMARY!B:B, A10, SUMMARY!A:A, "SAN FERNANDO MB"), 0) -> 0 | O10: =IFERROR(SUMIFS(SUMMARY!D:D, SUMMARY!B:B, A10, SUMMARY!A:A, "Y3S SAN FERNANDO"), 0) -> 0 | P10: =IFERROR(SUMIFS(SUMMARY!D:D, SUMMARY!B:B, A10, SUMMARY!A:A, "LILOAN"), 0) -> 10 | Q10: =IFERROR(SUMIFS(SUMMARY!D:D, SUMMARY!B:B, A10, SUMMARY!A:A, "CORDOVA MB"), 0) -> 5 | R10: =IFERROR(SUMIFS(SUMMARY!D:D, SUMMARY!B:B, A10, SUMMARY!A:A, "Y3S CORDOVA"), 0) -> 10 | S10: =IFERROR(SUMIFS(SUMMARY!D:D, SUMMARY!B:B, A10, SUMMARY!A:A, "CLARIN"), 0) -> 10 | T10: =IFERROR(SUMIFS(SUMMARY!D:D, SUMMARY!B:B, A10, SUMMARY!A:A, "TOLEDO"), 0) -> 0 | U10: =IFERROR(SUMIFS(SUMMARY!D:D, SUMMARY!B:B, A10, SUMMARY!A:A, "UBAY"), 0) -> 10 | V10: =IFERROR(SUMIFS(SUMMARY!D:D, SUMMARY!B:B, A10, SUMMARY!A:A, "CARMEN"), 0) -> 0 | W10: =IFERROR(SUMIFS(SUMMARY!D:D, SUMMARY!B:B, A10, SUMMARY!A:A, "TUBIGON"), 0) -> 10 | X10: =IFERROR(SUMIFS(SUMMARY!D:D, SUMMARY!B:B, A10, SUMMARY!A:A, "TALIBON"), 0) -> 0 | Y10: =IFERROR(SUMIFS(SUMMARY!D:D, SUMMARY!B:B, A10, SUMMARY!A:A, "BOGO"), 0) -> 0 | Z10: =IFERROR(SUMIFS(SUMMARY!D:D, SUMMARY!B:B, A10, SUMMARY!A:A, "BALAMBAN"), 0) -> 0 | AA10: =IFERROR(SUMIFS(SUMMARY!D:D, SUMMARY!B:B, A10, SUMMARY!A:A, "Y3S BARILI"), 0) -> 10 | AB10: =IFERROR(SUMIFS(SUMMARY!D:D, SUMMARY!B:B, A10, SUMMARY!A:A, "BARILI MB"), 0) -> 0 | AC10: =IFERROR(SUMIFS(SUMMARY!D:D, SUMMARY!B:B, A10, SUMMARY!A:A, "SIERRA BULLONES"), 0) -> 0 | AD10: =IFERROR(SUMIFS(SUMMARY!D:D, SUMMARY!B:B, A10, SUMMARY!A:A, "PITOGO"), 0) -> 5 | AE10: =IFERROR(SUMIFS(SUMMARY!D:D, SUMMARY!B:B, A10, SUMMARY!A:A, "TAYUD CONSOLACION"), 0) -> 0 | AF10: 0 | AG10: =IFERROR(SUMIFS(SUMMARY!D:D, SUMMARY!B:B, A10, SUMMARY!A:A, "CANDIJAY"), 0) -> 0 | AH10: =IFERROR(SUMIFS(SUMMARY!D:D, SUMMARY!B:B, A10, SUMMARY!A:A, "YATI LILOAN"), 0) -> 10 | AI10: =IFERROR(SUMIFS(SUMMARY!D:D, SUMMARY!B:B, A10, SUMMARY!A:A, "CAMOTES"), 0) -> 0 | AJ10: =SUM(D10:AH10) -> 111
A11: ITM010 | B11: BROWN ENVELOPE (LONG) | C11: PC | D11: =IFERROR(SUMIFS(SUMMARY!D:D, SUMMARY!B:B, A11, SUMMARY!A:A, "ADMIN"), 0) -> 0 | E11: =IFERROR(SUMIFS(SUMMARY!D:D, SUMMARY!B:B, A11, SUMMARY!A:A, "WAREHOUSE"), 0) -> 0 | F11: =IFERROR(SUMIFS(SUMMARY!D:D, SUMMARY!B:B, A11, SUMMARY!A:A, "LAGTANG"), 0) -> 5 | G11: =IFERROR(SUMIFS(SUMMARY!D:D, SUMMARY!B:B, A11, SUMMARY!A:A, "V-RAMA"), 0) -> 0 | H11: =IFERROR(SUMIFS(SUMMARY!D:D, SUMMARY!B:B, A11, SUMMARY!A:A, "BULACAO"), 0) -> 0 | I11: =IFERROR(SUMIFS(SUMMARY!D:D, SUMMARY!B:B, A11, SUMMARY!A:A, "Y3S TALISAY"), 0) -> 15 | J11: =IFERROR(SUMIFS(SUMMARY!D:D, SUMMARY!B:B, A11, SUMMARY!A:A, "MINGLANILLA"), 0) -> 0 | K11: =IFERROR(SUMIFS(SUMMARY!D:D, SUMMARY!B:B, A11, SUMMARY!A:A, "Y3S PARDO"), 0) -> 0 | L11: =IFERROR(SUMIFS(SUMMARY!D:D, SUMMARY!B:B, A11, SUMMARY!A:A, "LAPU-LAPU"), 0) -> 0 | M11: =IFERROR(SUMIFS(SUMMARY!D:D, SUMMARY!B:B, A11, SUMMARY!A:A, "BACAYAN"), 0) -> 0 | N11: =IFERROR(SUMIFS(SUMMARY!D:D, SUMMARY!B:B, A11, SUMMARY!A:A, "SAN FERNANDO MB"), 0) -> 20 | O11: =IFERROR(SUMIFS(SUMMARY!D:D, SUMMARY!B:B, A11, SUMMARY!A:A, "Y3S SAN FERNANDO"), 0) -> 15 | P11: =IFERROR(SUMIFS(SUMMARY!D:D, SUMMARY!B:B, A11, SUMMARY!A:A, "LILOAN"), 0) -> 0 | Q11: =IFERROR(SUMIFS(SUMMARY!D:D, SUMMARY!B:B, A11, SUMMARY!A:A, "CORDOVA MB"), 0) -> 0 | R11: =IFERROR(SUMIFS(SUMMARY!D:D, SUMMARY!B:B, A11, SUMMARY!A:A, "Y3S CORDOVA"), 0) -> 0 | S11: =IFERROR(SUMIFS(SUMMARY!D:D, SUMMARY!B:B, A11, SUMMARY!A:A, "CLARIN"), 0) -> 0 | T11: =IFERROR(SUMIFS(SUMMARY!D:D, SUMMARY!B:B, A11, SUMMARY!A:A, "TOLEDO"), 0) -> 0 | U11: =IFERROR(SUMIFS(SUMMARY!D:D, SUMMARY!B:B, A11, SUMMARY!A:A, "UBAY"), 0) -> 0 | V11: =IFERROR(SUMIFS(SUMMARY!D:D, SUMMARY!B:B, A11, SUMMARY!A:A, "CARMEN"), 0) -> 0 | W11: =IFERROR(SUMIFS(SUMMARY!D:D, SUMMARY!B:B, A11, SUMMARY!A:A, "TUBIGON"), 0) -> 30 | X11: =IFERROR(SUMIFS(SUMMARY!D:D, SUMMARY!B:B, A11, SUMMARY!A:A, "TALIBON"), 0) -> 0 | Y11: =IFERROR(SUMIFS(SUMMARY!D:D, SUMMARY!B:B, A11, SUMMARY!A:A, "BOGO"), 0) -> 0 | Z11: =IFERROR(SUMIFS(SUMMARY!D:D, SUMMARY!B:B, A11, SUMMARY!A:A, "BALAMBAN"), 0) -> 0 | AA11: =IFERROR(SUMIFS(SUMMARY!D:D, SUMMARY!B:B, A11, SUMMARY!A:A, "Y3S BARILI"), 0) -> 0 | AB11: =IFERROR(SUMIFS(SUMMARY!D:D, SUMMARY!B:B, A11, SUMMARY!A:A, "BARILI MB"), 0) -> 0 | AC11: =IFERROR(SUMIFS(SUMMARY!D:D, SUMMARY!B:B, A11, SUMMARY!A:A, "SIERRA BULLONES"), 0) -> 0 | AD11: =IFERROR(SUMIFS(SUMMARY!D:D, SUMMARY!B:B, A11, SUMMARY!A:A, "PITOGO"), 0) -> 0 | AE11: =IFERROR(SUMIFS(SUMMARY!D:D, SUMMARY!B:B, A11, SUMMARY!A:A, "TAYUD CONSOLACION"), 0) -> 0 | AF11: =IFERROR(SUMIFS(SUMMARY!D:D, SUMMARY!B:B, A11, SUMMARY!A:A, "PINAMUNGAJAN"), 0) -> 0 | AG11: =IFERROR(SUMIFS(SUMMARY!D:D, SUMMARY!B:B, A11, SUMMARY!A:A, "CANDIJAY"), 0) -> 0 | AH11: =IFERROR(SUMIFS(SUMMARY!D:D, SUMMARY!B:B, A11, SUMMARY!A:A, "YATI LILOAN"), 0) -> 0 | AI11: =IFERROR(SUMIFS(SUMMARY!D:D, SUMMARY!B:B, A11, SUMMARY!A:A, "CAMOTES"), 0) -> 0 | AJ11: =SUM(D11:AH11) -> 85
A12: ITM011 | B12: BROWN ENVELOPE (SHORT) | C12: PC | D12: =IFERROR(SUMIFS(SUMMARY!D:D, SUMMARY!B:B, A12, SUMMARY!A:A, "ADMIN"), 0) -> 0 | E12: =IFERROR(SUMIFS(SUMMARY!D:D, SUMMARY!B:B, A12, SUMMARY!A:A, "WAREHOUSE"), 0) -> 0 | F12: =IFERROR(SUMIFS(SUMMARY!D:D, SUMMARY!B:B, A12, SUMMARY!A:A, "LAGTANG"), 0) -> 5 | G12: =IFERROR(SUMIFS(SUMMARY!D:D, SUMMARY!B:B, A12, SUMMARY!A:A, "V-RAMA"), 0) -> 0 | H12: =IFERROR(SUMIFS(SUMMARY!D:D, SUMMARY!B:B, A12, SUMMARY!A:A, "BULACAO"), 0) -> 0 | I12: =IFERROR(SUMIFS(SUMMARY!D:D, SUMMARY!B:B, A12, SUMMARY!A:A, "Y3S TALISAY"), 0) -> 20 | J12: =IFERROR(SUMIFS(SUMMARY!D:D, SUMMARY!B:B, A12, SUMMARY!A:A, "MINGLANILLA"), 0) -> 10 | K12: =IFERROR(SUMIFS(SUMMARY!D:D, SUMMARY!B:B, A12, SUMMARY!A:A, "Y3S PARDO"), 0) -> 20 | L12: =IFERROR(SUMIFS(SUMMARY!D:D, SUMMARY!B:B, A12, SUMMARY!A:A, "LAPU-LAPU"), 0) -> 0 | M12: =IFERROR(SUMIFS(SUMMARY!D:D, SUMMARY!B:B, A12, SUMMARY!A:A, "BACAYAN"), 0) -> 10 | N12: =IFERROR(SUMIFS(SUMMARY!D:D, SUMMARY!B:B, A12, SUMMARY!A:A, "SAN FERNANDO MB"), 0) -> 0 | O12: =IFERROR(SUMIFS(SUMMARY!D:D, SUMMARY!B:B, A12, SUMMARY!A:A, "Y3S SAN FERNANDO"), 0) -> 0 | P12: =IFERROR(SUMIFS(SUMMARY!D:D, SUMMARY!B:B, A12, SUMMARY!A:A, "LILOAN"), 0) -> 0 | Q12: =IFERROR(SUMIFS(SUMMARY!D:D, SUMMARY!B:B, A12, SUMMARY!A:A, "CORDOVA MB"), 0) -> 0 | R12: =IFERROR(SUMIFS(SUMMARY!D:D, SUMMARY!B:B, A12, SUMMARY!A:A, "Y3S CORDOVA"), 0) -> 30 | S12: =IFERROR(SUMIFS(SUMMARY!D:D, SUMMARY!B:B, A12, SUMMARY!A:A, "CLARIN"), 0) -> 10 | T12: =IFERROR(SUMIFS(SUMMARY!D:D, SUMMARY!B:B, A12, SUMMARY!A:A, "TOLEDO"), 0) -> 0 | U12: =IFERROR(SUMIFS(SUMMARY!D:D, SUMMARY!B:B, A12, SUMMARY!A:A, "UBAY"), 0) -> 0 | V12: =IFERROR(SUMIFS(SUMMARY!D:D, SUMMARY!B:B, A12, SUMMARY!A:A, "CARMEN"), 0) -> 0 | W12: =IFERROR(SUMIFS(SUMMARY!D:D, SUMMARY!B:B, A12, SUMMARY!A:A, "TUBIGON"), 0) -> 0 | X12: =IFERROR(SUMIFS(SUMMARY!D:D, SUMMARY!B:B, A12, SUMMARY!A:A, "TALIBON"), 0) -> 0 | Y12: =IFERROR(SUMIFS(SUMMARY!D:D, SUMMARY!B:B, A12, SUMMARY!A:A, "BOGO"), 0) -> 10 | Z12: =IFERROR(SUMIFS(SUMMARY!D:D, SUMMARY!B:B, A12, SUMMARY!A:A, "BALAMBAN"), 0) -> 0 | AA12: =IFERROR(SUMIFS(SUMMARY!D:D, SUMMARY!B:B, A12, SUMMARY!A:A, "Y3S BARILI"), 0) -> 0 | AB12: =IFERROR(SUMIFS(SUMMARY!D:D, SUMMARY!B:B, A12, SUMMARY!A:A, "BARILI MB"), 0) -> 0 | AC12: =IFERROR(SUMIFS(SUMMARY!D:D, SUMMARY!B:B, A12, SUMMARY!A:A, "SIERRA BULLONES"), 0) -> 0 | AD12: =IFERROR(SUMIFS(SUMMARY!D:D, SUMMARY!B:B, A12, SUMMARY!A:A, "PITOGO"), 0) -> 0 | AE12: =IFERROR(SUMIFS(SUMMARY!D:D, SUMMARY!B:B, A12, SUMMARY!A:A, "TAYUD CONSOLACION"), 0) -> 0 | AF12: =IFERROR(SUMIFS(SUMMARY!D:D, SUMMARY!B:B, A12, SUMMARY!A:A, "PINAMUNGAJAN"), 0) -> 0 | AG12: =IFERROR(SUMIFS(SUMMARY!D:D, SUMMARY!B:B, A12, SUMMARY!A:A, "CANDIJAY"), 0) -> 0 | AH12: =IFERROR(SUMIFS(SUMMARY!D:D, SUMMARY!B:B, A12, SUMMARY!A:A, "YATI LILOAN"), 0) -> 0 | AI12: =IFERROR(SUMIFS(SUMMARY!D:D, SUMMARY!B:B, A12, SUMMARY!A:A, "CAMOTES"), 0) -> 0 | AJ12: =SUM(D12:AH12) -> 115
A13: ITM012 | B13: BROWN FOLDER (LONG) | C13: PC | D13: =IFERROR(SUMIFS(SUMMARY!D:D, SUMMARY!B:B, A13, SUMMARY!A:A, "ADMIN"), 0) -> 0 | E13: =IFERROR(SUMIFS(SUMMARY!D:D, SUMMARY!B:B, A13, SUMMARY!A:A, "WAREHOUSE"), 0) -> 0 | F13: =IFERROR(SUMIFS(SUMMARY!D:D, SUMMARY!B:B, A13, SUMMARY!A:A, "LAGTANG"), 0) -> 20 | G13: =IFERROR(SUMIFS(SUMMARY!D:D, SUMMARY!B:B, A13, SUMMARY!A:A, "V-RAMA"), 0) -> 20 | H13: =IFERROR(SUMIFS(SUMMARY!D:D, SUMMARY!B:B, A13, SUMMARY!A:A, "BULACAO"), 0) -> 30 | I13: =IFERROR(SUMIFS(SUMMARY!D:D, SUMMARY!B:B, A13, SUMMARY!A:A, "Y3S TALISAY"), 0) -> 40 | J13: =IFERROR(SUMIFS(SUMMARY!D:D, SUMMARY!B:B, A13, SUMMARY!A:A, "MINGLANILLA"), 0) -> 10 | K13: =IFERROR(SUMIFS(SUMMARY!D:D, SUMMARY!B:B, A13, SUMMARY!A:A, "Y3S PARDO"), 0) -> 20 | L13: =IFERROR(SUMIFS(SUMMARY!D:D, SUMMARY!B:B, A13, SUMMARY!A:A, "LAPU-LAPU"), 0) -> 0 | M13: =IFERROR(SUMIFS(SUMMARY!D:D, SUMMARY!B:B, A13, SUMMARY!A:A, "BACAYAN"), 0) -> 30 | N13: =IFERROR(SUMIFS(SUMMARY!D:D, SUMMARY!B:B, A13, SUMMARY!A:A, "SAN FERNANDO MB"), 0) -> 20 | O13: =IFERROR(SUMIFS(SUMMARY!D:D, SUMMARY!B:B, A13, SUMMARY!A:A, "Y3S SAN FERNANDO"), 0) -> 40 | P13: =IFERROR(SUMIFS(SUMMARY!D:D, SUMMARY!B:B, A13, SUMMARY!A:A, "LILOAN"), 0) -> 30 | Q13: =IFERROR(SUMIFS(SUMMARY!D:D, SUMMARY!B:B, A13, SUMMARY!A:A, "CORDOVA MB"), 0) -> 30 | R13: =IFERROR(SUMIFS(SUMMARY!D:D, SUMMARY!B:B, A13, SUMMARY!A:A, "Y3S CORDOVA"), 0) -> 60 | S13: =IFERROR(SUMIFS(SUMMARY!D:D, SUMMARY!B:B, A13, SUMMARY!A:A, "CLARIN"), 0) -> 40 | T13: =IFERROR(SUMIFS(SUMMARY!D:D, SUMMARY!B:B, A13, SUMMARY!A:A, "TOLEDO"), 0) -> 0 | U13: =IFERROR(SUMIFS(SUMMARY!D:D, SUMMARY!B:B, A13, SUMMARY!A:A, "UBAY"), 0) -> 30 | V13: =IFERROR(SUMIFS(SUMMARY!D:D, SUMMARY!B:B, A13, SUMMARY!A:A, "CARMEN"), 0) -> 30 | W13: =IFERROR(SUMIFS(SUMMARY!D:D, SUMMARY!B:B, A13, SUMMARY!A:A, "TUBIGON"), 0) -> 30 | X13: =IFERROR(SUMIFS(SUMMARY!D:D, SUMMARY!B:B, A13, SUMMARY!A:A, "TALIBON"), 0) -> 30 | Y13: =IFERROR(SUMIFS(SUMMARY!D:D, SUMMARY!B:B, A13, SUMMARY!A:A, "BOGO"), 0) -> 30 | Z13: =IFERROR(SUMIFS(SUMMARY!D:D, SUMMARY!B:B, A13, SUMMARY!A:A, "BALAMBAN"), 0) -> 10 | AA13: =IFERROR(SUMIFS(SUMMARY!D:D, SUMMARY!B:B, A13, SUMMARY!A:A, "Y3S BARILI"), 0) -> 20 | AB13: =IFERROR(SUMIFS(SUMMARY!D:D, SUMMARY!B:B, A13, SUMMARY!A:A, "BARILI MB"), 0) -> 20 | AC13: =IFERROR(SUMIFS(SUMMARY!D:D, SUMMARY!B:B, A13, SUMMARY!A:A, "SIERRA BULLONES"), 0) -> 30 | AD13: =IFERROR(SUMIFS(SUMMARY!D:D, SUMMARY!B:B, A13, SUMMARY!A:A, "PITOGO"), 0) -> 20 | AE13: =IFERROR(SUMIFS(SUMMARY!D:D, SUMMARY!B:B, A13, SUMMARY!A:A, "TAYUD CONSOLACION"), 0) -> 20 | AF13: =IFERROR(SUMIFS(SUMMARY!D:D, SUMMARY!B:B, A13, SUMMARY!A:A, "PINAMUNGAJAN"), 0) -> 20 | AG13: =IFERROR(SUMIFS(SUMMARY!D:D, SUMMARY!B:B, A13, SUMMARY!A:A, "CANDIJAY"), 0) -> 30 | AH13: =IFERROR(SUMIFS(SUMMARY!D:D, SUMMARY!B:B, A13, SUMMARY!A:A, "YATI LILOAN"), 0) -> 20 | AI13: =IFERROR(SUMIFS(SUMMARY!D:D, SUMMARY!B:B, A13, SUMMARY!A:A, "CAMOTES"), 0) -> 0 | AJ13: =SUM(D13:AH13) -> 730
A14: ITM013 | B14: BROWN FOLDER (SHORT) | C14: PC | D14: =IFERROR(SUMIFS(SUMMARY!D:D, SUMMARY!B:B, A14, SUMMARY!A:A, "ADMIN"), 0) -> 0 | E14: =IFERROR(SUMIFS(SUMMARY!D:D, SUMMARY!B:B, A14, SUMMARY!A:A, "WAREHOUSE"), 0) -> 0 | F14: =IFERROR(SUMIFS(SUMMARY!D:D, SUMMARY!B:B, A14, SUMMARY!A:A, "LAGTANG"), 0) -> 0 | G14: =IFERROR(SUMIFS(SUMMARY!D:D, SUMMARY!B:B, A14, SUMMARY!A:A, "V-RAMA"), 0) -> 0 | H14: =IFERROR(SUMIFS(SUMMARY!D:D, SUMMARY!B:B, A14, SUMMARY!A:A, "BULACAO"), 0) -> 0 | I14: =IFERROR(SUMIFS(SUMMARY!D:D, SUMMARY!B:B, A14, SUMMARY!A:A, "Y3S TALISAY"), 0) -> 0 | J14: =IFERROR(SUMIFS(SUMMARY!D:D, SUMMARY!B:B, A14, SUMMARY!A:A, "MINGLANILLA"), 0) -> 0 | K14: =IFERROR(SUMIFS(SUMMARY!D:D, SUMMARY!B:B, A14, SUMMARY!A:A, "Y3S PARDO"), 0) -> 0 | L14: =IFERROR(SUMIFS(SUMMARY!D:D, SUMMARY!B:B, A14, SUMMARY!A:A, "LAPU-LAPU"), 0) -> 0 | M14: =IFERROR(SUMIFS(SUMMARY!D:D, SUMMARY!B:B, A14, SUMMARY!A:A, "BACAYAN"), 0) -> 0 | N14: =IFERROR(SUMIFS(SUMMARY!D:D, SUMMARY!B:B, A14, SUMMARY!A:A, "SAN FERNANDO MB"), 0) -> 0 | O14: =IFERROR(SUMIFS(SUMMARY!D:D, SUMMARY!B:B, A14, SUMMARY!A:A, "Y3S SAN FERNANDO"), 0) -> 0 | P14: =IFERROR(SUMIFS(SUMMARY!D:D, SUMMARY!B:B, A14, SUMMARY!A:A, "LILOAN"), 0) -> 0 | Q14: =IFERROR(SUMIFS(SUMMARY!D:D, SUMMARY!B:B, A14, SUMMARY!A:A, "CORDOVA MB"), 0) -> 0 | R14: =IFERROR(SUMIFS(SUMMARY!D:D, SUMMARY!B:B, A14, SUMMARY!A:A, "Y3S CORDOVA"), 0) -> 0 | S14: =IFERROR(SUMIFS(SUMMARY!D:D, SUMMARY!B:B, A14, SUMMARY!A:A, "CLARIN"), 0) -> 0 | T14: =IFERROR(SUMIFS(SUMMARY!D:D, SUMMARY!B:B, A14, SUMMARY!A:A, "TOLEDO"), 0) -> 0 | U14: =IFERROR(SUMIFS(SUMMARY!D:D, SUMMARY!B:B, A14, SUMMARY!A:A, "UBAY"), 0) -> 0 | V14: =IFERROR(SUMIFS(SUMMARY!D:D, SUMMARY!B:B, A14, SUMMARY!A:A, "CARMEN"), 0) -> 0 | W14: =IFERROR(SUMIFS(SUMMARY!D:D, SUMMARY!B:B, A14, SUMMARY!A:A, "TUBIGON"), 0) -> 0 | X14: =IFERROR(SUMIFS(SUMMARY!D:D, SUMMARY!B:B, A14, SUMMARY!A:A, "TALIBON"), 0) -> 0 | Y14: =IFERROR(SUMIFS(SUMMARY!D:D, SUMMARY!B:B, A14, SUMMARY!A:A, "BOGO"), 0) -> 0 | Z14: =IFERROR(SUMIFS(SUMMARY!D:D, SUMMARY!B:B, A14, SUMMARY!A:A, "BALAMBAN"), 0) -> 0 | AA14: =IFERROR(SUMIFS(SUMMARY!D:D, SUMMARY!B:B, A14, SUMMARY!A:A, "Y3S BARILI"), 0) -> 0 | AB14: =IFERROR(SUMIFS(SUMMARY!D:D, SUMMARY!B:B, A14, SUMMARY!A:A, "BARILI MB"), 0) -> 0 | AC14: =IFERROR(SUMIFS(SUMMARY!D:D, SUMMARY!B:B, A14, SUMMARY!A:A, "SIERRA BULLONES"), 0) -> 0 | AD14: =IFERROR(SUMIFS(SUMMARY!D:D, SUMMARY!B:B, A14, SUMMARY!A:A, "PITOGO"), 0) -> 0 | AE14: =IFERROR(SUMIFS(SUMMARY!D:D, SUMMARY!B:B, A14, SUMMARY!A:A, "TAYUD CONSOLACION"), 0) -> 0 | AF14: =IFERROR(SUMIFS(SUMMARY!D:D, SUMMARY!B:B, A14, SUMMARY!A:A, "PINAMUNGAJAN"), 0) -> 0 | AG14: =IFERROR(SUMIFS(SUMMARY!D:D, SUMMARY!B:B, A14, SUMMARY!A:A, "CANDIJAY"), 0) -> 0 | AH14: =IFERROR(SUMIFS(SUMMARY!D:D, SUMMARY!B:B, A14, SUMMARY!A:A, "YATI LILOAN"), 0) -> 0 | AI14: =IFERROR(SUMIFS(SUMMARY!D:D, SUMMARY!B:B, A14, SUMMARY!A:A, "CAMOTES"), 0) -> 0 | AJ14: =SUM(D14:AH14) -> 0
A15: ITM014 | B15: WHITE FOLDER (LONG) | C15: PC | D15: =IFERROR(SUMIFS(SUMMARY!D:D, SUMMARY!B:B, A15, SUMMARY!A:A, "ADMIN"), 0) -> 0 | E15: =IFERROR(SUMIFS(SUMMARY!D:D, SUMMARY!B:B, A15, SUMMARY!A:A, "WAREHOUSE"), 0) -> 0 | F15: =IFERROR(SUMIFS(SUMMARY!D:D, SUMMARY!B:B, A15, SUMMARY!A:A, "LAGTANG"), 0) -> 0 | G15: =IFERROR(SUMIFS(SUMMARY!D:D, SUMMARY!B:B, A15, SUMMARY!A:A, "V-RAMA"), 0) -> 0 | H15: =IFERROR(SUMIFS(SUMMARY!D:D, SUMMARY!B:B, A15, SUMMARY!A:A, "BULACAO"), 0) -> 0 | I15: =IFERROR(SUMIFS(SUMMARY!D:D, SUMMARY!B:B, A15, SUMMARY!A:A, "Y3S TALISAY"), 0) -> 0 | J15: =IFERROR(SUMIFS(SUMMARY!D:D, SUMMARY!B:B, A15, SUMMARY!A:A, "MINGLANILLA"), 0) -> 0 | K15: =IFERROR(SUMIFS(SUMMARY!D:D, SUMMARY!B:B, A15, SUMMARY!A:A, "Y3S PARDO"), 0) -> 0 | L15: =IFERROR(SUMIFS(SUMMARY!D:D, SUMMARY!B:B, A15, SUMMARY!A:A, "LAPU-LAPU"), 0) -> 0 | M15: =IFERROR(SUMIFS(SUMMARY!D:D, SUMMARY!B:B, A15, SUMMARY!A:A, "BACAYAN"), 0) -> 0 | N15: =IFERROR(SUMIFS(SUMMARY!D:D, SUMMARY!B:B, A15, SUMMARY!A:A, "SAN FERNANDO MB"), 0) -> 0 | O15: =IFERROR(SUMIFS(SUMMARY!D:D, SUMMARY!B:B, A15, SUMMARY!A:A, "Y3S SAN FERNANDO"), 0) -> 0 | P15: =IFERROR(SUMIFS(SUMMARY!D:D, SUMMARY!B:B, A15, SUMMARY!A:A, "LILOAN"), 0) -> 0 | Q15: =IFERROR(SUMIFS(SUMMARY!D:D, SUMMARY!B:B, A15, SUMMARY!A:A, "CORDOVA MB"), 0) -> 0 | R15: =IFERROR(SUMIFS(SUMMARY!D:D, SUMMARY!B:B, A15, SUMMARY!A:A, "Y3S CORDOVA"), 0) -> 0 | S15: =IFERROR(SUMIFS(SUMMARY!D:D, SUMMARY!B:B, A15, SUMMARY!A:A, "CLARIN"), 0) -> 0 | T15: =IFERROR(SUMIFS(SUMMARY!D:D, SUMMARY!B:B, A15, SUMMARY!A:A, "TOLEDO"), 0) -> 0 | U15: =IFERROR(SUMIFS(SUMMARY!D:D, SUMMARY!B:B, A15, SUMMARY!A:A, "UBAY"), 0) -> 0 | V15: =IFERROR(SUMIFS(SUMMARY!D:D, SUMMARY!B:B, A15, SUMMARY!A:A, "CARMEN"), 0) -> 0 | W15: =IFERROR(SUMIFS(SUMMARY!D:D, SUMMARY!B:B, A15, SUMMARY!A:A, "TUBIGON"), 0) -> 10 | X15: =IFERROR(SUMIFS(SUMMARY!D:D, SUMMARY!B:B, A15, SUMMARY!A:A, "TALIBON"), 0) -> 0 | Y15: =IFERROR(SUMIFS(SUMMARY!D:D, SUMMARY!B:B, A15, SUMMARY!A:A, "BOGO"), 0) -> 15 | Z15: =IFERROR(SUMIFS(SUMMARY!D:D, SUMMARY!B:B, A15, SUMMARY!A:A, "BALAMBAN"), 0) -> 0 | AA15: =IFERROR(SUMIFS(SUMMARY!D:D, SUMMARY!B:B, A15, SUMMARY!A:A, "Y3S BARILI"), 0) -> 5 | AB15: =IFERROR(SUMIFS(SUMMARY!D:D, SUMMARY!B:B, A15, SUMMARY!A:A, "BARILI MB"), 0) -> 0 | AC15: =IFERROR(SUMIFS(SUMMARY!D:D, SUMMARY!B:B, A15, SUMMARY!A:A, "SIERRA BULLONES"), 0) -> 0 | AD15: =IFERROR(SUMIFS(SUMMARY!D:D, SUMMARY!B:B, A15, SUMMARY!A:A, "PITOGO"), 0) -> 0 | AE15: =IFERROR(SUMIFS(SUMMARY!D:D, SUMMARY!B:B, A15, SUMMARY!A:A, "TAYUD CONSOLACION"), 0) -> 0 | AF15: =IFERROR(SUMIFS(SUMMARY!D:D, SUMMARY!B:B, A15, SUMMARY!A:A, "PINAMUNGAJAN"), 0) -> 10 | AG15: =IFERROR(SUMIFS(SUMMARY!D:D, SUMMARY!B:B, A15, SUMMARY!A:A, "CANDIJAY"), 0) -> 0 | AH15: =IFERROR(SUMIFS(SUMMARY!D:D, SUMMARY!B:B, A15, SUMMARY!A:A, "YATI LILOAN"), 0) -> 0 | AI15: =IFERROR(SUMIFS(SUMMARY!D:D, SUMMARY!B:B, A15, SUMMARY!A:A, "CAMOTES"), 0) -> 0 | AJ15: =SUM(D15:AH15) -> 40
A16: ITM015 | B16: WHITE FOLDER (SHORT) | C16: PC | D16: =IFERROR(SUMIFS(SUMMARY!D:D, SUMMARY!B:B, A16, SUMMARY!A:A, "ADMIN"), 0) -> 0 | E16: =IFERROR(SUMIFS(SUMMARY!D:D, SUMMARY!B:B, A16, SUMMARY!A:A, "WAREHOUSE"), 0) -> 0 | F16: =IFERROR(SUMIFS(SUMMARY!D:D, SUMMARY!B:B, A16, SUMMARY!A:A, "LAGTANG"), 0) -> 5 | G16: =IFERROR(SUMIFS(SUMMARY!D:D, SUMMARY!B:B, A16, SUMMARY!A:A, "V-RAMA"), 0) -> 0 | H16: =IFERROR(SUMIFS(SUMMARY!D:D, SUMMARY!B:B, A16, SUMMARY!A:A, "BULACAO"), 0) -> 0 | I16: =IFERROR(SUMIFS(SUMMARY!D:D, SUMMARY!B:B, A16, SUMMARY!A:A, "Y3S TALISAY"), 0) -> 5 | J16: =IFERROR(SUMIFS(SUMMARY!D:D, SUMMARY!B:B, A16, SUMMARY!A:A, "MINGLANILLA"), 0) -> 0 | K16: =IFERROR(SUMIFS(SUMMARY!D:D, SUMMARY!B:B, A16, SUMMARY!A:A, "Y3S PARDO"), 0) -> 0 | L16: =IFERROR(SUMIFS(SUMMARY!D:D, SUMMARY!B:B, A16, SUMMARY!A:A, "LAPU-LAPU"), 0) -> 0 | M16: =IFERROR(SUMIFS(SUMMARY!D:D, SUMMARY!B:B, A16, SUMMARY!A:A, "BACAYAN"), 0) -> 0 | N16: =IFERROR(SUMIFS(SUMMARY!D:D, SUMMARY!B:B, A16, SUMMARY!A:A, "SAN FERNANDO MB"), 0) -> 0 | O16: =IFERROR(SUMIFS(SUMMARY!D:D, SUMMARY!B:B, A16, SUMMARY!A:A, "Y3S SAN FERNANDO"), 0) -> 15 | P16: =IFERROR(SUMIFS(SUMMARY!D:D, SUMMARY!B:B, A16, SUMMARY!A:A, "LILOAN"), 0) -> 0 | Q16: =IFERROR(SUMIFS(SUMMARY!D:D, SUMMARY!B:B, A16, SUMMARY!A:A, "CORDOVA MB"), 0) -> 0 | R16: =IFERROR(SUMIFS(SUMMARY!D:D, SUMMARY!B:B, A16, SUMMARY!A:A, "Y3S CORDOVA"), 0) -> 0 | S16: =IFERROR(SUMIFS(SUMMARY!D:D, SUMMARY!B:B, A16, SUMMARY!A:A, "CLARIN"), 0) -> 0 | T16: =IFERROR(SUMIFS(SUMMARY!D:D, SUMMARY!B:B, A16, SUMMARY!A:A, "TOLEDO"), 0) -> 0 | U16: =IFERROR(SUMIFS(SUMMARY!D:D, SUMMARY!B:B, A16, SUMMARY!A:A, "UBAY"), 0) -> 0 | V16: =IFERROR(SUMIFS(SUMMARY!D:D, SUMMARY!B:B, A16, SUMMARY!A:A, "CARMEN"), 0) -> 0 | W16: =IFERROR(SUMIFS(SUMMARY!D:D, SUMMARY!B:B, A16, SUMMARY!A:A, "TUBIGON"), 0) -> 10 | X16: =IFERROR(SUMIFS(SUMMARY!D:D, SUMMARY!B:B, A16, SUMMARY!A:A, "TALIBON"), 0) -> 0 | Y16: =IFERROR(SUMIFS(SUMMARY!D:D, SUMMARY!B:B, A16, SUMMARY!A:A, "BOGO"), 0) -> 0 | Z16: =IFERROR(SUMIFS(SUMMARY!D:D, SUMMARY!B:B, A16, SUMMARY!A:A, "BALAMBAN"), 0) -> 0 | AA16: =IFERROR(SUMIFS(SUMMARY!D:D, SUMMARY!B:B, A16, SUMMARY!A:A, "Y3S BARILI"), 0) -> 0 | AB16: =IFERROR(SUMIFS(SUMMARY!D:D, SUMMARY!B:B, A16, SUMMARY!A:A, "BARILI MB"), 0) -> 0 | AC16: =IFERROR(SUMIFS(SUMMARY!D:D, SUMMARY!B:B, A16, SUMMARY!A:A, "SIERRA BULLONES"), 0) -> 0 | AD16: =IFERROR(SUMIFS(SUMMARY!D:D, SUMMARY!B:B, A16, SUMMARY!A:A, "PITOGO"), 0) -> 0 | AE16: =IFERROR(SUMIFS(SUMMARY!D:D, SUMMARY!B:B, A16, SUMMARY!A:A, "TAYUD CONSOLACION"), 0) -> 0 | AF16: =IFERROR(SUMIFS(SUMMARY!D:D, SUMMARY!B:B, A16, SUMMARY!A:A, "PINAMUNGAJAN"), 0) -> 10 | AG16: =IFERROR(SUMIFS(SUMMARY!D:D, SUMMARY!B:B, A16, SUMMARY!A:A, "CANDIJAY"), 0) -> 0 | AH16: =IFERROR(SUMIFS(SUMMARY!D:D, SUMMARY!B:B, A16, SUMMARY!A:A, "YATI LILOAN"), 0) -> 0 | AI16: =IFERROR(SUMIFS(SUMMARY!D:D, SUMMARY!B:B, A16, SUMMARY!A:A, "CAMOTES"), 0) -> 0 | AJ16: =SUM(D16:AH16) -> 45
A17: ITM016 | B17: LETTER SHORT WHITE ENVELOPE | C17: PC | D17: =IFERROR(SUMIFS(SUMMARY!D:D, SUMMARY!B:B, A17, SUMMARY!A:A, "ADMIN"), 0) -> 0 | E17: =IFERROR(SUMIFS(SUMMARY!D:D, SUMMARY!B:B, A17, SUMMARY!A:A, "WAREHOUSE"), 0) -> 0 | F17: =IFERROR(SUMIFS(SUMMARY!D:D, SUMMARY!B:B, A17, SUMMARY!A:A, "LAGTANG"), 0) -> 0 | G17: =IFERROR(SUMIFS(SUMMARY!D:D, SUMMARY!B:B, A17, SUMMARY!A:A, "V-RAMA"), 0) -> 0 | H17: =IFERROR(SUMIFS(SUMMARY!D:D, SUMMARY!B:B, A17, SUMMARY!A:A, "BULACAO"), 0) -> 0 | I17: =IFERROR(SUMIFS(SUMMARY!D:D, SUMMARY!B:B, A17, SUMMARY!A:A, "Y3S TALISAY"), 0) -> 0 | J17: =IFERROR(SUMIFS(SUMMARY!D:D, SUMMARY!B:B, A17, SUMMARY!A:A, "MINGLANILLA"), 0) -> 0 | K17: =IFERROR(SUMIFS(SUMMARY!D:D, SUMMARY!B:B, A17, SUMMARY!A:A, "Y3S PARDO"), 0) -> 0 | L17: =IFERROR(SUMIFS(SUMMARY!D:D, SUMMARY!B:B, A17, SUMMARY!A:A, "LAPU-LAPU"), 0) -> 0 | M17: =IFERROR(SUMIFS(SUMMARY!D:D, SUMMARY!B:B, A17, SUMMARY!A:A, "BACAYAN"), 0) -> 0 | N17: =IFERROR(SUMIFS(SUMMARY!D:D, SUMMARY!B:B, A17, SUMMARY!A:A, "SAN FERNANDO MB"), 0) -> 0 | O17: =IFERROR(SUMIFS(SUMMARY!D:D, SUMMARY!B:B, A17, SUMMARY!A:A, "Y3S SAN FERNANDO"), 0) -> 0 | P17: =IFERROR(SUMIFS(SUMMARY!D:D, SUMMARY!B:B, A17, SUMMARY!A:A, "LILOAN"), 0) -> 10 | Q17: =IFERROR(SUMIFS(SUMMARY!D:D, SUMMARY!B:B, A17, SUMMARY!A:A, "CORDOVA MB"), 0) -> 0 | R17: =IFERROR(SUMIFS(SUMMARY!D:D, SUMMARY!B:B, A17, SUMMARY!A:A, "Y3S CORDOVA"), 0) -> 0 | S17: =IFERROR(SUMIFS(SUMMARY!D:D, SUMMARY!B:B, A17, SUMMARY!A:A, "CLARIN"), 0) -> 0 | T17: =IFERROR(SUMIFS(SUMMARY!D:D, SUMMARY!B:B, A17, SUMMARY!A:A, "TOLEDO"), 0) -> 0 | U17: =IFERROR(SUMIFS(SUMMARY!D:D, SUMMARY!B:B, A17, SUMMARY!A:A, "UBAY"), 0) -> 0 | V17: =IFERROR(SUMIFS(SUMMARY!D:D, SUMMARY!B:B, A17, SUMMARY!A:A, "CARMEN"), 0) -> 0 | W17: =IFERROR(SUMIFS(SUMMARY!D:D, SUMMARY!B:B, A17, SUMMARY!A:A, "TUBIGON"), 0) -> 0 | X17: =IFERROR(SUMIFS(SUMMARY!D:D, SUMMARY!B:B, A17, SUMMARY!A:A, "TALIBON"), 0) -> 0 | Y17: =IFERROR(SUMIFS(SUMMARY!D:D, SUMMARY!B:B, A17, SUMMARY!A:A, "BOGO"), 0) -> 0 | Z17: =IFERROR(SUMIFS(SUMMARY!D:D, SUMMARY!B:B, A17, SUMMARY!A:A, "BALAMBAN"), 0) -> 0 | AA17: =IFERROR(SUMIFS(SUMMARY!D:D, SUMMARY!B:B, A17, SUMMARY!A:A, "Y3S BARILI"), 0) -> 0 | AB17: =IFERROR(SUMIFS(SUMMARY!D:D, SUMMARY!B:B, A17, SUMMARY!A:A, "BARILI MB"), 0) -> 0 | AC17: =IFERROR(SUMIFS(SUMMARY!D:D, SUMMARY!B:B, A17, SUMMARY!A:A, "SIERRA BULLONES"), 0) -> 0 | AD17: =IFERROR(SUMIFS(SUMMARY!D:D, SUMMARY!B:B, A17, SUMMARY!A:A, "PITOGO"), 0) -> 0 | AE17: =IFERROR(SUMIFS(SUMMARY!D:D, SUMMARY!B:B, A17, SUMMARY!A:A, "TAYUD CONSOLACION"), 0) -> 0 | AF17: =IFERROR(SUMIFS(SUMMARY!D:D, SUMMARY!B:B, A17, SUMMARY!A:A, "PINAMUNGAJAN"), 0) -> 0 | AG17: =IFERROR(SUMIFS(SUMMARY!D:D, SUMMARY!B:B, A17, SUMMARY!A:A, "CANDIJAY"), 0) -> 0 | AH17: =IFERROR(SUMIFS(SUMMARY!D:D, SUMMARY!B:B, A17, SUMMARY!A:A, "YATI LILOAN"), 0) -> 0 | AI17: =IFERROR(SUMIFS(SUMMARY!D:D, SUMMARY!B:B, A17, SUMMARY!A:A, "CAMOTES"), 0) -> 0 | AJ17: =SUM(D17:AH17) -> 10
A18: ITM017 | B18: LETTER LONG WHITE ENVELOPE | C18: PC | D18: =IFERROR(SUMIFS(SUMMARY!D:D, SUMMARY!B:B, A18, SUMMARY!A:A, "ADMIN"), 0) -> 0 | E18: =IFERROR(SUMIFS(SUMMARY!D:D, SUMMARY!B:B, A18, SUMMARY!A:A, "WAREHOUSE"), 0) -> 0 | F18: =IFERROR(SUMIFS(SUMMARY!D:D, SUMMARY!B:B, A18, SUMMARY!A:A, "LAGTANG"), 0) -> 0 | G18: =IFERROR(SUMIFS(SUMMARY!D:D, SUMMARY!B:B, A18, SUMMARY!A:A, "V-RAMA"), 0) -> 0 | H18: =IFERROR(SUMIFS(SUMMARY!D:D, SUMMARY!B:B, A18, SUMMARY!A:A, "BULACAO"), 0) -> 0 | I18: =IFERROR(SUMIFS(SUMMARY!D:D, SUMMARY!B:B, A18, SUMMARY!A:A, "Y3S TALISAY"), 0) -> 0 | J18: =IFERROR(SUMIFS(SUMMARY!D:D, SUMMARY!B:B, A18, SUMMARY!A:A, "MINGLANILLA"), 0) -> 0 | K18: =IFERROR(SUMIFS(SUMMARY!D:D, SUMMARY!B:B, A18, SUMMARY!A:A, "Y3S PARDO"), 0) -> 0 | L18: =IFERROR(SUMIFS(SUMMARY!D:D, SUMMARY!B:B, A18, SUMMARY!A:A, "LAPU-LAPU"), 0) -> 0 | M18: =IFERROR(SUMIFS(SUMMARY!D:D, SUMMARY!B:B, A18, SUMMARY!A:A, "BACAYAN"), 0) -> 0 | N18: =IFERROR(SUMIFS(SUMMARY!D:D, SUMMARY!B:B, A18, SUMMARY!A:A, "SAN FERNANDO MB"), 0) -> 0 | O18: =IFERROR(SUMIFS(SUMMARY!D:D, SUMMARY!B:B, A18, SUMMARY!A:A, "Y3S SAN FERNANDO"), 0) -> 10 | P18: =IFERROR(SUMIFS(SUMMARY!D:D, SUMMARY!B:B, A18, SUMMARY!A:A, "LILOAN"), 0) -> 10 | Q18: =IFERROR(SUMIFS(SUMMARY!D:D, SUMMARY!B:B, A18, SUMMARY!A:A, "CORDOVA MB"), 0) -> 0 | R18: =IFERROR(SUMIFS(SUMMARY!D:D, SUMMARY!B:B, A18, SUMMARY!A:A, "Y3S CORDOVA"), 0) -> 0 | S18: =IFERROR(SUMIFS(SUMMARY!D:D, SUMMARY!B:B, A18, SUMMARY!A:A, "CLARIN"), 0) -> 0 | T18: =IFERROR(SUMIFS(SUMMARY!D:D, SUMMARY!B:B, A18, SUMMARY!A:A, "TOLEDO"), 0) -> 0 | U18: =IFERROR(SUMIFS(SUMMARY!D:D, SUMMARY!B:B, A18, SUMMARY!A:A, "UBAY"), 0) -> 0 | V18: =IFERROR(SUMIFS(SUMMARY!D:D, SUMMARY!B:B, A18, SUMMARY!A:A, "CARMEN"), 0) -> 0 | W18: =IFERROR(SUMIFS(SUMMARY!D:D, SUMMARY!B:B, A18, SUMMARY!A:A, "TUBIGON"), 0) -> 0 | X18: =IFERROR(SUMIFS(SUMMARY!D:D, SUMMARY!B:B, A18, SUMMARY!A:A, "TALIBON"), 0) -> 0 | Y18: =IFERROR(SUMIFS(SUMMARY!D:D, SUMMARY!B:B, A18, SUMMARY!A:A, "BOGO"), 0) -> 0 | Z18: =IFERROR(SUMIFS(SUMMARY!D:D, SUMMARY!B:B, A18, SUMMARY!A:A, "BALAMBAN"), 0) -> 0 | AA18: =IFERROR(SUMIFS(SUMMARY!D:D, SUMMARY!B:B, A18, SUMMARY!A:A, "Y3S BARILI"), 0) -> 0 | AB18: =IFERROR(SUMIFS(SUMMARY!D:D, SUMMARY!B:B, A18, SUMMARY!A:A, "BARILI MB"), 0) -> 0 | AC18: =IFERROR(SUMIFS(SUMMARY!D:D, SUMMARY!B:B, A18, SUMMARY!A:A, "SIERRA BULLONES"), 0) -> 0 | AD18: =IFERROR(SUMIFS(SUMMARY!D:D, SUMMARY!B:B, A18, SUMMARY!A:A, "PITOGO"), 0) -> 0 | AE18: =IFERROR(SUMIFS(SUMMARY!D:D, SUMMARY!B:B, A18, SUMMARY!A:A, "TAYUD CONSOLACION"), 0) -> 0 | AF18: =IFERROR(SUMIFS(SUMMARY!D:D, SUMMARY!B:B, A18, SUMMARY!A:A, "PINAMUNGAJAN"), 0) -> 0 | AG18: =IFERROR(SUMIFS(SUMMARY!D:D, SUMMARY!B:B, A18, SUMMARY!A:A, "CANDIJAY"), 0) -> 0 | AH18: =IFERROR(SUMIFS(SUMMARY!D:D, SUMMARY!B:B, A18, SUMMARY!A:A, "YATI LILOAN"), 0) -> 0 | AI18: =IFERROR(SUMIFS(SUMMARY!D:D, SUMMARY!B:B, A18, SUMMARY!A:A, "CAMOTES"), 0) -> 0 | AJ18: =SUM(D18:AH18) -> 20
A19: ITM018 | B19: CARD HOLDER | C19: PC | D19: =IFERROR(SUMIFS(SUMMARY!D:D, SUMMARY!B:B, A19, SUMMARY!A:A, "ADMIN"), 0) -> 0 | E19: =IFERROR(SUMIFS(SUMMARY!D:D, SUMMARY!B:B, A19, SUMMARY!A:A, "WAREHOUSE"), 0) -> 0 | F19: =IFERROR(SUMIFS(SUMMARY!D:D, SUMMARY!B:B, A19, SUMMARY!A:A, "LAGTANG"), 0) -> 0 | G19: =IFERROR(SUMIFS(SUMMARY!D:D, SUMMARY!B:B, A19, SUMMARY!A:A, "V-RAMA"), 0) -> 0 | H19: =IFERROR(SUMIFS(SUMMARY!D:D, SUMMARY!B:B, A19, SUMMARY!A:A, "BULACAO"), 0) -> 0 | I19: =IFERROR(SUMIFS(SUMMARY!D:D, SUMMARY!B:B, A19, SUMMARY!A:A, "Y3S TALISAY"), 0) -> 0 | J19: =IFERROR(SUMIFS(SUMMARY!D:D, SUMMARY!B:B, A19, SUMMARY!A:A, "MINGLANILLA"), 0) -> 0 | K19: =IFERROR(SUMIFS(SUMMARY!D:D, SUMMARY!B:B, A19, SUMMARY!A:A, "Y3S PARDO"), 0) -> 0 | L19: =IFERROR(SUMIFS(SUMMARY!D:D, SUMMARY!B:B, A19, SUMMARY!A:A, "LAPU-LAPU"), 0) -> 0 | M19: =IFERROR(SUMIFS(SUMMARY!D:D, SUMMARY!B:B, A19, SUMMARY!A:A, "BACAYAN"), 0) -> 0 | N19: =IFERROR(SUMIFS(SUMMARY!D:D, SUMMARY!B:B, A19, SUMMARY!A:A, "SAN FERNANDO MB"), 0) -> 0 | O19: =IFERROR(SUMIFS(SUMMARY!D:D, SUMMARY!B:B, A19, SUMMARY!A:A, "Y3S SAN FERNANDO"), 0) -> 0 | P19: =IFERROR(SUMIFS(SUMMARY!D:D, SUMMARY!B:B, A19, SUMMARY!A:A, "LILOAN"), 0) -> 0 | Q19: =IFERROR(SUMIFS(SUMMARY!D:D, SUMMARY!B:B, A19, SUMMARY!A:A, "CORDOVA MB"), 0) -> 0 | R19: =IFERROR(SUMIFS(SUMMARY!D:D, SUMMARY!B:B, A19, SUMMARY!A:A, "Y3S CORDOVA"), 0) -> 0 | S19: =IFERROR(SUMIFS(SUMMARY!D:D, SUMMARY!B:B, A19, SUMMARY!A:A, "CLARIN"), 0) -> 0 | T19: =IFERROR(SUMIFS(SUMMARY!D:D, SUMMARY!B:B, A19, SUMMARY!A:A, "TOLEDO"), 0) -> 0 | U19: =IFERROR(SUMIFS(SUMMARY!D:D, SUMMARY!B:B, A19, SUMMARY!A:A, "UBAY"), 0) -> 0 | V19: =IFERROR(SUMIFS(SUMMARY!D:D, SUMMARY!B:B, A19, SUMMARY!A:A, "CARMEN"), 0) -> 0 | W19: =IFERROR(SUMIFS(SUMMARY!D:D, SUMMARY!B:B, A19, SUMMARY!A:A, "TUBIGON"), 0) -> 0 | X19: =IFERROR(SUMIFS(SUMMARY!D:D, SUMMARY!B:B, A19, SUMMARY!A:A, "TALIBON"), 0) -> 0 | Y19: =IFERROR(SUMIFS(SUMMARY!D:D, SUMMARY!B:B, A19, SUMMARY!A:A, "BOGO"), 0) -> 0 | Z19: =IFERROR(SUMIFS(SUMMARY!D:D, SUMMARY!B:B, A19, SUMMARY!A:A, "BALAMBAN"), 0) -> 0 | AA19: =IFERROR(SUMIFS(SUMMARY!D:D, SUMMARY!B:B, A19, SUMMARY!A:A, "Y3S BARILI"), 0) -> 0 | AB19: =IFERROR(SUMIFS(SUMMARY!D:D, SUMMARY!B:B, A19, SUMMARY!A:A, "BARILI MB"), 0) -> 0 | AC19: =IFERROR(SUMIFS(SUMMARY!D:D, SUMMARY!B:B, A19, SUMMARY!A:A, "SIERRA BULLONES"), 0) -> 0 | AD19: =IFERROR(SUMIFS(SUMMARY!D:D, SUMMARY!B:B, A19, SUMMARY!A:A, "PITOGO"), 0) -> 0 | AE19: =IFERROR(SUMIFS(SUMMARY!D:D, SUMMARY!B:B, A19, SUMMARY!A:A, "TAYUD CONSOLACION"), 0) -> 0 | AF19: =IFERROR(SUMIFS(SUMMARY!D:D, SUMMARY!B:B, A19, SUMMARY!A:A, "PINAMUNGAJAN"), 0) -> 0 | AG19: =IFERROR(SUMIFS(SUMMARY!D:D, SUMMARY!B:B, A19, SUMMARY!A:A, "CANDIJAY"), 0) -> 0 | AH19: =IFERROR(SUMIFS(SUMMARY!D:D, SUMMARY!B:B, A19, SUMMARY!A:A, "YATI LILOAN"), 0) -> 0 | AI19: =IFERROR(SUMIFS(SUMMARY!D:D, SUMMARY!B:B, A19, SUMMARY!A:A, "CAMOTES"), 0) -> 0 | AJ19: =SUM(D19:AH19) -> 0
A20: ITM019 | B20: FLEXSTICK BLACK BALLPEN (0.5) | C20: PC | D20: =IFERROR(SUMIFS(SUMMARY!D:D, SUMMARY!B:B, A20, SUMMARY!A:A, "ADMIN"), 0) -> 1 | E20: =IFERROR(SUMIFS(SUMMARY!D:D, SUMMARY!B:B, A20, SUMMARY!A:A, "WAREHOUSE"), 0) -> 0 | F20: =IFERROR(SUMIFS(SUMMARY!D:D, SUMMARY!B:B, A20, SUMMARY!A:A, "LAGTANG"), 0) -> 6 | G20: =IFERROR(SUMIFS(SUMMARY!D:D, SUMMARY!B:B, A20, SUMMARY!A:A, "V-RAMA"), 0) -> 6 | H20: =IFERROR(SUMIFS(SUMMARY!D:D, SUMMARY!B:B, A20, SUMMARY!A:A, "BULACAO"), 0) -> 5 | I20: =IFERROR(SUMIFS(SUMMARY!D:D, SUMMARY!B:B, A20, SUMMARY!A:A, "Y3S TALISAY"), 0) -> 0 | J20: =IFERROR(SUMIFS(SUMMARY!D:D, SUMMARY!B:B, A20, SUMMARY!A:A, "MINGLANILLA"), 0) -> 6 | K20: =IFERROR(SUMIFS(SUMMARY!D:D, SUMMARY!B:B, A20, SUMMARY!A:A, "Y3S PARDO"), 0) -> 9 | L20: =IFERROR(SUMIFS(SUMMARY!D:D, SUMMARY!B:B, A20, SUMMARY!A:A, "LAPU-LAPU"), 0) -> 0 | M20: =IFERROR(SUMIFS(SUMMARY!D:D, SUMMARY!B:B, A20, SUMMARY!A:A, "BACAYAN"), 0) -> 5 | N20: =IFERROR(SUMIFS(SUMMARY!D:D, SUMMARY!B:B, A20, SUMMARY!A:A, "SAN FERNANDO MB"), 0) -> 3 | O20: =IFERROR(SUMIFS(SUMMARY!D:D, SUMMARY!B:B, A20, SUMMARY!A:A, "Y3S SAN FERNANDO"), 0) -> 5 | P20: =IFERROR(SUMIFS(SUMMARY!D:D, SUMMARY!B:B, A20, SUMMARY!A:A, "LILOAN"), 0) -> 6 | Q20: =IFERROR(SUMIFS(SUMMARY!D:D, SUMMARY!B:B, A20, SUMMARY!A:A, "CORDOVA MB"), 0) -> 0 | R20: =IFERROR(SUMIFS(SUMMARY!D:D, SUMMARY!B:B, A20, SUMMARY!A:A, "Y3S CORDOVA"), 0) -> 13 | S20: =IFERROR(SUMIFS(SUMMARY!D:D, SUMMARY!B:B, A20, SUMMARY!A:A, "CLARIN"), 0) -> 12 | T20: =IFERROR(SUMIFS(SUMMARY!D:D, SUMMARY!B:B, A20, SUMMARY!A:A, "TOLEDO"), 0) -> 0 | U20: =IFERROR(SUMIFS(SUMMARY!D:D, SUMMARY!B:B, A20, SUMMARY!A:A, "UBAY"), 0) -> 12 | V20: =IFERROR(SUMIFS(SUMMARY!D:D, SUMMARY!B:B, A20, SUMMARY!A:A, "CARMEN"), 0) -> 20 | W20: =IFERROR(SUMIFS(SUMMARY!D:D, SUMMARY!B:B, A20, SUMMARY!A:A, "TUBIGON"), 0) -> 12 | X20: =IFERROR(SUMIFS(SUMMARY!D:D, SUMMARY!B:B, A20, SUMMARY!A:A, "TALIBON"), 0) -> 6 | Y20: =IFERROR(SUMIFS(SUMMARY!D:D, SUMMARY!B:B, A20, SUMMARY!A:A, "BOGO"), 0) -> 0 | Z20: =IFERROR(SUMIFS(SUMMARY!D:D, SUMMARY!B:B, A20, SUMMARY!A:A, "BALAMBAN"), 0) -> 7 | AA20: =IFERROR(SUMIFS(SUMMARY!D:D, SUMMARY!B:B, A20, SUMMARY!A:A, "Y3S BARILI"), 0) -> 0 | AB20: =IFERROR(SUMIFS(SUMMARY!D:D, SUMMARY!B:B, A20, SUMMARY!A:A, "BARILI MB"), 0) -> 6 | AC20: =IFERROR(SUMIFS(SUMMARY!D:D, SUMMARY!B:B, A20, SUMMARY!A:A, "SIERRA BULLONES"), 0) -> 6 | AD20: =IFERROR(SUMIFS(SUMMARY!D:D, SUMMARY!B:B, A20, SUMMARY!A:A, "PITOGO"), 0) -> 5 | AE20: =IFERROR(SUMIFS(SUMMARY!D:D, SUMMARY!B:B, A20, SUMMARY!A:A, "TAYUD CONSOLACION"), 0) -> 0 | AF20: =IFERROR(SUMIFS(SUMMARY!D:D, SUMMARY!B:B, A20, SUMMARY!A:A, "PINAMUNGAJAN"), 0) -> 6 | AG20: =IFERROR(SUMIFS(SUMMARY!D:D, SUMMARY!B:B, A20, SUMMARY!A:A, "CANDIJAY"), 0) -> 8 | AH20: =IFERROR(SUMIFS(SUMMARY!D:D, SUMMARY!B:B, A20, SUMMARY!A:A, "YATI LILOAN"), 0) -> 0 | AI20: =IFERROR(SUMIFS(SUMMARY!D:D, SUMMARY!B:B, A20, SUMMARY!A:A, "CAMOTES"), 0) -> 0 | AJ20: =SUM(D20:AH20) -> 165
A21: ITM020 | B21: FLEXSTICK RED BALLPEN (0.5) | C21: PC | D21: =IFERROR(SUMIFS(SUMMARY!D:D, SUMMARY!B:B, A21, SUMMARY!A:A, "ADMIN"), 0) -> 1 | E21: =IFERROR(SUMIFS(SUMMARY!D:D, SUMMARY!B:B, A21, SUMMARY!A:A, "WAREHOUSE"), 0) -> 0 | F21: =IFERROR(SUMIFS(SUMMARY!D:D, SUMMARY!B:B, A21, SUMMARY!A:A, "LAGTANG"), 0) -> 5 | G21: =IFERROR(SUMIFS(SUMMARY!D:D, SUMMARY!B:B, A21, SUMMARY!A:A, "V-RAMA"), 0) -> 0 | H21: =IFERROR(SUMIFS(SUMMARY!D:D, SUMMARY!B:B, A21, SUMMARY!A:A, "BULACAO"), 0) -> 0 | I21: =IFERROR(SUMIFS(SUMMARY!D:D, SUMMARY!B:B, A21, SUMMARY!A:A, "Y3S TALISAY"), 0) -> 2 | J21: =IFERROR(SUMIFS(SUMMARY!D:D, SUMMARY!B:B, A21, SUMMARY!A:A, "MINGLANILLA"), 0) -> 0 | K21: =IFERROR(SUMIFS(SUMMARY!D:D, SUMMARY!B:B, A21, SUMMARY!A:A, "Y3S PARDO"), 0) -> 2 | L21: =IFERROR(SUMIFS(SUMMARY!D:D, SUMMARY!B:B, A21, SUMMARY!A:A, "LAPU-LAPU"), 0) -> 0 | M21: =IFERROR(SUMIFS(SUMMARY!D:D, SUMMARY!B:B, A21, SUMMARY!A:A, "BACAYAN"), 0) -> 5 | N21: =IFERROR(SUMIFS(SUMMARY!D:D, SUMMARY!B:B, A21, SUMMARY!A:A, "SAN FERNANDO MB"), 0) -> 0 | O21: =IFERROR(SUMIFS(SUMMARY!D:D, SUMMARY!B:B, A21, SUMMARY!A:A, "Y3S SAN FERNANDO"), 0) -> 2 | P21: =IFERROR(SUMIFS(SUMMARY!D:D, SUMMARY!B:B, A21, SUMMARY!A:A, "LILOAN"), 0) -> 0 | Q21: =IFERROR(SUMIFS(SUMMARY!D:D, SUMMARY!B:B, A21, SUMMARY!A:A, "CORDOVA MB"), 0) -> 0 | R21: =IFERROR(SUMIFS(SUMMARY!D:D, SUMMARY!B:B, A21, SUMMARY!A:A, "Y3S CORDOVA"), 0) -> 0 | S21: =IFERROR(SUMIFS(SUMMARY!D:D, SUMMARY!B:B, A21, SUMMARY!A:A, "CLARIN"), 0) -> 0 | T21: =IFERROR(SUMIFS(SUMMARY!D:D, SUMMARY!B:B, A21, SUMMARY!A:A, "TOLEDO"), 0) -> 0 | U21: =IFERROR(SUMIFS(SUMMARY!D:D, SUMMARY!B:B, A21, SUMMARY!A:A, "UBAY"), 0) -> 0 | V21: =IFERROR(SUMIFS(SUMMARY!D:D, SUMMARY!B:B, A21, SUMMARY!A:A, "CARMEN"), 0) -> 0 | W21: =IFERROR(SUMIFS(SUMMARY!D:D, SUMMARY!B:B, A21, SUMMARY!A:A, "TUBIGON"), 0) -> 0 | X21: =IFERROR(SUMIFS(SUMMARY!D:D, SUMMARY!B:B, A21, SUMMARY!A:A, "TALIBON"), 0) -> 0 | Y21: =IFERROR(SUMIFS(SUMMARY!D:D, SUMMARY!B:B, A21, SUMMARY!A:A, "BOGO"), 0) -> 0 | Z21: =IFERROR(SUMIFS(SUMMARY!D:D, SUMMARY!B:B, A21, SUMMARY!A:A, "BALAMBAN"), 0) -> 0 | AA21: =IFERROR(SUMIFS(SUMMARY!D:D, SUMMARY!B:B, A21, SUMMARY!A:A, "Y3S BARILI"), 0) -> 0 | AB21: =IFERROR(SUMIFS(SUMMARY!D:D, SUMMARY!B:B, A21, SUMMARY!A:A, "BARILI MB"), 0) -> 3 | AC21: =IFERROR(SUMIFS(SUMMARY!D:D, SUMMARY!B:B, A21, SUMMARY!A:A, "SIERRA BULLONES"), 0) -> 2 | AD21: =IFERROR(SUMIFS(SUMMARY!D:D, SUMMARY!B:B, A21, SUMMARY!A:A, "PITOGO"), 0) -> 0 | AE21: =IFERROR(SUMIFS(SUMMARY!D:D, SUMMARY!B:B, A21, SUMMARY!A:A, "TAYUD CONSOLACION"), 0) -> 0 | AF21: =IFERROR(SUMIFS(SUMMARY!D:D, SUMMARY!B:B, A21, SUMMARY!A:A, "PINAMUNGAJAN"), 0) -> 0 | AG21: =IFERROR(SUMIFS(SUMMARY!D:D, SUMMARY!B:B, A21, SUMMARY!A:A, "CANDIJAY"), 0) -> 8 | AH21: =IFERROR(SUMIFS(SUMMARY!D:D, SUMMARY!B:B, A21, SUMMARY!A:A, "YATI LILOAN"), 0) -> 0 | AI21: =IFERROR(SUMIFS(SUMMARY!D:D, SUMMARY!B:B, A21, SUMMARY!A:A, "CAMOTES"), 0) -> 0 | AJ21: =SUM(D21:AH21) -> 30
A22: ITM021 | B22: WYTEBORD MARKER PILOT (BLACK) | C22: PC | D22: =IFERROR(SUMIFS(SUMMARY!D:D, SUMMARY!B:B, A22, SUMMARY!A:A, "ADMIN"), 0) -> 0 | E22: =IFERROR(SUMIFS(SUMMARY!D:D, SUMMARY!B:B, A22, SUMMARY!A:A, "WAREHOUSE"), 0) -> 0 | F22: =IFERROR(SUMIFS(SUMMARY!D:D, SUMMARY!B:B, A22, SUMMARY!A:A, "LAGTANG"), 0) -> 0 | G22: =IFERROR(SUMIFS(SUMMARY!D:D, SUMMARY!B:B, A22, SUMMARY!A:A, "V-RAMA"), 0) -> 1 | H22: =IFERROR(SUMIFS(SUMMARY!D:D, SUMMARY!B:B, A22, SUMMARY!A:A, "BULACAO"), 0) -> 0 | I22: =IFERROR(SUMIFS(SUMMARY!D:D, SUMMARY!B:B, A22, SUMMARY!A:A, "Y3S TALISAY"), 0) -> 0 | J22: =IFERROR(SUMIFS(SUMMARY!D:D, SUMMARY!B:B, A22, SUMMARY!A:A, "MINGLANILLA"), 0) -> 0 | K22: =IFERROR(SUMIFS(SUMMARY!D:D, SUMMARY!B:B, A22, SUMMARY!A:A, "Y3S PARDO"), 0) -> 0 | L22: =IFERROR(SUMIFS(SUMMARY!D:D, SUMMARY!B:B, A22, SUMMARY!A:A, "LAPU-LAPU"), 0) -> 0 | M22: =IFERROR(SUMIFS(SUMMARY!D:D, SUMMARY!B:B, A22, SUMMARY!A:A, "BACAYAN"), 0) -> 0 | N22: =IFERROR(SUMIFS(SUMMARY!D:D, SUMMARY!B:B, A22, SUMMARY!A:A, "SAN FERNANDO MB"), 0) -> 0 | O22: =IFERROR(SUMIFS(SUMMARY!D:D, SUMMARY!B:B, A22, SUMMARY!A:A, "Y3S SAN FERNANDO"), 0) -> 1 | P22: =IFERROR(SUMIFS(SUMMARY!D:D, SUMMARY!B:B, A22, SUMMARY!A:A, "LILOAN"), 0) -> 0 | Q22: =IFERROR(SUMIFS(SUMMARY!D:D, SUMMARY!B:B, A22, SUMMARY!A:A, "CORDOVA MB"), 0) -> 0 | R22: =IFERROR(SUMIFS(SUMMARY!D:D, SUMMARY!B:B, A22, SUMMARY!A:A, "Y3S CORDOVA"), 0) -> 0 | S22: =IFERROR(SUMIFS(SUMMARY!D:D, SUMMARY!B:B, A22, SUMMARY!A:A, "CLARIN"), 0) -> 0 | T22: =IFERROR(SUMIFS(SUMMARY!D:D, SUMMARY!B:B, A22, SUMMARY!A:A, "TOLEDO"), 0) -> 0 | U22: =IFERROR(SUMIFS(SUMMARY!D:D, SUMMARY!B:B, A22, SUMMARY!A:A, "UBAY"), 0) -> 1 | V22: =IFERROR(SUMIFS(SUMMARY!D:D, SUMMARY!B:B, A22, SUMMARY!A:A, "CARMEN"), 0) -> 1 | W22: =IFERROR(SUMIFS(SUMMARY!D:D, SUMMARY!B:B, A22, SUMMARY!A:A, "TUBIGON"), 0) -> 0 | X22: =IFERROR(SUMIFS(SUMMARY!D:D, SUMMARY!B:B, A22, SUMMARY!A:A, "TALIBON"), 0) -> 0 | Y22: =IFERROR(SUMIFS(SUMMARY!D:D, SUMMARY!B:B, A22, SUMMARY!A:A, "BOGO"), 0) -> 0 | Z22: =IFERROR(SUMIFS(SUMMARY!D:D, SUMMARY!B:B, A22, SUMMARY!A:A, "BALAMBAN"), 0) -> 0 | AA22: =IFERROR(SUMIFS(SUMMARY!D:D, SUMMARY!B:B, A22, SUMMARY!A:A, "Y3S BARILI"), 0) -> 1 | AB22: =IFERROR(SUMIFS(SUMMARY!D:D, SUMMARY!B:B, A22, SUMMARY!A:A, "BARILI MB"), 0) -> 0 | AC22: =IFERROR(SUMIFS(SUMMARY!D:D, SUMMARY!B:B, A22, SUMMARY!A:A, "SIERRA BULLONES"), 0) -> 0 | AD22: =IFERROR(SUMIFS(SUMMARY!D:D, SUMMARY!B:B, A22, SUMMARY!A:A, "PITOGO"), 0) -> 0 | AE22: =IFERROR(SUMIFS(SUMMARY!D:D, SUMMARY!B:B, A22, SUMMARY!A:A, "TAYUD CONSOLACION"), 0) -> 0 | AF22: =IFERROR(SUMIFS(SUMMARY!D:D, SUMMARY!B:B, A22, SUMMARY!A:A, "PINAMUNGAJAN"), 0) -> 0 | AG22: =IFERROR(SUMIFS(SUMMARY!D:D, SUMMARY!B:B, A22, SUMMARY!A:A, "CANDIJAY"), 0) -> 0 | AH22: =IFERROR(SUMIFS(SUMMARY!D:D, SUMMARY!B:B, A22, SUMMARY!A:A, "YATI LILOAN"), 0) -> 0 | AI22: =IFERROR(SUMIFS(SUMMARY!D:D, SUMMARY!B:B, A22, SUMMARY!A:A, "CAMOTES"), 0) -> 0 | AJ22: =SUM(D22:AH22) -> 5
... A106: ITM106 | B106: DOOR MAT | C106: PC | D106: =IFERROR(SUMIFS(SUMMARY!D:D, SUMMARY!B:B, A106, SUMMARY!A:A, "ADMIN"), 0) -> 0 | E106: =IFERROR(SUMIFS(SUMMARY!D:D, SUMMARY!B:B, A106, SUMMARY!A:A, "WAREHOUSE"), 0) -> 0 | F106: =IFERROR(SUMIFS(SUMMARY!D:D, SUMMARY!B:B, A106, SUMMARY!A:A, "LAGTANG"), 0) -> 0 | G106: =IFERROR(SUMIFS(SUMMARY!D:D, SUMMARY!B:B, A106, SUMMARY!A:A, "V-RAMA"), 0) -> 1 | H106: =IFERROR(SUMIFS(SUMMARY!D:D, SUMMARY!B:B, A106, SUMMARY!A:A, "BULACAO"), 0) -> 0 | I106: =IFERROR(SUMIFS(SUMMARY!D:D, SUMMARY!B:B, A106, SUMMARY!A:A, "Y3S TALISAY"), 0) -> 0 | J106: =IFERROR(SUMIFS(SUMMARY!D:D, SUMMARY!B:B, A106, SUMMARY!A:A, "MINGLANILLA"), 0) -> 0 | K106: =IFERROR(SUMIFS(SUMMARY!D:D, SUMMARY!B:B, A106, SUMMARY!A:A, "Y3S PARDO"), 0) -> 0 | L106: =IFERROR(SUMIFS(SUMMARY!D:D, SUMMARY!B:B, A106, SUMMARY!A:A, "LAPU-LAPU"), 0) -> 2 | M106: =IFERROR(SUMIFS(SUMMARY!D:D, SUMMARY!B:B, A106, SUMMARY!A:A, "BACAYAN"), 0) -> 0 | N106: =IFERROR(SUMIFS(SUMMARY!D:D, SUMMARY!B:B, A106, SUMMARY!A:A, "SAN FERNANDO MB"), 0) -> 0 | O106: =IFERROR(SUMIFS(SUMMARY!D:D, SUMMARY!B:B, A106, SUMMARY!A:A, "Y3S SAN FERNANDO"), 0) -> 0 | P106: =IFERROR(SUMIFS(SUMMARY!D:D, SUMMARY!B:B, A106, SUMMARY!A:A, "LILOAN"), 0) -> 0 | Q106: =IFERROR(SUMIFS(SUMMARY!D:D, SUMMARY!B:B, A106, SUMMARY!A:A, "CORDOVA MB"), 0) -> 0 | R106: =IFERROR(SUMIFS(SUMMARY!D:D, SUMMARY!B:B, A106, SUMMARY!A:A, "Y3S CORDOVA"), 0) -> 0 | S106: =IFERROR(SUMIFS(SUMMARY!D:D, SUMMARY!B:B, A106, SUMMARY!A:A, "CLARIN"), 0) -> 0 | T106: =IFERROR(SUMIFS(SUMMARY!D:D, SUMMARY!B:B, A106, SUMMARY!A:A, "TOLEDO"), 0) -> 1 | U106: =IFERROR(SUMIFS(SUMMARY!D:D, SUMMARY!B:B, A106, SUMMARY!A:A, "UBAY"), 0) -> 0 | V106: =IFERROR(SUMIFS(SUMMARY!D:D, SUMMARY!B:B, A106, SUMMARY!A:A, "CARMEN"), 0) -> 1 | W106: =IFERROR(SUMIFS(SUMMARY!D:D, SUMMARY!B:B, A106, SUMMARY!A:A, "TUBIGON"), 0) -> 1 | X106: =IFERROR(SUMIFS(SUMMARY!D:D, SUMMARY!B:B, A106, SUMMARY!A:A, "TALIBON"), 0) -> 0 | Y106: =IFERROR(SUMIFS(SUMMARY!D:D, SUMMARY!B:B, A106, SUMMARY!A:A, "BOGO"), 0) -> 0 | Z106: =IFERROR(SUMIFS(SUMMARY!D:D, SUMMARY!B:B, A106, SUMMARY!A:A, "BALAMBAN"), 0) -> 0 | AA106: =IFERROR(SUMIFS(SUMMARY!D:D, SUMMARY!B:B, A106, SUMMARY!A:A, "Y3S BARILI"), 0) -> 0 | AB106: =IFERROR(SUMIFS(SUMMARY!D:D, SUMMARY!B:B, A106, SUMMARY!A:A, "BARILI MB"), 0) -> 0 | AC106: =IFERROR(SUMIFS(SUMMARY!D:D, SUMMARY!B:B, A106, SUMMARY!A:A, "SIERRA BULLONES"), 0) -> 0 | AD106: =IFERROR(SUMIFS(SUMMARY!D:D, SUMMARY!B:B, A106, SUMMARY!A:A, "PITOGO"), 0) -> 1 | AE106: =IFERROR(SUMIFS(SUMMARY!D:D, SUMMARY!B:B, A106, SUMMARY!A:A, "TAYUD CONSOLACION"), 0) -> 0 | AF106: =IFERROR(SUMIFS(SUMMARY!D:D, SUMMARY!B:B, A106, SUMMARY!A:A, "PINAMUNGAJAN"), 0) -> 0 | AG106: =IFERROR(SUMIFS(SUMMARY!D:D, SUMMARY!B:B, A106, SUMMARY!A:A, "CANDIJAY"), 0) -> 0 | AH106: =IFERROR(SUMIFS(SUMMARY!D:D, SUMMARY!B:B, A106, SUMMARY!A:A, "YATI LILOAN"), 0) -> 0 | AI106: =IFERROR(SUMIFS(SUMMARY!D:D, SUMMARY!B:B, A106, SUMMARY!A:A, "CAMOTES"), 0) -> 0 | AJ106: =SUM(D106:AH106) -> 7

Sheet ADD STOCKS
A1: Item_ID | B1: Description | C1: Total Running Stocks | D1: Unit | E1: Uprice | F1: Total Qty | G1: Status | H1: 45992 | I1: 46235 | J1: 46327
A2: ITM001 | B2: BOND PAPER (LONG) | C2: =F2-'RUNNING STOCKS'!AJ2 -> 34 | D2: REAM | E2: 225 | F2: =SUM(H2:HI2) -> 48 | G2: =IF(C2<>0, "AVAILABLE", "OUT OF STOCKS") -> AVAILABLE | H2: 33 | I2: 15
A3: ITM002 | B3: BOND PAPER (SHORT) | C3: =F3-'RUNNING STOCKS'!AJ3 -> 11 | D3: REAM | E3: 195 | F3: =SUM(H3:HI3) -> 35 | G3: =IF(C3<>0, "AVAILABLE", "OUT OF STOCKS") -> AVAILABLE | H3: 5 | I3: 30
A4: ITM003 | B4: BOND PAPER A4 | C4: =F4-'RUNNING STOCKS'!AJ4 -> 13 | D4: REAM | E4: 205 | F4: =SUM(H4:HI4) -> 23 | G4: =IF(C4<>0, "AVAILABLE", "OUT OF STOCKS") -> AVAILABLE | H4: 18 | I4: 5
A5: ITM004 | B5: BOND PAPER NEWSPRINT (SHORT) | C5: =F5-'RUNNING STOCKS'!AJ5 -> 6 | D5: REAM | E5: 118 | F5: =SUM(H5:HI5) -> 13 | G5: =IF(C5<>0, "AVAILABLE", "OUT OF STOCKS") -> AVAILABLE | H5: 8 | I5: 5
A6: ITM005 | B6: BOND PAPER NEWSPRINT (LONG) | C6: =F6-'RUNNING STOCKS'!AJ6 -> 11 | D6: REAM | E6: 140 | F6: =SUM(H6:HI6) -> 15 | G6: =IF(C6<>0, "AVAILABLE", "OUT OF STOCKS") -> AVAILABLE | H6: 15
A7: ITM006 | B7: VELLUM PAPER | C7: =F7-'RUNNING STOCKS'!AJ7 -> 574 | D7: PC | E7: 250 | F7: =SUM(H7:HI7) -> 1114 | G7: =IF(C7<>0, "AVAILABLE", "OUT OF STOCKS") -> AVAILABLE | H7: 314 | I7: 800
A8: ITM007 | B8: LOGBOOK VALIANT RECORD (150 & 300P PAGES) | C8: =F8-'RUNNING STOCKS'!AJ8 -> 2 | D8: PC | E8: 68 | F8: =SUM(H8:HI8) -> 5 | G8: =IF(C8<>0, "AVAILABLE", "OUT OF STOCKS") -> AVAILABLE | H8: 0 | I8: 5
A9: ITM008 | B9: NOTEBOOK | C9: =F9-'RUNNING STOCKS'!AJ9 -> 8 | D9: PC | F9: =SUM(H9:HI9) -> 10 | G9: =IF(C9<>0, "AVAILABLE", "OUT OF STOCKS") -> AVAILABLE | H9: 0 | I9: 10
A10: ITM009 | B10: CARBON PAPER (LONG BLUE) | C10: =F10-'RUNNING STOCKS'!AJ10 -> 156 | D10: PC | E10: 725 | F10: =SUM(H10:HI10) -> 267 | G10: =IF(C10<>0, "AVAILABLE", "OUT OF STOCKS") -> AVAILABLE | H10: 67 | I10: 200
A11: ITM010 | B11: BROWN ENVELOPE (LONG) | C11: =F11-'RUNNING STOCKS'!AJ11 -> 65 | D11: PC | E11: 300 | F11: =SUM(H11:HI11) -> 150 | G11: =IF(C11<>0, "AVAILABLE", "OUT OF STOCKS") -> AVAILABLE | H11: 0 | I11: 150
A12: ITM011 | B12: BROWN ENVELOPE (SHORT) | C12: =F12-'RUNNING STOCKS'!AJ12 -> 150 | D12: PC | E12: 300 | F12: =SUM(H12:HI12) -> 265 | G12: =IF(C12<>0, "AVAILABLE", "OUT OF STOCKS") -> AVAILABLE | H12: 115 | I12: 150
A13: ITM012 | B13: BROWN FOLDER (LONG) | C13: =F13-'RUNNING STOCKS'!AJ13 -> 114 | D13: PC | E13: 600 | F13: =SUM(H13:HI13) -> 844 | G13: =IF(C13<>0, "AVAILABLE", "OUT OF STOCKS") -> AVAILABLE | H13: 244 | I13: 600
A14: ITM013 | B14: BROWN FOLDER (SHORT) | C14: =F14-'RUNNING STOCKS'!AJ14 -> 0 | D14: PC | F14: =SUM(H14:HI14) -> 0 | G14: =IF(C14<>0, "AVAILABLE", "OUT OF STOCKS") -> OUT OF STOCKS | H14: 0
A15: ITM014 | B15: WHITE FOLDER (LONG) | C15: =F15-'RUNNING STOCKS'!AJ15 -> 130 | D15: PC | F15: =SUM(H15:HI15) -> 170 | G15: =IF(C15<>0, "AVAILABLE", "OUT OF STOCKS") -> AVAILABLE | H15: 20 | I15: 150
A16: ITM015 | B16: WHITE FOLDER (SHORT) | C16: =F16-'RUNNING STOCKS'!AJ16 -> 105 | D16: PC | F16: =SUM(H16:HI16) -> 150 | G16: =IF(C16<>0, "AVAILABLE", "OUT OF STOCKS") -> AVAILABLE | H16: 0 | I16: 150
A17: ITM016 | B17: LETTER SHORT WHITE ENVELOPE | C17: =F17-'RUNNING STOCKS'!AJ17 -> 490 | D17: PC | F17: =SUM(H17:HI17) -> 500 | G17: =IF(C17<>0, "AVAILABLE", "OUT OF STOCKS") -> AVAILABLE | H17: 0 | I17: 500
A18: ITM017 | B18: LETTER LONG WHITE ENVELOPE | C18: =F18-'RUNNING STOCKS'!AJ18 -> 630 | D18: PC | F18: =SUM(H18:HI18) -> 650 | G18: =IF(C18<>0, "AVAILABLE", "OUT OF STOCKS") -> AVAILABLE | H18: 150 | I18: 500
A19: ITM018 | B19: CARD HOLDER | C19: =F19-'RUNNING STOCKS'!AJ19 -> 3 | D19: PC | E19: 30 | F19: =SUM(H19:HI19) -> 3 | G19: =IF(C19<>0, "AVAILABLE", "OUT OF STOCKS") -> AVAILABLE | H19: 3
A20: ITM019 | B20: FLEXSTICK BLACK BALLPEN (0.5) | C20: =F20-'RUNNING STOCKS'!AJ20 -> 137 | D20: PC | E20: 76 | F20: =SUM(H20:HI20) -> 302 | G20: =IF(C20<>0, "AVAILABLE", "OUT OF STOCKS") -> AVAILABLE | H20: 2 | I20: 300
A21: ITM020 | B21: FLEXSTICK RED BALLPEN (0.5) | C21: =F21-'RUNNING STOCKS'!AJ21 -> 78 | D21: PC | E21: 76 | F21: =SUM(H21:HI21) -> 108 | G21: =IF(C21<>0, "AVAILABLE", "OUT OF STOCKS") -> AVAILABLE | H21: 108
A22: ITM021 | B22: WYTEBORD MARKER PILOT (BLACK) | C22: =F22-'RUNNING STOCKS'!AJ22 -> 1 | D22: PC | E22: 165 | F22: =SUM(H22:HI22) -> 6 | G22: =IF(C22<>0, "AVAILABLE", "OUT OF STOCKS") -> AVAILABLE | H22: 1 | I22: 5
A23: ITM022 | B23: WYTEBORD MARKER PILOT (RED) | C23: =F23-'RUNNING STOCKS'!AJ23 -> 2 | D23: PC | E23: 165 | F23: =SUM(H23:HI23) -> 3 | G23: =IF(C23<>0, "AVAILABLE", "OUT OF STOCKS") -> AVAILABLE | H23: 3
A24: ITM023 | B24: HIGHLIGHTER | C24: =F24-'RUNNING STOCKS'!AJ24 -> 8 | D24: PC | E24: 35 | F24: =SUM(H24:HI24) -> 40 | G24: =IF(C24<>0, "AVAILABLE", "OUT OF STOCKS") -> AVAILABLE | H24: 20 | I24: 20
A25: ITM024 | B25: PENCIL | C25: =F25-'RUNNING STOCKS'!AJ25 -> 7 | D25: PC | E25: 7 | F25: =SUM(H25:HI25) -> 11 | G25: =IF(C25<>0, "AVAILABLE", "OUT OF STOCKS") -> AVAILABLE | H25: 11
A26: ITM025 | B26: SHARPENER | C26: =F26-'RUNNING STOCKS'!AJ26 -> 19 | D26: PC | F26: =SUM(H26:HI26) -> 21 | G26: =IF(C26<>0, "AVAILABLE", "OUT OF STOCKS") -> AVAILABLE | H26: 21
A27: ITM026 | B27: ERASER | C27: =F27-'RUNNING STOCKS'!AJ27 -> 0 | D27: PC | F27: =SUM(H27:HI27) -> 0 | G27: =IF(C27<>0, "AVAILABLE", "OUT OF STOCKS") -> OUT OF STOCKS | H27: 0
A28: ITM027 | B28: CORRECTION TAPE | C28: =F28-'RUNNING STOCKS'!AJ28 -> 3 | D28: PC | E28: 18 | F28: =SUM(H28:HI28) -> 39 | G28: =IF(C28<>0, "AVAILABLE", "OUT OF STOCKS") -> AVAILABLE | H28: 24 | I28: 15
A29: ITM028 | B29: CANDIES | C29: =F29-'RUNNING STOCKS'!AJ29 -> 40 | D29: PC | E29: 41 | F29: =SUM(H29:HI29) -> 200 | G29: =IF(C29<>0, "AVAILABLE", "OUT OF STOCKS") -> AVAILABLE | H29: 100 | J29: 100
A30: ITM029 | B30: PUNCHER | C30: =F30-'RUNNING STOCKS'!AJ30 -> 4 | D30: PC | E30: 175 | F30: =SUM(H30:HI30) -> 4 | G30: =IF(C30<>0, "AVAILABLE", "OUT OF STOCKS") -> AVAILABLE | H30: 4
A31: ITM030 | B31: STAPLER | C31: =F31-'RUNNING STOCKS'!AJ31 -> 8 | D31: PC | E31: 120 | F31: =SUM(H31:HI31) -> 9 | G31: =IF(C31<>0, "AVAILABLE", "OUT OF STOCKS") -> AVAILABLE | H31: 9
A32: ITM031 | B32: SCISSORS | C32: =F32-'RUNNING STOCKS'!AJ32 -> 1 | D32: PC | E32: 45 | F32: =SUM(H32:HI32) -> 4 | G32: =IF(C32<>0, "AVAILABLE", "OUT OF STOCKS") -> AVAILABLE | H32: 0 | I32: 4
A33: ITM032 | B33: GLUE | C33: =F33-'RUNNING STOCKS'!AJ33 -> 6 | D33: PC | F33: =SUM(H33:HI33) -> 9 | G33: =IF(C33<>0, "AVAILABLE", "OUT OF STOCKS") -> AVAILABLE | H33: 1 | I33: 8
A34: ITM033 | B34: RULER | C34: =F34-'RUNNING STOCKS'!AJ34 -> 7 | D34: PC | E34: 6 | F34: =SUM(H34:HI34) -> 8 | G34: =IF(C34<>0, "AVAILABLE", "OUT OF STOCKS") -> AVAILABLE | H34: 8
A35: ITM034 | B35: CALCULATOR MX-12B | C35: =F35-'RUNNING STOCKS'!AJ35 -> 4 | D35: PC | F35: =SUM(H35:HI35) -> 5 | G35: =IF(C35<>0, "AVAILABLE", "OUT OF STOCKS") -> AVAILABLE | H35: 0 | I35: 5
A36: ITM035 | B36: TAPE DISPENSER BIG | C36: =F36-'RUNNING STOCKS'!AJ36 -> 0 | D36: PC | E36: 120 | F36: =SUM(H36:HI36) -> 4 | G36: =IF(C36<>0, "AVAILABLE", "OUT OF STOCKS") -> OUT OF STOCKS | H36: 0 | I36: 4
A37: ITM036 | B37: SCOTCH TAPE (1 INCH) | C37: =F37-'RUNNING STOCKS'!AJ37 -> 6 | D37: PC | F37: =SUM(H37:HI37) -> 30 | G37: =IF(C37<>0, "AVAILABLE", "OUT OF STOCKS") -> AVAILABLE | H37: 0 | I37: 30
A38: ITM037 | B38: SCOTCH TAPE (2 INCH) | C38: =F38-'RUNNING STOCKS'!AJ38 -> 0 | D38: PC | F38: =SUM(H38:HI38) -> 0 | G38: =IF(C38<>0, "AVAILABLE", "OUT OF STOCKS") -> OUT OF STOCKS | H38: 0
A39: ITM038 | B39: MASKING TAPE | C39: =F39-'RUNNING STOCKS'!AJ39 -> 15 | D39: PC | E39: 35 | F39: =SUM(H39:HI39) -> 37 | G39: =IF(C39<>0, "AVAILABLE", "OUT OF STOCKS") -> AVAILABLE | H39: 7 | I39: 30
A40: ITM039 | B40: PACKAGING TAPE BROWN | C40: =F40-'RUNNING STOCKS'!AJ40 -> 0 | D40: PC | E40: 49 | F40: =SUM(H40:HI40) -> 5 | G40: =IF(C40<>0, "AVAILABLE", "OUT OF STOCKS") -> OUT OF STOCKS | H40: 0 | I40: 5
A41: ITM040 | B41: DOUBLE-SIDED TAPE (1 INCH) | C41: =F41-'RUNNING STOCKS'!AJ41 -> 4 | D41: PC | E41: 25 | F41: =SUM(H41:HI41) -> 20 | G41: =IF(C41<>0, "AVAILABLE", "OUT OF STOCKS") -> AVAILABLE | H41: 20
A42: ITM041 | B42: DUCT TAPE | C42: =F42-'RUNNING STOCKS'!AJ42 -> 0 | D42: PC | E42: 108 | F42: =SUM(H42:HI42) -> 3 | G42: =IF(C42<>0, "AVAILABLE", "OUT OF STOCKS") -> OUT OF STOCKS | H42: 3
A43: ITM043 | B43: TYPEWRITER BLACK NYLON | C43: =F43-'RUNNING STOCKS'!AJ43 -> 7 | D43: PC | F43: =SUM(H43:HI43) -> 10 | G43: =IF(C43<>0, "AVAILABLE", "OUT OF STOCKS") -> AVAILABLE | H43: 0 | I43: 10
A44: ITM044 | B44: INK EPSON 003 (YELLOW) | C44: =F44-'RUNNING STOCKS'!AJ44 -> 5 | D44: PC | F44: =SUM(H44:HI44) -> 5 | G44: =IF(C44<>0, "AVAILABLE", "OUT OF STOCKS") -> AVAILABLE | H44: 5
A45: ITM045 | B45: INK EPSON 003 (MAGENTA) | C45: =F45-'RUNNING STOCKS'!AJ45 -> 3 | D45: PC | F45: =SUM(H45:HI45) -> 3 | G45: =IF(C45<>0, "AVAILABLE", "OUT OF STOCKS") -> AVAILABLE | H45: 3
A46: ITM046 | B46: INK EPSON 003 (CYAN) | C46: =F46-'RUNNING STOCKS'!AJ46 -> 5 | D46: PC | F46: =SUM(H46:HI46) -> 5 | G46: =IF(C46<>0, "AVAILABLE", "OUT OF STOCKS") -> AVAILABLE | H46: 5
A47: ITM047 | B47: INK EPSON 003 (BLACK) | C47: =F47-'RUNNING STOCKS'!AJ47 -> 2 | D47: PC | F47: =SUM(H47:HI47) -> 3 | G47: =IF(C47<>0, "AVAILABLE", "OUT OF STOCKS") -> AVAILABLE | H47: 3
A48: ITM048 | B48: INK BROTHER BT5000Y | C48: =F48-'RUNNING STOCKS'!AJ48 -> 0 | D48: PC | F48: =SUM(H48:HI48) -> 0 | G48: =IF(C48<>0, "AVAILABLE", "OUT OF STOCKS") -> OUT OF STOCKS
A49: ITM049 | B49: INK BROTHER BT5000M | C49: =F49-'RUNNING STOCKS'!AJ49 -> 0 | D49: PC | F49: =SUM(H49:HI49) -> 0 | G49: =IF(C49<>0, "AVAILABLE", "OUT OF STOCKS") -> OUT OF STOCKS
A50: ITM050 | B50: INK BROTHER BT5000C | C50: =F50-'RUNNING STOCKS'!AJ50 -> 0 | D50: PC | F50: =SUM(H50:HI50) -> 0 | G50: =IF(C50<>0, "AVAILABLE", "OUT OF STOCKS") -> OUT OF STOCKS
A51: ITM051 | B51: INK BROTHER BTD60BK | C51: =F51-'RUNNING STOCKS'!AJ51 -> 0 | D51: PC | F51: =SUM(H51:HI51) -> 0 | G51: =IF(C51<>0, "AVAILABLE", "OUT OF STOCKS") -> OUT OF STOCKS
A52: ITM052 | B52: INK HP (YELLOW | C52: =F52-'RUNNING STOCKS'!AJ52 -> 0 | D52: PC | F52: =SUM(H52:HI52) -> 0 | G52: =IF(C52<>0, "AVAILABLE", "OUT OF STOCKS") -> OUT OF STOCKS
A53: ITM053 | B53: INK HP (MAGENTA) | C53: =F53-'RUNNING STOCKS'!AJ53 -> 0 | D53: PC | F53: =SUM(H53:HI53) -> 0 | G53: =IF(C53<>0, "AVAILABLE", "OUT OF STOCKS") -> OUT OF STOCKS
A54: ITM054 | B54: INK HP (CYAN) | C54: =F54-'RUNNING STOCKS'!AJ54 -> 0 | D54: PC | F54: =SUM(H54:HI54) -> 0 | G54: =IF(C54<>0, "AVAILABLE", "OUT OF STOCKS") -> OUT OF STOCKS
A55: ITM055 | B55: INK HP (BLACK) | C55: =F55-'RUNNING STOCKS'!AJ55 -> 0 | D55: PC | F55: =SUM(H55:HI55) -> 0 | G55: =IF(C55<>0, "AVAILABLE", "OUT OF STOCKS") -> OUT OF STOCKS
A56: ITM056 | B56: PRIDE SOAP POWDER | C56: =F56-'RUNNING STOCKS'!AJ56 -> 165 | D56: PC | E56: 27 | F56: =SUM(H56:HI56) -> 366 | G56: =IF(C56<>0, "AVAILABLE", "OUT OF STOCKS") -> AVAILABLE | H56: 126 | J56: 240
A57: ITM057 | B57: STAMP PAD INK BLACK 30ML | C57: =F57-'RUNNING STOCKS'!AJ57 -> 0 | D57: PC | F57: =SUM(H57:HI57) -> 1 | G57: =IF(C57<>0, "AVAILABLE", "OUT OF STOCKS") -> OUT OF STOCKS | H57: 1
A58: ITM058 | B58: STAMP PAD INK BLUE 30ML | C58: =F58-'RUNNING STOCKS'!AJ58 -> 0 | D58: PC | F58: =SUM(H58:HI58) -> 2 | G58: =IF(C58<>0, "AVAILABLE", "OUT OF STOCKS") -> OUT OF STOCKS | H58: 2
A59: ITM059 | B59: STAMP PAD INK RED 30ML | C59: =F59-'RUNNING STOCKS'!AJ59 -> 3 | D59: PC | F59: =SUM(H59:HI59) -> 3 | G59: =IF(C59<>0, "AVAILABLE", "OUT OF STOCKS") -> AVAILABLE | H59: 3
A60: ITM060 | B60: SUPER COLOR MARKER PILOT (BLACK) | C60: =F60-'RUNNING STOCKS'!AJ60 -> 6 | D60: PC | E60: 165 | F60: =SUM(H60:HI60) -> 10 | G60: =IF(C60<>0, "AVAILABLE", "OUT OF STOCKS") -> AVAILABLE | H60: 5 | I60: 5
A61: ITM061 | B61: JOY | C61: =F61-'RUNNING STOCKS'!AJ61 -> 39 | D61: PC | E61: 12 | F61: =SUM(H61:HI61) -> 95 | G61: =IF(C61<>0, "AVAILABLE", "OUT OF STOCKS") -> AVAILABLE | H61: 23 | J61: 72
A62: ITM062 | B62: DOWNY | C62: =F62-'RUNNING STOCKS'!AJ62 -> 9 | D62: PC | E62: 38 | F62: =SUM(H62:HI62) -> 54 | G62: =IF(C62<>0, "AVAILABLE", "OUT OF STOCKS") -> AVAILABLE | H62: 36 | J62: 18
A63: ITM063 | B63: SAFEGUARD SOAP | C63: =F63-'RUNNING STOCKS'!AJ63 -> 8 | D63: PC | F63: =SUM(H63:HI63) -> 18 | G63: =IF(C63<>0, "AVAILABLE", "OUT OF STOCKS") -> AVAILABLE | H63: 4 | J63: 14
A64: ITM064 | B64: STICKY NOTES 2X2 A02 | C64: =F64-'RUNNING STOCKS'!AJ64 -> 4 | D64: PAD | E64: 47 | F64: =SUM(H64:HI64) -> 23 | G64: =IF(C64<>0, "AVAILABLE", "OUT OF STOCKS") -> AVAILABLE | H64: 3 | I64: 20
A65: ITM065 | B65: STICKY NOTES A03 | C65: =F65-'RUNNING STOCKS'!AJ65 -> 0 | D65: PAD | F65: =SUM(H65:HI65) -> 0 | G65: =IF(C65<>0, "AVAILABLE", "OUT OF STOCKS") -> OUT OF STOCKS
A66: ITM066 | B66: STICKY NOTES A05 | C66: =F66-'RUNNING STOCKS'!AJ66 -> 0 | D66: PAD | F66: =SUM(H66:HI66) -> 0 | G66: =IF(C66<>0, "AVAILABLE", "OUT OF STOCKS") -> OUT OF STOCKS
A67: ITM067 | B67: FASTENER | C67: =F67-'RUNNING STOCKS'!AJ67 -> 16 | D67: BOX | F67: =SUM(H67:HI67) -> 27 | G67: =IF(C67<>0, "AVAILABLE", "OUT OF STOCKS") -> AVAILABLE | H67: 7 | I67: 20
A68: ITM068 | B68: PAPER CLIPS 50MM | C68: =F68-'RUNNING STOCKS'!AJ68 -> 10 | D68: BOX | F68: =SUM(H68:HI68) -> 15 | G68: =IF(C68<>0, "AVAILABLE", "OUT OF STOCKS") -> AVAILABLE | H68: 15
A69: ITM069 | B69: PAPER CLIPS JUMBO | C69: =F69-'RUNNING STOCKS'!AJ69 -> 0 | D69: BOX | F69: =SUM(H69:HI69) -> 0 | G69: =IF(C69<>0, "AVAILABLE", "OUT OF STOCKS") -> OUT OF STOCKS
A70: ITM070 | B70: BINDER CLIPS 2 INCHES | C70: =F70-'RUNNING STOCKS'!AJ70 -> 8 | D70: BOX | F70: =SUM(H70:HI70) -> 9 | G70: =IF(C70<>0, "AVAILABLE", "OUT OF STOCKS") -> AVAILABLE | H70: 6 | I70: 3
A71: ITM071 | B71: BINDER CLIPS 1 5/8 41MM | C71: =F71-'RUNNING STOCKS'!AJ71 -> 7 | D71: BOX | F71: =SUM(H71:HI71) -> 8 | G71: =IF(C71<>0, "AVAILABLE", "OUT OF STOCKS") -> AVAILABLE | H71: 5 | I71: 3
A72: ITM072 | B72: BINDER CLIPS 1 1/4 32MM | C72: =F72-'RUNNING STOCKS'!AJ72 -> 9 | D72: BOX | E72: 28 | F72: =SUM(H72:HI72) -> 10 | G72: =IF(C72<>0, "AVAILABLE", "OUT OF STOCKS") -> AVAILABLE | H72: 7 | I72: 3
A73: ITM073 | B73: BINDER CLIPS 1 INCHES | C73: =F73-'RUNNING STOCKS'!AJ73 -> 10 | D73: BOX | F73: =SUM(H73:HI73) -> 12 | G73: =IF(C73<>0, "AVAILABLE", "OUT OF STOCKS") -> AVAILABLE | H73: 7 | I73: 5
A74: ITM074 | B74: STAPLE WIRE #35 | C74: =F74-'RUNNING STOCKS'!AJ74 -> 5 | D74: BOX | E74: 45 | F74: =SUM(H74:HI74) -> 11 | G74: =IF(C74<>0, "AVAILABLE", "OUT OF STOCKS") -> AVAILABLE | H74: 6 | I74: 5
A75: ITM075 | B75: STAPLE WIRE #10-M | C75: =F75-'RUNNING STOCKS'!AJ75 -> 0 | D75: BOX | F75: =SUM(H75:HI75) -> 0 | G75: =IF(C75<>0, "AVAILABLE", "OUT OF STOCKS") -> OUT OF STOCKS | H75: 0
A76: ITM076 | B76: RUBBER BAND ROUND RB-350 | C76: =F76-'RUNNING STOCKS'!AJ76 -> 0 | D76: PACK | F76: =SUM(H76:HI76) -> 4 | G76: =IF(C76<>0, "AVAILABLE", "OUT OF STOCKS") -> OUT OF STOCKS | H76: 4
A77: ITM077 | B77: CABLE TIE | C77: =F77-'RUNNING STOCKS'!AJ77 -> 0 | D77: PACK | E77: 45 | F77: =SUM(H77:HI77) -> 3 | G77: =IF(C77<>0, "AVAILABLE", "OUT OF STOCKS") -> OUT OF STOCKS | H77: 3
A78: ITM078 | B78: COFFEE CUPS | C78: =F78-'RUNNING STOCKS'!AJ78 -> 5 | D78: PACK | E78: 34 | F78: =SUM(H78:HI78) -> 12 | G78: =IF(C78<>0, "AVAILABLE", "OUT OF STOCKS") -> AVAILABLE | H78: 12
A79: ITM079 | B79: DRINKING CUPS | C79: =F79-'RUNNING STOCKS'!AJ79 -> 5 | D79: PACK | E79: 19 | F79: =SUM(H79:HI79) -> 14 | G79: =IF(C79<>0, "AVAILABLE", "OUT OF STOCKS") -> AVAILABLE | H79: 14
A80: ITM080 | B80: COFFEE STICK | C80: =F80-'RUNNING STOCKS'!AJ80 -> 2 | D80: PACK | E80: 33.25 | F80: =SUM(H80:HI80) -> 8 | G80: =IF(C80<>0, "AVAILABLE", "OUT OF STOCKS") -> AVAILABLE | H80: 3 | J80: 5
A81: ITM081 | B81: CREAMER | C81: =F81-'RUNNING STOCKS'!AJ81 -> 4 | D81: PACK | E81: 51 | F81: =SUM(H81:HI81) -> 9 | G81: =IF(C81<>0, "AVAILABLE", "OUT OF STOCKS") -> AVAILABLE | H81: 4 | J81: 5
A82: ITM082 | B82: BROWN SUGAR | C82: =F82-'RUNNING STOCKS'!AJ82 -> 3 | D82: PACK | E82: 67 | F82: =SUM(H82:HI82) -> 9 | G82: =IF(C82<>0, "AVAILABLE", "OUT OF STOCKS") -> AVAILABLE | H82: 4 | J82: 5
A83: ITM083 | B83: STIRRER | C83: =F83-'RUNNING STOCKS'!AJ83 -> 370 | D83: PC | F83: =SUM(H83:HI83) -> 600 | G83: =IF(C83<>0, "AVAILABLE", "OUT OF STOCKS") -> AVAILABLE | H83: 600
A84: ITM084 | B84: SUPER COLOR MARKER REFILL INK (BLACK) | C84: =F84-'RUNNING STOCKS'!AJ84 -> 7 | D84: BTL | F84: =SUM(H84:HI84) -> 8 | G84: =IF(C84<>0, "AVAILABLE", "OUT OF STOCKS") -> AVAILABLE | H84: 8
A85: ITM085 | B85: WYTEBORD MARKER REFILL INK PILOT (BLACK) | C85: =F85-'RUNNING STOCKS'!AJ85 -> 9 | D85: BTL | F85: =SUM(H85:HI85) -> 11 | G85: =IF(C85<>0, "AVAILABLE", "OUT OF STOCKS") -> AVAILABLE | H85: 11
A86: ITM086 | B86: WYTEBORD MARKER REFILL INK PILOT (RED) | C86: =F86-'RUNNING STOCKS'!AJ86 -> 0 | D86: BTL | F86: =SUM(H86:HI86) -> 0 | G86: =IF(C86<>0, "AVAILABLE", "OUT OF STOCKS") -> OUT OF STOCKS
A87: ITM087 | B87: ALBATROSS | C87: =F87-'RUNNING STOCKS'!AJ87 -> 3 | D87: PC | F87: =SUM(H87:HI87) -> 10 | G87: =IF(C87<>0, "AVAILABLE", "OUT OF STOCKS") -> AVAILABLE | H87: 5 | J87: 5
A88: ITM088 | B88: ZONROX (ORIGINAL) | C88: =F88-'RUNNING STOCKS'!AJ88 -> 22 | D88: BTL | E88: 16.15 | F88: =SUM(H88:HI88) -> 34 | G88: =IF(C88<>0, "AVAILABLE", "OUT OF STOCKS") -> AVAILABLE | H88: 9 | J88: 25
A89: ITM089 | B89: ZONROX (COLORSAFE) | C89: =F89-'RUNNING STOCKS'!AJ89 -> 22 | D89: BTL | E89: 26.55 | F89: =SUM(H89:HI89) -> 31 | G89: =IF(C89<>0, "AVAILABLE", "OUT OF STOCKS") -> AVAILABLE | H89: 6 | J89: 25
A90: ITM090 | B90: GLASS CLEANER | C90: =F90-'RUNNING STOCKS'!AJ90 -> 1 | D90: BTL | E90: 68 | F90: =SUM(H90:HI90) -> 5 | G90: =IF(C90<>0, "AVAILABLE", "OUT OF STOCKS") -> AVAILABLE | H90: 0 | J90: 5
A91: ITM091 | B91: HANDWASH | C91: =F91-'RUNNING STOCKS'!AJ91 -> 0 | D91: BTL | F91: =SUM(H91:HI91) -> 2 | G91: =IF(C91<>0, "AVAILABLE", "OUT OF STOCKS") -> OUT OF STOCKS | H91: 2
A92: ITM092 | B92: RAGS | C92: =F92-'RUNNING STOCKS'!AJ92 -> -1 | D92: BDL | F92: =SUM(H92:HI92) -> 17 | G92: =IF(C92<>0, "AVAILABLE", "OUT OF STOCKS") -> AVAILABLE | H92: 8 | J92: 9
A93: ITM093 | B93: TRASH BAG (XXL) | C93: =F93-'RUNNING STOCKS'!AJ93 -> 4 | D93: ROLL | E93: 62 | F93: =SUM(H93:HI93) -> 12 | G93: =IF(C93<>0, "AVAILABLE", "OUT OF STOCKS") -> AVAILABLE | H93: 2 | J93: 10
A94: ITM094 | B94: TRASH BAG (XL) | C94: =F94-'RUNNING STOCKS'!AJ94 -> 1 | D94: ROLL | E94: 48 | F94: =SUM(H94:HI94) -> 10 | G94: =IF(C94<>0, "AVAILABLE", "OUT OF STOCKS") -> AVAILABLE | J94: 10
A95: ITM095 | B95: TRASH BAG (LARGE) | C95: =F95-'RUNNING STOCKS'!AJ95 -> 2 | D95: ROLL | E95: 34 | F95: =SUM(H95:HI95) -> 7 | G95: =IF(C95<>0, "AVAILABLE", "OUT OF STOCKS") -> AVAILABLE | J95: 7
A96: ITM096 | B96: TRASH BAG (MEDIUM) | C96: =F96-'RUNNING STOCKS'!AJ96 -> 0 | D96: ROLL | F96: =SUM(H96:HI96) -> 10 | G96: =IF(C96<>0, "AVAILABLE", "OUT OF STOCKS") -> OUT OF STOCKS | H96: 6 | J96: 4
A97: ITM097 | B97: TRASH BAG (SMALL) | C97: =F97-'RUNNING STOCKS'!AJ97 -> 1 | D97: ROLL | E97: 28 | F97: =SUM(H97:HI97) -> 8 | G97: =IF(C97<>0, "AVAILABLE", "OUT OF STOCKS") -> AVAILABLE | J97: 8
A98: ITM098 | B98: TISSUE PAPER | C98: =F98-'RUNNING STOCKS'!AJ98 -> 59 | D98: ROLL | E98: 216 | F98: =SUM(H98:HI98) -> 76 | G98: =IF(C98<>0, "AVAILABLE", "OUT OF STOCKS") -> AVAILABLE | H98: 28 | J98: 48
A99: ITM099 | B99: INK EPSON SET | C99: =F99-'RUNNING STOCKS'!AJ99 -> 9 | D99: SET | F99: =SUM(H99:HI99) -> 10 | G99: =IF(C99<>0, "AVAILABLE", "OUT OF STOCKS") -> AVAILABLE | H99: 10
A100: ITM100 | B100: INK BROTHER SET | C100: =F100-'RUNNING STOCKS'!AJ100 -> 4 | D100: SET | F100: =SUM(H100:HI100) -> 10 | G100: =IF(C100<>0, "AVAILABLE", "OUT OF STOCKS") -> AVAILABLE | H100: 10
...

Sheet REAL-TIME STOCKS
A1: Item_ID | B1: Description | C1: Real-Time Stocks | D1: Unit | E1: Uprice | F1: Total Qty | G1: Total Outgoing Stocks | H1: Status | I1: 45992 | J1: 46235 | K1: 46327
A2: ITM001 | B2: BOND PAPER (LONG) | C2: =SUM(F2-G2) -> 34 | D2: REAM | E2: 225 | F2: =SUM(I2:HG2) -> 48 | G2: =SUM('RUNNING STOCKS'!D2:AH2) -> 14 | H2: =IF(C2<>0, "AVAILABLE", "OUT OF STOCKS") -> AVAILABLE | I2: 33 | J2: 15
A3: ITM002 | B3: BOND PAPER (SHORT) | C3: =SUM(F3-G3) -> 11 | D3: REAM | E3: 195 | F3: =SUM(I3:HG3) -> 35 | G3: =SUM('RUNNING STOCKS'!D3:AH3) -> 24 | H3: =IF(C3<>0, "AVAILABLE", "OUT OF STOCKS") -> AVAILABLE | I3: 5 | J3: 30
A4: ITM003 | B4: BOND PAPER A4 | C4: =SUM(F4-G4) -> 13 | D4: REAM | E4: 205 | F4: =SUM(I4:HG4) -> 23 | G4: =SUM('RUNNING STOCKS'!D4:AH4) -> 10 | H4: =IF(C4<>0, "AVAILABLE", "OUT OF STOCKS") -> AVAILABLE | I4: 18 | J4: 5
A5: ITM004 | B5: BOND PAPER NEWSPRINT (SHORT) | C5: =SUM(F5-G5) -> 6 | D5: REAM | E5: 118 | F5: =SUM(I5:HG5) -> 13 | G5: =SUM('RUNNING STOCKS'!D5:AH5) -> 7 | H5: =IF(C5<>0, "AVAILABLE", "OUT OF STOCKS") -> AVAILABLE | I5: 8 | J5: 5
A6: ITM005 | B6: BOND PAPER NEWSPRINT (LONG) | C6: =SUM(F6-G6) -> 11 | D6: REAM | E6: 140 | F6: =SUM(I6:HG6) -> 15 | G6: =SUM('RUNNING STOCKS'!D6:AH6) -> 4 | H6: =IF(C6<>0, "AVAILABLE", "OUT OF STOCKS") -> AVAILABLE | I6: 15
A7: ITM006 | B7: VELLUM PAPER | C7: =SUM(F7-G7) -> 574 | D7: PC | E7: 250 | F7: =SUM(I7:HG7) -> 1114 | G7: =SUM('RUNNING STOCKS'!D7:AH7) -> 540 | H7: =IF(C7<>0, "AVAILABLE", "OUT OF STOCKS") -> AVAILABLE | I7: 314 | J7: 800
A8: ITM007 | B8: LOGBOOK VALIANT RECORD (150 & 300P PAGES) | C8: =SUM(F8-G8) -> 2 | D8: PC | E8: 68 | F8: =SUM(I8:HG8) -> 5 | G8: =SUM('RUNNING STOCKS'!D8:AH8) -> 3 | H8: =IF(C8<>0, "AVAILABLE", "OUT OF STOCKS") -> AVAILABLE | I8: 0 | J8: 5
A9: ITM008 | B9: NOTEBOOK | C9: =SUM(F9-G9) -> 8 | D9: PC | F9: =SUM(I9:HG9) -> 10 | G9: =SUM('RUNNING STOCKS'!D9:AH9) -> 2 | H9: =IF(C9<>0, "AVAILABLE", "OUT OF STOCKS") -> AVAILABLE | I9: 0 | J9: 10
A10: ITM009 | B10: CARBON PAPER (LONG BLUE) | C10: =SUM(F10-G10) -> 156 | D10: PC | E10: 725 | F10: =SUM(I10:HG10) -> 267 | G10: =SUM('RUNNING STOCKS'!D10:AH10) -> 111 | H10: =IF(C10<>0, "AVAILABLE", "OUT OF STOCKS") -> AVAILABLE | I10: 67 | J10: 200
A11: ITM010 | B11: BROWN ENVELOPE (LONG) | C11: =SUM(F11-G11) -> 65 | D11: PC | E11: 300 | F11: =SUM(I11:HG11) -> 150 | G11: =SUM('RUNNING STOCKS'!D11:AH11) -> 85 | H11: =IF(C11<>0, "AVAILABLE", "OUT OF STOCKS") -> AVAILABLE | I11: 0 | J11: 150
A12: ITM011 | B12: BROWN ENVELOPE (SHORT) | C12: =SUM(F12-G12) -> 150 | D12: PC | E12: 300 | F12: =SUM(I12:HG12) -> 265 | G12: =SUM('RUNNING STOCKS'!D12:AH12) -> 115 | H12: =IF(C12<>0, "AVAILABLE", "OUT OF STOCKS") -> AVAILABLE | I12: 115 | J12: 150
A13: ITM012 | B13: BROWN FOLDER (LONG) | C13: =SUM(F13-G13) -> 114 | D13: PC | E13: 600 | F13: =SUM(I13:HG13) -> 844 | G13: =SUM('RUNNING STOCKS'!D13:AH13) -> 730 | H13: =IF(C13<>0, "AVAILABLE", "OUT OF STOCKS") -> AVAILABLE | I13: 244 | J13: 600
A14: ITM013 | B14: BROWN FOLDER (SHORT) | C14: =SUM(F14-G14) -> 0 | D14: PC | F14: =SUM(I14:HG14) -> 0 | G14: =SUM('RUNNING STOCKS'!D14:AH14) -> 0 | H14: =IF(C14<>0, "AVAILABLE", "OUT OF STOCKS") -> OUT OF STOCKS | I14: 0
A15: ITM014 | B15: WHITE FOLDER (LONG) | C15: =SUM(F15-G15) -> 130 | D15: PC | F15: =SUM(I15:HG15) -> 170 | G15: =SUM('RUNNING STOCKS'!D15:AH15) -> 40 | H15: =IF(C15<>0, "AVAILABLE", "OUT OF STOCKS") -> AVAILABLE | I15: 20 | J15: 150
A16: ITM015 | B16: WHITE FOLDER (SHORT) | C16: =SUM(F16-G16) -> 105 | D16: PC | F16: =SUM(I16:HG16) -> 150 | G16: =SUM('RUNNING STOCKS'!D16:AH16) -> 45 | H16: =IF(C16<>0, "AVAILABLE", "OUT OF STOCKS") -> AVAILABLE | I16: 0 | J16: 150
A17: ITM016 | B17: LETTER SHORT WHITE ENVELOPE | C17: =SUM(F17-G17) -> 490 | D17: PC | F17: =SUM(I17:HG17) -> 500 | G17: =SUM('RUNNING STOCKS'!D17:AH17) -> 10 | H17: =IF(C17<>0, "AVAILABLE", "OUT OF STOCKS") -> AVAILABLE | I17: 0 | J17: 500
A18: ITM017 | B18: LETTER LONG WHITE ENVELOPE | C18: =SUM(F18-G18) -> 480 | D18: PC | F18: =SUM(I18:HG18) -> 500 | G18: =SUM('RUNNING STOCKS'!D18:AH18) -> 20 | H18: =IF(C18<>0, "AVAILABLE", "OUT OF STOCKS") -> AVAILABLE | I18: 0 | J18: 500
A19: ITM018 | B19: CARD HOLDER | C19: =SUM(F19-G19) -> 3 | D19: PC | E19: 30 | F19: =SUM(I19:HG19) -> 3 | G19: =SUM('RUNNING STOCKS'!D19:AH19) -> 0 | H19: =IF(C19<>0, "AVAILABLE", "OUT OF STOCKS") -> AVAILABLE | I19: 3
A20: ITM019 | B20: FLEXSTICK BLACK BALLPEN (0.5) | C20: =SUM(F20-G20) -> 137 | D20: PC | E20: 76 | F20: =SUM(I20:HG20) -> 302 | G20: =SUM('RUNNING STOCKS'!D20:AH20) -> 165 | H20: =IF(C20<>0, "AVAILABLE", "OUT OF STOCKS") -> AVAILABLE | I20: 2 | J20: 300
A21: ITM020 | B21: FLEXSTICK RED BALLPEN (0.5) | C21: =SUM(F21-G21) -> 78 | D21: PC | E21: 76 | F21: =SUM(I21:HG21) -> 108 | G21: =SUM('RUNNING STOCKS'!D21:AH21) -> 30 | H21: =IF(C21<>0, "AVAILABLE", "OUT OF STOCKS") -> AVAILABLE | I21: 108
A22: ITM021 | B22: WYTEBORD MARKER PILOT (BLACK) | C22: =SUM(F22-G22) -> 1 | D22: PC | E22: 165 | F22: =SUM(I22:HG22) -> 6 | G22: =SUM('RUNNING STOCKS'!D22:AH22) -> 5 | H22: =IF(C22<>0, "AVAILABLE", "OUT OF STOCKS") -> AVAILABLE | I22: 1 | J22: 5
A23: ITM022 | B23: WYTEBORD MARKER PILOT (RED) | C23: =SUM(F23-G23) -> 2 | D23: PC | E23: 165 | F23: =SUM(I23:HG23) -> 3 | G23: =SUM('RUNNING STOCKS'!D23:AH23) -> 1 | H23: =IF(C23<>0, "AVAILABLE", "OUT OF STOCKS") -> AVAILABLE | I23: 3
A24: ITM023 | B24: HIGHLIGHTER | C24: =SUM(F24-G24) -> 8 | D24: PC | E24: 35 | F24: =SUM(I24:HG24) -> 40 | G24: =SUM('RUNNING STOCKS'!D24:AH24) -> 32 | H24: =IF(C24<>0, "AVAILABLE", "OUT OF STOCKS") -> AVAILABLE | I24: 20 | J24: 20
A25: ITM024 | B25: PENCIL | C25: =SUM(F25-G25) -> 7 | D25: PC | E25: 7 | F25: =SUM(I25:HG25) -> 11 | G25: =SUM('RUNNING STOCKS'!D25:AH25) -> 4 | H25: =IF(C25<>0, "AVAILABLE", "OUT OF STOCKS") -> AVAILABLE | I25: 11
A26: ITM025 | B26: SHARPENER | C26: =SUM(F26-G26) -> 19 | D26: PC | F26: =SUM(I26:HG26) -> 21 | G26: =SUM('RUNNING STOCKS'!D26:AH26) -> 2 | H26: =IF(C26<>0, "AVAILABLE", "OUT OF STOCKS") -> AVAILABLE | I26: 21
A27: ITM026 | B27: ERASER | C27: =SUM(F27-G27) -> 0 | D27: PC | F27: =SUM(I27:HG27) -> 0 | G27: =SUM('RUNNING STOCKS'!D27:AH27) -> 0 | H27: =IF(C27<>0, "AVAILABLE", "OUT OF STOCKS") -> OUT OF STOCKS | I27: 0
A28: ITM027 | B28: CORRECTION TAPE | C28: =SUM(F28-G28) -> 0 | D28: PC | E28: 18 | F28: =SUM(I28:HG28) -> 36 | G28: =SUM('RUNNING STOCKS'!D28:AH28) -> 36 | H28: =IF(C28<>0, "AVAILABLE", "OUT OF STOCKS") -> OUT OF STOCKS | I28: 21 | J28: 15
A29: ITM028 | B29: CANDIES | C29: =SUM(F29-G29) -> 40 | D29: PC | E29: 41 | F29: =SUM(I29:HG29) -> 200 | G29: =SUM('RUNNING STOCKS'!D29:AH29) -> 160 | H29: =IF(C29<>0, "AVAILABLE", "OUT OF STOCKS") -> AVAILABLE | I29: 100 | K29: 100
A30: ITM029 | B30: PUNCHER | C30: =SUM(F30-G30) -> 4 | D30: PC | E30: 175 | F30: =SUM(I30:HG30) -> 4 | G30: =SUM('RUNNING STOCKS'!D30:AH30) -> 0 | H30: =IF(C30<>0, "AVAILABLE", "OUT OF STOCKS") -> AVAILABLE | I30: 4
A31: ITM030 | B31: STAPLER | C31: =SUM(F31-G31) -> 8 | D31: PC | E31: 120 | F31: =SUM(I31:HG31) -> 9 | G31: =SUM('RUNNING STOCKS'!D31:AH31) -> 1 | H31: =IF(C31<>0, "AVAILABLE", "OUT OF STOCKS") -> AVAILABLE | I31: 9
A32: ITM031 | B32: SCISSORS | C32: =SUM(F32-G32) -> 1 | D32: PC | E32: 45 | F32: =SUM(I32:HG32) -> 4 | G32: =SUM('RUNNING STOCKS'!D32:AH32) -> 3 | H32: =IF(C32<>0, "AVAILABLE", "OUT OF STOCKS") -> AVAILABLE | I32: 0 | J32: 4
A33: ITM032 | B33: GLUE | C33: =SUM(F33-G33) -> 6 | D33: PC | F33: =SUM(I33:HG33) -> 9 | G33: =SUM('RUNNING STOCKS'!D33:AH33) -> 3 | H33: =IF(C33<>0, "AVAILABLE", "OUT OF STOCKS") -> AVAILABLE | I33: 1 | J33: 8
A34: ITM033 | B34: RULER | C34: =SUM(F34-G34) -> 7 | D34: PC | E34: 6 | F34: =SUM(I34:HG34) -> 8 | G34: =SUM('RUNNING STOCKS'!D34:AH34) -> 1 | H34: =IF(C34<>0, "AVAILABLE", "OUT OF STOCKS") -> AVAILABLE | I34: 8
A35: ITM034 | B35: CALCULATOR MX-12B | C35: =SUM(F35-G35) -> 4 | D35: PC | F35: =SUM(I35:HG35) -> 5 | G35: =SUM('RUNNING STOCKS'!D35:AH35) -> 1 | H35: =IF(C35<>0, "AVAILABLE", "OUT OF STOCKS") -> AVAILABLE | I35: 0 | J35: 5
A36: ITM035 | B36: TAPE DISPENSER BIG | C36: =SUM(F36-G36) -> 0 | D36: PC | E36: 120 | F36: =SUM(I36:HG36) -> 4 | G36: =SUM('RUNNING STOCKS'!D36:AH36) -> 4 | H36: =IF(C36<>0, "AVAILABLE", "OUT OF STOCKS") -> OUT OF STOCKS | I36: 0 | J36: 4
A37: ITM036 | B37: SCOTCH TAPE (1 INCH) | C37: =SUM(F37-G37) -> 6 | D37: PC | F37: =SUM(I37:HG37) -> 30 | G37: =SUM('RUNNING STOCKS'!D37:AH37) -> 24 | H37: =IF(C37<>0, "AVAILABLE", "OUT OF STOCKS") -> AVAILABLE | I37: 0 | J37: 30
A38: ITM037 | B38: SCOTCH TAPE (2 INCH) | C38: =SUM(F38-G38) -> 0 | D38: PC | F38: =SUM(I38:HG38) -> 0 | G38: =SUM('RUNNING STOCKS'!D38:AH38) -> 0 | H38: =IF(C38<>0, "AVAILABLE", "OUT OF STOCKS") -> OUT OF STOCKS | I38: 0
A39: ITM038 | B39: MASKING TAPE | C39: =SUM(F39-G39) -> 15 | D39: PC | E39: 35 | F39: =SUM(I39:HG39) -> 37 | G39: =SUM('RUNNING STOCKS'!D39:AH39) -> 22 | H39: =IF(C39<>0, "AVAILABLE", "OUT OF STOCKS") -> AVAILABLE | I39: 7 | J39: 30
A40: ITM039 | B40: PACKAGING TAPE BROWN | C40: =SUM(F40-G40) -> 0 | D40: PC | E40: 49 | F40: =SUM(I40:HG40) -> 5 | G40: =SUM('RUNNING STOCKS'!D40:AH40) -> 5 | H40: =IF(C40<>0, "AVAILABLE", "OUT OF STOCKS") -> OUT OF STOCKS | I40: 0 | J40: 5
A41: ITM040 | B41: DOUBLE-SIDED TAPE (1 INCH) | C41: =SUM(F41-G41) -> 4 | D41: PC | E41: 25 | F41: =SUM(I41:HG41) -> 20 | G41: =SUM('RUNNING STOCKS'!D41:AH41) -> 16 | H41: =IF(C41<>0, "AVAILABLE", "OUT OF STOCKS") -> AVAILABLE | I41: 20
A42: ITM041 | B42: DUCT TAPE | C42: =SUM(F42-G42) -> 0 | D42: PC | E42: 108 | F42: =SUM(I42:HG42) -> 3 | G42: =SUM('RUNNING STOCKS'!D42:AH42) -> 3 | H42: =IF(C42<>0, "AVAILABLE", "OUT OF STOCKS") -> OUT OF STOCKS | I42: 3
A43: ITM043 | B43: TYPEWRITER BLACK NYLON | C43: =SUM(F43-G43) -> 7 | D43: PC | F43: =SUM(I43:HG43) -> 10 | G43: =SUM('RUNNING STOCKS'!D43:AH43) -> 3 | H43: =IF(C43<>0, "AVAILABLE", "OUT OF STOCKS") -> AVAILABLE | I43: 0 | J43: 10
A44: ITM044 | B44: INK EPSON 003 (YELLOW) | C44: =SUM(F44-G44) -> 5 | D44: PC | F44: =SUM(I44:HG44) -> 5 | G44: =SUM('RUNNING STOCKS'!D44:AH44) -> 0 | H44: =IF(C44<>0, "AVAILABLE", "OUT OF STOCKS") -> AVAILABLE | I44: 5
A45: ITM045 | B45: INK EPSON 003 (MAGENTA) | C45: =SUM(F45-G45) -> 3 | D45: PC | F45: =SUM(I45:HG45) -> 3 | G45: =SUM('RUNNING STOCKS'!D45:AH45) -> 0 | H45: =IF(C45<>0, "AVAILABLE", "OUT OF STOCKS") -> AVAILABLE | I45: 3
A46: ITM046 | B46: INK EPSON 003 (CYAN) | C46: =SUM(F46-G46) -> 5 | D46: PC | F46: =SUM(I46:HG46) -> 5 | G46: =SUM('RUNNING STOCKS'!D46:AH46) -> 0 | H46: =IF(C46<>0, "AVAILABLE", "OUT OF STOCKS") -> AVAILABLE | I46: 5
A47: ITM047 | B47: INK EPSON 003 (BLACK) | C47: =SUM(F47-G47) -> 2 | D47: PC | F47: =SUM(I47:HG47) -> 3 | G47: =SUM('RUNNING STOCKS'!D47:AH47) -> 1 | H47: =IF(C47<>0, "AVAILABLE", "OUT OF STOCKS") -> AVAILABLE | I47: 3
A48: ITM048 | B48: INK BROTHER BT5000Y | C48: =SUM(F48-G48) -> 0 | D48: PC | F48: =SUM(I48:HG48) -> 0 | G48: =SUM('RUNNING STOCKS'!D48:AH48) -> 0 | H48: =IF(C48<>0, "AVAILABLE", "OUT OF STOCKS") -> OUT OF STOCKS
A49: ITM049 | B49: INK BROTHER BT5000M | C49: =SUM(F49-G49) -> 0 | D49: PC | F49: =SUM(I49:HG49) -> 0 | G49: =SUM('RUNNING STOCKS'!D49:AH49) -> 0 | H49: =IF(C49<>0, "AVAILABLE", "OUT OF STOCKS") -> OUT OF STOCKS
A50: ITM050 | B50: INK BROTHER BT5000C | C50: =SUM(F50-G50) -> 0 | D50: PC | F50: =SUM(I50:HG50) -> 0 | G50: =SUM('RUNNING STOCKS'!D50:AH50) -> 0 | H50: =IF(C50<>0, "AVAILABLE", "OUT OF STOCKS") -> OUT OF STOCKS
A51: ITM051 | B51: INK BROTHER BTD60BK | C51: =SUM(F51-G51) -> 0 | D51: PC | F51: =SUM(I51:HG51) -> 0 | G51: =SUM('RUNNING STOCKS'!D51:AH51) -> 0 | H51: =IF(C51<>0, "AVAILABLE", "OUT OF STOCKS") -> OUT OF STOCKS
A52: ITM052 | B52: INK HP (YELLOW | C52: =SUM(F52-G52) -> 0 | D52: PC | F52: =SUM(I52:HG52) -> 0 | G52: =SUM('RUNNING STOCKS'!D52:AH52) -> 0 | H52: =IF(C52<>0, "AVAILABLE", "OUT OF STOCKS") -> OUT OF STOCKS
A53: ITM053 | B53: INK HP (MAGENTA) | C53: =SUM(F53-G53) -> 0 | D53: PC | F53: =SUM(I53:HG53) -> 0 | G53: =SUM('RUNNING STOCKS'!D53:AH53) -> 0 | H53: =IF(C53<>0, "AVAILABLE", "OUT OF STOCKS") -> OUT OF STOCKS
A54: ITM054 | B54: INK HP (CYAN) | C54: =SUM(F54-G54) -> 0 | D54: PC | F54: =SUM(I54:HG54) -> 0 | G54: =SUM('RUNNING STOCKS'!D54:AH54) -> 0 | H54: =IF(C54<>0, "AVAILABLE", "OUT OF STOCKS") -> OUT OF STOCKS
A55: ITM055 | B55: INK HP (BLACK) | C55: =SUM(F55-G55) -> 0 | D55: PC | F55: =SUM(I55:HG55) -> 0 | G55: =SUM('RUNNING STOCKS'!D55:AH55) -> 0 | H55: =IF(C55<>0, "AVAILABLE", "OUT OF STOCKS") -> OUT OF STOCKS
A56: ITM056 | B56: PRIDE SOAP POWDER | C56: =SUM(F56-G56) -> 165 | D56: PC | E56: 27 | F56: =SUM(I56:HG56) -> 366 | G56: =SUM('RUNNING STOCKS'!D56:AH56) -> 201 | H56: =IF(C56<>0, "AVAILABLE", "OUT OF STOCKS") -> AVAILABLE | I56: 126 | K56: 240
A57: ITM057 | B57: STAMP PAD INK BLACK 30ML | C57: =SUM(F57-G57) -> 0 | D57: PC | F57: =SUM(I57:HG57) -> 1 | G57: =SUM('RUNNING STOCKS'!D57:AH57) -> 1 | H57: =IF(C57<>0, "AVAILABLE", "OUT OF STOCKS") -> OUT OF STOCKS | I57: 1
A58: ITM058 | B58: STAMP PAD INK BLUE 30ML | C58: =SUM(F58-G58) -> 0 | D58: PC | F58: =SUM(I58:HG58) -> 2 | G58: =SUM('RUNNING STOCKS'!D58:AH58) -> 2 | H58: =IF(C58<>0, "AVAILABLE", "OUT OF STOCKS") -> OUT OF STOCKS | I58: 2
A59: ITM059 | B59: STAMP PAD INK RED 30ML | C59: =SUM(F59-G59) -> 3 | D59: PC | F59: =SUM(I59:HG59) -> 3 | G59: =SUM('RUNNING STOCKS'!D59:AH59) -> 0 | H59: =IF(C59<>0, "AVAILABLE", "OUT OF STOCKS") -> AVAILABLE | I59: 3
A60: ITM060 | B60: SUPER COLOR MARKER PILOT (BLACK) | C60: =SUM(F60-G60) -> 6 | D60: PC | E60: 165 | F60: =SUM(I60:HG60) -> 10 | G60: =SUM('RUNNING STOCKS'!D60:AH60) -> 4 | H60: =IF(C60<>0, "AVAILABLE", "OUT OF STOCKS") -> AVAILABLE | I60: 5 | J60: 5
A61: ITM061 | B61: JOY | C61: =SUM(F61-G61) -> 39 | D61: PC | E61: 12 | F61: =SUM(I61:HG61) -> 95 | G61: =SUM('RUNNING STOCKS'!D61:AH61) -> 56 | H61: =IF(C61<>0, "AVAILABLE", "OUT OF STOCKS") -> AVAILABLE | I61: 23 | K61: 72
A62: ITM062 | B62: DOWNY | C62: =SUM(F62-G62) -> 9 | D62: PC | E62: 38 | F62: =SUM(I62:HG62) -> 54 | G62: =SUM('RUNNING STOCKS'!D62:AH62) -> 45 | H62: =IF(C62<>0, "AVAILABLE", "OUT OF STOCKS") -> AVAILABLE | I62: 36 | K62: 18
A63: ITM063 | B63: SAFEGUARD SOAP | C63: =SUM(F63-G63) -> 8 | D63: PC | F63: =SUM(I63:HG63) -> 18 | G63: =SUM('RUNNING STOCKS'!D63:AH63) -> 10 | H63: =IF(C63<>0, "AVAILABLE", "OUT OF STOCKS") -> AVAILABLE | I63: 4 | K63: 14
A64: ITM064 | B64: STICKY NOTES 2X2 A02 | C64: =SUM(F64-G64) -> 4 | D64: PAD | E64: 47 | F64: =SUM(I64:HG64) -> 23 | G64: =SUM('RUNNING STOCKS'!D64:AH64) -> 19 | H64: =IF(C64<>0, "AVAILABLE", "OUT OF STOCKS") -> AVAILABLE | I64: 3 | J64: 20
A65: ITM065 | B65: STICKY NOTES A03 | C65: =SUM(F65-G65) -> 0 | D65: PAD | F65: =SUM(I65:HG65) -> 0 | G65: =SUM('RUNNING STOCKS'!D65:AH65) -> 0 | H65: =IF(C65<>0, "AVAILABLE", "OUT OF STOCKS") -> OUT OF STOCKS
A66: ITM066 | B66: STICKY NOTES A05 | C66: =SUM(F66-G66) -> 0 | D66: PAD | F66: =SUM(I66:HG66) -> 0 | G66: =SUM('RUNNING STOCKS'!D66:AH66) -> 0 | H66: =IF(C66<>0, "AVAILABLE", "OUT OF STOCKS") -> OUT OF STOCKS
A67: ITM067 | B67: FASTENER | C67: =SUM(F67-G67) -> 16 | D67: BOX | F67: =SUM(I67:HG67) -> 27 | G67: =SUM('RUNNING STOCKS'!D67:AH67) -> 11 | H67: =IF(C67<>0, "AVAILABLE", "OUT OF STOCKS") -> AVAILABLE | I67: 7 | J67: 20
A68: ITM068 | B68: PAPER CLIPS 50MM | C68: =SUM(F68-G68) -> 10 | D68: BOX | F68: =SUM(I68:HG68) -> 15 | G68: =SUM('RUNNING STOCKS'!D68:AH68) -> 5 | H68: =IF(C68<>0, "AVAILABLE", "OUT OF STOCKS") -> AVAILABLE | I68: 15
A69: ITM069 | B69: PAPER CLIPS JUMBO | C69: =SUM(F69-G69) -> 0 | D69: BOX | F69: =SUM(I69:HG69) -> 0 | G69: =SUM('RUNNING STOCKS'!D69:AH69) -> 0 | H69: =IF(C69<>0, "AVAILABLE", "OUT OF STOCKS") -> OUT OF STOCKS
A70: ITM070 | B70: BINDER CLIPS 2 INCHES | C70: =SUM(F70-G70) -> 8 | D70: BOX | F70: =SUM(I70:HG70) -> 9 | G70: =SUM('RUNNING STOCKS'!D70:AH70) -> 1 | H70: =IF(C70<>0, "AVAILABLE", "OUT OF STOCKS") -> AVAILABLE | I70: 6 | J70: 3
A71: ITM071 | B71: BINDER CLIPS 1 5/8 41MM | C71: =SUM(F71-G71) -> 7 | D71: BOX | F71: =SUM(I71:HG71) -> 8 | G71: =SUM('RUNNING STOCKS'!D71:AH71) -> 1 | H71: =IF(C71<>0, "AVAILABLE", "OUT OF STOCKS") -> AVAILABLE | I71: 5 | J71: 3
A72: ITM072 | B72: BINDER CLIPS 1 1/4 32MM | C72: =SUM(F72-G72) -> 9 | D72: BOX | E72: 28 | F72: =SUM(I72:HG72) -> 10 | G72: =SUM('RUNNING STOCKS'!D72:AH72) -> 1 | H72: =IF(C72<>0, "AVAILABLE", "OUT OF STOCKS") -> AVAILABLE | I72: 7 | J72: 3
A73: ITM073 | B73: BINDER CLIPS 1 INCHES | C73: =SUM(F73-G73) -> 10 | D73: BOX | F73: =SUM(I73:HG73) -> 12 | G73: =SUM('RUNNING STOCKS'!D73:AH73) -> 2 | H73: =IF(C73<>0, "AVAILABLE", "OUT OF STOCKS") -> AVAILABLE | I73: 7 | J73: 5
A74: ITM074 | B74: STAPLE WIRE #35 | C74: =SUM(F74-G74) -> 5 | D74: BOX | E74: 45 | F74: =SUM(I74:HG74) -> 11 | G74: =SUM('RUNNING STOCKS'!D74:AH74) -> 6 | H74: =IF(C74<>0, "AVAILABLE", "OUT OF STOCKS") -> AVAILABLE | I74: 6 | J74: 5
A75: ITM075 | B75: STAPLE WIRE #10-M | C75: =SUM(F75-G75) -> 0 | D75: BOX | F75: =SUM(I75:HG75) -> 0 | G75: =SUM('RUNNING STOCKS'!D75:AH75) -> 0 | H75: =IF(C75<>0, "AVAILABLE", "OUT OF STOCKS") -> OUT OF STOCKS | I75: 0
A76: ITM076 | B76: RUBBER BAND ROUND RB-350 | C76: =SUM(F76-G76) -> 0 | D76: PACK | F76: =SUM(I76:HG76) -> 4 | G76: =SUM('RUNNING STOCKS'!D76:AH76) -> 4 | H76: =IF(C76<>0, "AVAILABLE", "OUT OF STOCKS") -> OUT OF STOCKS | I76: 4
A77: ITM077 | B77: CABLE TIE | C77: =SUM(F77-G77) -> 10 | D77: PACK | E77: 45 | F77: =SUM(I77:HG77) -> 13 | G77: =SUM('RUNNING STOCKS'!D77:AH77) -> 3 | H77: =IF(C77<>0, "AVAILABLE", "OUT OF STOCKS") -> AVAILABLE | I77: 3 | K77: 10
A78: ITM078 | B78: COFFEE CUPS | C78: =SUM(F78-G78) -> 5 | D78: PACK | E78: 34 | F78: =SUM(I78:HG78) -> 12 | G78: =SUM('RUNNING STOCKS'!D78:AH78) -> 7 | H78: =IF(C78<>0, "AVAILABLE", "OUT OF STOCKS") -> AVAILABLE | I78: 12
A79: ITM079 | B79: DRINKING CUPS | C79: =SUM(F79-G79) -> 5 | D79: PACK | E79: 19 | F79: =SUM(I79:HG79) -> 14 | G79: =SUM('RUNNING STOCKS'!D79:AH79) -> 9 | H79: =IF(C79<>0, "AVAILABLE", "OUT OF STOCKS") -> AVAILABLE | I79: 14
A80: ITM080 | B80: COFFEE STICK | C80: =SUM(F80-G80) -> 2 | D80: PACK | E80: 33.25 | F80: =SUM(I80:HG80) -> 8 | G80: =SUM('RUNNING STOCKS'!D80:AH80) -> 6 | H80: =IF(C80<>0, "AVAILABLE", "OUT OF STOCKS") -> AVAILABLE | I80: 3 | K80: 5
A81: ITM081 | B81: CREAMER | C81: =SUM(F81-G81) -> 4 | D81: PACK | E81: 51 | F81: =SUM(I81:HG81) -> 9 | G81: =SUM('RUNNING STOCKS'!D81:AH81) -> 5 | H81: =IF(C81<>0, "AVAILABLE", "OUT OF STOCKS") -> AVAILABLE | I81: 4 | K81: 5
A82: ITM082 | B82: BROWN SUGAR | C82: =SUM(F82-G82) -> 3 | D82: PACK | E82: 67 | F82: =SUM(I82:HG82) -> 9 | G82: =SUM('RUNNING STOCKS'!D82:AH82) -> 6 | H82: =IF(C82<>0, "AVAILABLE", "OUT OF STOCKS") -> AVAILABLE | I82: 4 | K82: 5
A83: ITM083 | B83: STIRRER | C83: =SUM(F83-G83) -> 370 | D83: PC | F83: =SUM(I83:HG83) -> 600 | G83: =SUM('RUNNING STOCKS'!D83:AH83) -> 230 | H83: =IF(C83<>0, "AVAILABLE", "OUT OF STOCKS") -> AVAILABLE | I83: 600
A84: ITM084 | B84: SUPER COLOR MARKER REFILL INK (BLACK) | C84: =SUM(F84-G84) -> 7 | D84: BTL | F84: =SUM(I84:HG84) -> 8 | G84: =SUM('RUNNING STOCKS'!D84:AH84) -> 1 | H84: =IF(C84<>0, "AVAILABLE", "OUT OF STOCKS") -> AVAILABLE | I84: 8
A85: ITM085 | B85: WYTEBORD MARKER REFILL INK PILOT (BLACK) | C85: =SUM(F85-G85) -> 9 | D85: BTL | F85: =SUM(I85:HG85) -> 11 | G85: =SUM('RUNNING STOCKS'!D85:AH85) -> 2 | H85: =IF(C85<>0, "AVAILABLE", "OUT OF STOCKS") -> AVAILABLE | I85: 11
A86: ITM086 | B86: WYTEBORD MARKER REFILL INK PILOT (RED) | C86: =SUM(F86-G86) -> 0 | D86: BTL | F86: =SUM(I86:HG86) -> 0 | G86: =SUM('RUNNING STOCKS'!D86:AH86) -> 0 | H86: =IF(C86<>0, "AVAILABLE", "OUT OF STOCKS") -> OUT OF STOCKS
A87: ITM087 | B87: ALBATROSS | C87: =SUM(F87-G87) -> 3 | D87: PC | F87: =SUM(I87:HG87) -> 10 | G87: =SUM('RUNNING STOCKS'!D87:AH87) -> 7 | H87: =IF(C87<>0, "AVAILABLE", "OUT OF STOCKS") -> AVAILABLE | I87: 5 | K87: 5
A88: ITM088 | B88: ZONROX (ORIGINAL) | C88: =SUM(F88-G88) -> 22 | D88: BTL | E88: 16.15 | F88: =SUM(I88:HG88) -> 34 | G88: =SUM('RUNNING STOCKS'!D88:AH88) -> 12 | H88: =IF(C88<>0, "AVAILABLE", "OUT OF STOCKS") -> AVAILABLE | I88: 9 | K88: 25
A89: ITM089 | B89: ZONROX (COLORSAFE) | C89: =SUM(F89-G89) -> 22 | D89: BTL | E89: 26.55 | F89: =SUM(I89:HG89) -> 31 | G89: =SUM('RUNNING STOCKS'!D89:AH89) -> 9 | H89: =IF(C89<>0, "AVAILABLE", "OUT OF STOCKS") -> AVAILABLE | I89: 6 | K89: 25
A90: ITM090 | B90: GLASS CLEANER | C90: =SUM(F90-G90) -> 1 | D90: BTL | E90: 68 | F90: =SUM(I90:HG90) -> 5 | G90: =SUM('RUNNING STOCKS'!D90:AH90) -> 4 | H90: =IF(C90<>0, "AVAILABLE", "OUT OF STOCKS") -> AVAILABLE | I90: 0 | K90: 5
A91: ITM091 | B91: HANDWASH | C91: =SUM(F91-G91) -> 0 | D91: BTL | F91: =SUM(I91:HG91) -> 2 | G91: =SUM('RUNNING STOCKS'!D91:AH91) -> 2 | H91: =IF(C91<>0, "AVAILABLE", "OUT OF STOCKS") -> OUT OF STOCKS | I91: 2
A92: ITM092 | B92: RAGS | C92: =SUM(F92-G92) -> -1 | D92: BDL | F92: =SUM(I92:HG92) -> 17 | G92: =SUM('RUNNING STOCKS'!D92:AH92) -> 18 | H92: =IF(C92<>0, "AVAILABLE", "OUT OF STOCKS") -> AVAILABLE | I92: 8 | K92: 9
A93: ITM093 | B93: TRASH BAG (XXL) | C93: =SUM(F93-G93) -> 4 | D93: ROLL | E93: 62 | F93: =SUM(I93:HG93) -> 12 | G93: =SUM('RUNNING STOCKS'!D93:AH93) -> 8 | H93: =IF(C93<>0, "AVAILABLE", "OUT OF STOCKS") -> AVAILABLE | I93: 2 | K93: 10
A94: ITM094 | B94: TRASH BAG (XL) | C94: =SUM(F94-G94) -> 1 | D94: ROLL | E94: 48 | F94: =SUM(I94:HG94) -> 10 | G94: =SUM('RUNNING STOCKS'!D94:AH94) -> 9 | H94: =IF(C94<>0, "AVAILABLE", "OUT OF STOCKS") -> AVAILABLE | K94: 10
A95: ITM095 | B95: TRASH BAG (LARGE) | C95: =SUM(F95-G95) -> 2 | D95: ROLL | E95: 34 | F95: =SUM(I95:HG95) -> 7 | G95: =SUM('RUNNING STOCKS'!D95:AH95) -> 5 | H95: =IF(C95<>0, "AVAILABLE", "OUT OF STOCKS") -> AVAILABLE | K95: 7
A96: ITM096 | B96: TRASH BAG (MEDIUM) | C96: =SUM(F96-G96) -> 0 | D96: ROLL | F96: =SUM(I96:HG96) -> 10 | G96: =SUM('RUNNING STOCKS'!D96:AH96) -> 10 | H96: =IF(C96<>0, "AVAILABLE", "OUT OF STOCKS") -> OUT OF STOCKS | I96: 6 | K96: 4
A97: ITM097 | B97: TRASH BAG (SMALL) | C97: =SUM(F97-G97) -> 1 | D97: ROLL | E97: 28 | F97: =SUM(I97:HG97) -> 8 | G97: =SUM('RUNNING STOCKS'!D97:AH97) -> 7 | H97: =IF(C97<>0, "AVAILABLE", "OUT OF STOCKS") -> AVAILABLE | K97: 8
A98: ITM098 | B98: TISSUE PAPER | C98: =SUM(F98-G98) -> 59 | D98: ROLL | E98: 216 | F98: =SUM(I98:HG98) -> 76 | G98: =SUM('RUNNING STOCKS'!D98:AH98) -> 17 | H98: =IF(C98<>0, "AVAILABLE", "OUT OF STOCKS") -> AVAILABLE | I98: 28 | K98: 48
A99: ITM099 | B99: INK EPSON SET | C99: =SUM(F99-G99) -> 9 | D99: SET | F99: =SUM(I99:HG99) -> 10 | G99: =SUM('RUNNING STOCKS'!D99:AH99) -> 1 | H99: =IF(C99<>0, "AVAILABLE", "OUT OF STOCKS") -> AVAILABLE | I99: 10
A100: ITM100 | B100: INK BROTHER SET | C100: =SUM(F100-G100) -> 4 | D100: SET | F100: =SUM(I100:HG100) -> 10 | G100: =SUM('RUNNING STOCKS'!D100:AH100) -> 6 | H100: =IF(C100<>0, "AVAILABLE", "OUT OF STOCKS") -> AVAILABLE | I100: 10
...

Sheet JAN.2026 OFFICE SUPPLIES REQ.

Sheet PRINT STOCKS

Sheet ADMIN
A1: Timestamp | B1: Branch | C1: Date | D1: To | E1: Purpose | F1: ITEM_ID | G1: Qty | H1: Unit | I1: Description | J1: UPrice | K1: Amount | L1: Total | M1: Requested By | N1: Status | O1: Release Date | P1: Received By | Q1: PDF URL
A2: 46026.57 | B2: ADMIN | C2: 46026 | D2: PURCHASING OFFICE | E2: OFFICE SUPPLIES | F2: ITM007 | G2: 1 | H2: PC | I2: LOGBOOK VALIANT RECORD (150 & 300P PAGES) | K2: 0 | L2: 0 | M2: MERNALYN M. JAVIER - INVENTORY DEPT. | N2: Approved | Q2: https://drive.google.com/file/d/1mkBvAQ_o9bmC8OjE9brLOI1HABpiLPRg/view?usp=drivesdk
A3: 46029.619 | B3: ADMIN | C3: 46029 | D3: PURCHASING OFFICE | E3: OFFICE SUPPLIES | F3: ITM003 | G3: 1 | H3: REAM | I3: BOND PAPER A4 | K3: 0 | L3: 0 | M3: Sir Jhojie | N3: Approved | Q3: https://drive.google.com/file/d/18dZdLGRdHBaO0CUJoQKWNwbjJZmCmKP_/view?usp=drivesdk
A4: 46030.589 | B4: ADMIN | C4: 46030 | D4: PURCHASING OFFICE | E4: OFFICE SUPPLIES | F4: ITM001 | G4: 1 | H4: REAM | I4: BOND PAPER (LONG) | K4: 0 | L4: 0 | M4: SIR JASON | N4: Approved | Q4: https://drive.google.com/file/d/1Ab0YvVeDXzOQD96sx4CsypHQw2BKfFew/view?usp=drivesdk
A5: 46030.589 | B5: ADMIN | C5: 46030 | D5: PURCHASING OFFICE | E5: OFFICE SUPPLIES | F5: ITM023 | G5: 1 | H5: PC | I5: HIGHLIGHTER | K5: 0 | L5: 0 | M5: SIR JASON | N5: Approved | Q5: https://drive.google.com/file/d/1Ab0YvVeDXzOQD96sx4CsypHQw2BKfFew/view?usp=drivesdk
A6: 46031.368 | B6: ADMIN | C6: 46031 | D6: PURCHASING OFFICE | E6: OFFICE SUPPLIES | F6: ITM002 | G6: 1 | H6: REAM | I6: BOND PAPER (SHORT) | K6: 0 | L6: 0 | M6: SIR JASON | N6: Approved | Q6: https://drive.google.com/file/d/1xjzFeAPUUzdY_mjCQq7TEIU9BYk6dWj8/view?usp=drivesdk
A7: 46034.697 | B7: ADMIN | C7: 46033 | D7: PURCHASING OFFICE | E7: OFFICE SUPPLIES | F7: ITM031 | G7: 1 | H7: PC | I7: SCISSORS | K7: 0 | L7: 0 | M7: Ma'am Agnes | N7: Approved | Q7: https://drive.google.com/file/d/1-B5mzUQ2bdBrlxSA7lUX8Ty13MVwxN6S/view?usp=drivesdk
A8: 46035.628 | B8: ADMIN | C8: 46035 | D8: PURCHASING OFFICE | E8: OFFICE SUPPLIES | F8: ITM027 | G8: 1 | H8: PC | I8: CORRECTION TAPE | K8: 0 | L8: 0 | M8: Ma'am Ivy | N8: Approved | Q8: https://drive.google.com/file/d/1wiJ7UbibpVcnBp3gaik-iX72p3SuTufH/view?usp=drivesdk
A9: 46035.628 | B9: ADMIN | C9: 46035 | D9: PURCHASING OFFICE | E9: OFFICE SUPPLIES | F9: ITM019 | G9: 1 | H9: PC | I9: FLEXSTICK BLACK BALLPEN (0.5) | K9: 0 | L9: 0 | M9: Ma'am Ivy | N9: Approved | Q9: https://drive.google.com/file/d/1wiJ7UbibpVcnBp3gaik-iX72p3SuTufH/view?usp=drivesdk
A10: 46035.628 | B10: ADMIN | C10: 46035 | D10: PURCHASING OFFICE | E10: OFFICE SUPPLIES | F10: ITM020 | G10: 1 | H10: PC | I10: FLEXSTICK RED BALLPEN (0.5) | K10: 0 | L10: 0 | M10: Ma'am Ivy | N10: Approved | Q10: https://drive.google.com/file/d/1wiJ7UbibpVcnBp3gaik-iX72p3SuTufH/view?usp=drivesdk
A11: 46035.628 | B11: ADMIN | C11: 46035 | D11: PURCHASING OFFICE | E11: OFFICE SUPPLIES | F11: ITM031 | G11: 1 | H11: PC | I11: SCISSORS | K11: 0 | L11: 0 | M11: Ma'am Ivy | N11: Approved | Q11: https://drive.google.com/file/d/1wiJ7UbibpVcnBp3gaik-iX72p3SuTufH/view?usp=drivesdk
A12: 46036.386 | B12: ADMIN | C12: 46036 | D12: PURCHASING OFFICE | E12: OFFICE SUPPLIES | F12: ITM034 | G12: 1 | H12: PC | I12: CALCULATOR MX-12B | K12: 0 | L12: 0 | M12: LTO Dept, Ma'am Ivy | N12: Approved | Q12: https://drive.google.com/file/d/1bYjh7C1tRC8nqxEZ8M9nxV8gIObbASlN/view?usp=drivesdk
A13: 46036.386 | B13: ADMIN | C13: 46036 | D13: PURCHASING OFFICE | E13: OFFICE SUPPLIES | F13: ITM074 | G13: 1 | H13: BOX | I13: STAPLE WIRE #35 | K13: 0 | L13: 0 | M13: LTO Dept, Ma'am Ivy | N13: Approved | Q13: https://drive.google.com/file/d/1bYjh7C1tRC8nqxEZ8M9nxV8gIObbASlN/view?usp=drivesdk
... A19: 46044.438 | B19: ADMIN | C19: 46044 | D19: PURCHASING OFFICE | E19: OFFICE SUPPLIES | F19: ITM103 | G19: 1 | H19: PC | I19: STAMP PAD BLACK NO.2 | K19: 0 | L19: 0 | M19: JHAISRHIE EMATA | N19: Pending | Q19: https://drive.google.com/file/d/1RBMfhNHwe35lHXtUpI1pDKYc4ZKoa8wQ/view?usp=drivesdk

Sheet WAREHOUSE
A1: Timestamp | B1: Branch | C1: Date | D1: To | E1: Purpose | F1: ITEM_ID | G1: Qty | H1: Unit | I1: Description | J1: UPrice | K1: Amount | L1: Total | M1: Requested By | N1: Status | O1: Release Date | P1: Received By | Q1: PDF URL
A2: 46038.387 | B2: WAREHOUSE | C2: 46038 | D2: PURCHASING OFFICE | E2: OFFICE SUPPLIES | F2: ITM038 | G2: 3 | H2: PCS | I2: MASKING TAPE | K2: 0 | L2: 0 | M2: GLENN CAMPILAN | N2: Approved | Q2: https://drive.google.com/file/d/1gqerNjb33IlnGS9RUKG3rbnNEb_rQxyT/view?usp=drivesdk
A3: 46038.387 | B3: WAREHOUSE | C3: 46038 | D3: PURCHASING OFFICE | E3: OFFICE SUPPLIES | F3: ITM056 | G3: 10 | H3: PCS | I3: PRIDE SOAP POWDER | K3: 0 | L3: 0 | M3: GLENN CAMPILAN | N3: Approved | Q3: https://drive.google.com/file/d/1gqerNjb33IlnGS9RUKG3rbnNEb_rQxyT/view?usp=drivesdk
A4: 46038.387 | B4: WAREHOUSE | C4: 46038 | D4: PURCHASING OFFICE | E4: OFFICE SUPPLIES | F4: ITM061 | G4: 3 | H4: PCS | I4: JOY | K4: 0 | L4: 0 | M4: GLENN CAMPILAN | N4: Approved | Q4: https://drive.google.com/file/d/1gqerNjb33IlnGS9RUKG3rbnNEb_rQxyT/view?usp=drivesdk
A5: 46038.387 | B5: WAREHOUSE | C5: 46038 | D5: PURCHASING OFFICE | E5: OFFICE SUPPLIES | F5: ITM002 | G5: 1 | H5: REAM | I5: BOND PAPER (SHORT) | K5: 0 | L5: 0 | M5: GLENN CAMPILAN | N5: Approved | Q5: https://drive.google.com/file/d/1gqerNjb33IlnGS9RUKG3rbnNEb_rQxyT/view?usp=drivesdk
A6: 46038.387 | B6: WAREHOUSE | C6: 46038 | D6: PURCHASING OFFICE | E6: OFFICE SUPPLIES | F6: ITM092 | G6: 1 | H6: BDL | I6: RAGS | K6: 0 | L6: 0 | M6: GLENN CAMPILAN | N6: Approved | Q6: https://drive.google.com/file/d/1gqerNjb33IlnGS9RUKG3rbnNEb_rQxyT/view?usp=drivesdk
A7: 46041.627 | B7: WAREHOUSE | C7: 46041 | D7: PURCHASING OFFICE | E7: OFFICE SUPPLIES | F7: ITM079 | G7: 1 | H7: PACK | I7: DRINKING CUPS | K7: 0 | L7: 0 | M7: GLENN CAMPILAN | N7: Approved | Q7: https://drive.google.com/file/d/1L3s7AhsuRV75CtQ7A7gIzEryNeO1U2Px/view?usp=drivesdk

Sheet LAGTANG
A1: Timestamp | B1: Branch | C1: Date | D1: To | E1: Purpose | F1: ITEM_ID | G1: Qty | H1: Unit | I1: Description | J1: UPrice | K1: Amount | L1: Total | M1: Requested By | N1: Status | O1: Release Date | P1: Received By | Q1: PDF URL
A2: 46028.612 | B2: LAGTANG | C2: 46028 | D2: PURCHASING OFFICE | E2: OFFICE SUPPLIES | F2: ITM002 | G2: 1 | H2: REAM | I2: BOND PAPER (SHORT) | K2: 0 | L2: 0 | M2: MARLON LLOYD ROSALITA | N2: Approved | Q2: https://drive.google.com/file/d/1NxVOGYg83D1jEFEAUgDSPC5BM_ieYkFu/view?usp=drivesdk
A3: 46028.612 | B3: LAGTANG | C3: 46028 | D3: PURCHASING OFFICE | E3: OFFICE SUPPLIES | F3: ITM012 | G3: 20 | H3: PCS | I3: BROWN FOLDER (LONG) | K3: 0 | L3: 0 | M3: MARLON LLOYD ROSALITA | N3: Approved | Q3: https://drive.google.com/file/d/1NxVOGYg83D1jEFEAUgDSPC5BM_ieYkFu/view?usp=drivesdk
A4: 46028.612 | B4: LAGTANG | C4: 46028 | D4: PURCHASING OFFICE | E4: OFFICE SUPPLIES | F4: ITM027 | G4: 2 | H4: PCS | I4: CORRECTION TAPE | K4: 0 | L4: 0 | M4: MARLON LLOYD ROSALITA | N4: Approved | Q4: https://drive.google.com/file/d/1NxVOGYg83D1jEFEAUgDSPC5BM_ieYkFu/view?usp=drivesdk
A5: 46028.612 | B5: LAGTANG | C5: 46028 | D5: PURCHASING OFFICE | E5: OFFICE SUPPLIES | F5: ITM062 | G5: 3 | H5: PCS | I5: DOWNY | K5: 0 | L5: 0 | M5: MARLON LLOYD ROSALITA | N5: Approved | Q5: https://drive.google.com/file/d/1NxVOGYg83D1jEFEAUgDSPC5BM_ieYkFu/view?usp=drivesdk
A6: 46028.612 | B6: LAGTANG | C6: 46028 | D6: PURCHASING OFFICE | E6: OFFICE SUPPLIES | F6: ITM020 | G6: 5 | H6: PCS | I6: FLEXSTICK RED BALLPEN (0.5) | K6: 0 | L6: 0 | M6: MARLON LLOYD ROSALITA | N6: Approved | Q6: https://drive.google.com/file/d/1NxVOGYg83D1jEFEAUgDSPC5BM_ieYkFu/view?usp=drivesdk
A7: 46028.612 | B7: LAGTANG | C7: 46028 | D7: PURCHASING OFFICE | E7: OFFICE SUPPLIES | F7: ITM023 | G7: 1 | H7: PC | I7: HIGHLIGHTER | K7: 0 | L7: 0 | M7: MARLON LLOYD ROSALITA | N7: Approved | Q7: https://drive.google.com/file/d/1NxVOGYg83D1jEFEAUgDSPC5BM_ieYkFu/view?usp=drivesdk
A8: 46028.612 | B8: LAGTANG | C8: 46028 | D8: PURCHASING OFFICE | E8: OFFICE SUPPLIES | F8: ITM061 | G8: 3 | H8: PCS | I8: JOY | K8: 0 | L8: 0 | M8: MARLON LLOYD ROSALITA | N8: Approved | Q8: https://drive.google.com/file/d/1NxVOGYg83D1jEFEAUgDSPC5BM_ieYkFu/view?usp=drivesdk
A9: 46028.612 | B9: LAGTANG | C9: 46028 | D9: PURCHASING OFFICE | E9: OFFICE SUPPLIES | F9: ITM038 | G9: 1 | H9: PC | I9: MASKING TAPE | K9: 0 | L9: 0 | M9: MARLON LLOYD ROSALITA | N9: Approved | Q9: https://drive.google.com/file/d/1NxVOGYg83D1jEFEAUgDSPC5BM_ieYkFu/view?usp=drivesdk
A10: 46028.612 | B10: LAGTANG | C10: 46028 | D10: PURCHASING OFFICE | E10: OFFICE SUPPLIES | F10: ITM056 | G10: 6 | H10: PCS | I10: PRIDE SOAP POWDER | K10: 0 | L10: 0 | M10: MARLON LLOYD ROSALITA | N10: Approved | Q10: https://drive.google.com/file/d/1NxVOGYg83D1jEFEAUgDSPC5BM_ieYkFu/view?usp=drivesdk
A11: 46028.612 | B11: LAGTANG | C11: 46028 | D11: PURCHASING OFFICE | E11: OFFICE SUPPLIES | F11: ITM063 | G11: 1 | H11: PCS | I11: SAFEGUARD SOAP | K11: 0 | L11: 0 | M11: MARLON LLOYD ROSALITA | N11: Approved | Q11: https://drive.google.com/file/d/1NxVOGYg83D1jEFEAUgDSPC5BM_ieYkFu/view?usp=drivesdk
A12: 46028.612 | B12: LAGTANG | C12: 46028 | D12: PURCHASING OFFICE | E12: OFFICE SUPPLIES | F12: ITM064 | G12: 1 | H12: PADS | I12: STICKY NOTES 2X2 A02 | K12: 0 | L12: 0 | M12: MARLON LLOYD ROSALITA | N12: Approved | Q12: https://drive.google.com/file/d/1NxVOGYg83D1jEFEAUgDSPC5BM_ieYkFu/view?usp=drivesdk
A13: 46028.612 | B13: LAGTANG | C13: 46028 | D13: PURCHASING OFFICE | E13: OFFICE SUPPLIES | F13: ITM096 | G13: 1 | H13: ROLLS | I13: TRASH BAG (MEDIUM) | K13: 0 | L13: 0 | M13: MARLON LLOYD ROSALITA | N13: Approved | Q13: https://drive.google.com/file/d/1NxVOGYg83D1jEFEAUgDSPC5BM_ieYkFu/view?usp=drivesdk
... A21: 46037.716 | B21: LAGTANG | C21: 46037 | D21: PURCHASING OFFICE | E21: OFFICE SUPPLIES | F21: ITM015 | G21: 5 | H21: PCS | I21: WHITE FOLDER (SHORT) | K21: 0 | L21: 0 | M21: MARLON LLOYD ROSALITA | N21: Approved | Q21: https://drive.google.com/file/d/10HOVVzsHBl9a5f0sMLZrrVtKPHhLV_hz/view?usp=drivesdk
A22: 46043.646 | B22: LAGTANG | C22: 46044 | D22: PURCHASING OFFICE | E22: OFFICE SUPPLIES | G22: 1 | I22: sqd | K22: 0 | L22: 0 | M22: 1 | N22: not allowed | Q22: https://drive.google.com/file/d/1ZYysj228v6_ora3XiqlHp9QeMPQK5s-6/view?usp=drivesdk

Sheet BULACAO
A1: Timestamp | B1: Branch | C1: Date | D1: To | E1: Purpose | F1: ITEM_ID | G1: Qty | H1: Unit | I1: Description | J1: UPrice | K1: Amount | L1: Total | M1: Requested By | N1: Status | O1: Release Date | P1: Received By | Q1: PDF URL
A2: 46029.361 | B2: BULACAO | C2: 46029 | D2: PURCHASING OFFICE | E2: OFFICE SUPPLIES | F2: ITM087 | G2: 1 | H2: PC | I2: ALBATROSS | K2: 0 | L2: 0 | M2: IVY L HAMISTOSO | N2: Approved | Q2: https://drive.google.com/file/d/19Bw1ttWp273eOV1yO7Zc5BKzMJCFq_Oj/view?usp=drivesdk
A3: 46029.361 | B3: BULACAO | C3: 46029 | D3: PURCHASING OFFICE | E3: OFFICE SUPPLIES | F3: ITM056 | G3: 6 | H3: PCS | I3: PRIDE SOAP POWDER | K3: 0 | L3: 0 | M3: IVY L HAMISTOSO | N3: Approved | Q3: https://drive.google.com/file/d/19Bw1ttWp273eOV1yO7Zc5BKzMJCFq_Oj/view?usp=drivesdk
A4: 46029.361 | B4: BULACAO | C4: 46029 | D4: PURCHASING OFFICE | E4: OFFICE SUPPLIES | F4: ITM063 | G4: 1 | H4: PC | I4: SAFEGUARD SOAP | K4: 0 | L4: 0 | M4: IVY L HAMISTOSO | N4: Approved | Q4: https://drive.google.com/file/d/19Bw1ttWp273eOV1yO7Zc5BKzMJCFq_Oj/view?usp=drivesdk
